Workbook

Sheet GEV Quarterly
A1: GE Vernova Inc. (GEV): Quarterly Financials and Segment Data
A2: US$ millions except per-share, unit and percentage data. Blue = taken from the 10-Qs, black = formula. Grey = not in the filings provided. Yellow italic = estimate. Q4 = full year (10-K) less 9M. Notes at the bottom.
A4: Fiscal year | B4: 2024 | C4: 2024 | D4: 2024 | E4: 2024 | F4: 2025 | G4: 2025 | H4: 2025 | I4: 2025 | J4: 2026 | K4: 2026
A5: Quarter | B5: Q1'24 | C5: Q2'24 | D5: Q3'24 | E5: Q4'24 | F5: Q1'25 | G5: Q2'25 | H5: Q3'25 | I5: Q4'25 | J5: Q1'26 | K5: Q2'26
A6: Period end | B6: Mar 31, 2024 | C6: Jun 30, 2024 | D6: Sep 30, 2024 | E6: Dec 31, 2024 | F6: Mar 31, 2025 | G6: Jun 30, 2025 | H6: Sep 30, 2025 | I6: Dec 31, 2025 | J6: Mar 31, 2026 | K6: Jun 30, 2026
A7: Source for income statement, cash flow and segments (latest 10-Q reporting the quarter) | B7: 1Q25 10-Q | C7: 2Q25 10-Q | D7: 3Q25 10-Q | E7: FY24 10-K less 9M | F7: 1Q26 10-Q | G7: 2Q26 10-Q | H7: 3Q25 10-Q | I7: FY25 10-K less 9M | J7: 1Q26 10-Q | K7: 2Q26 10-Q
A9: INCOME STATEMENT
A10: Sales of equipment | B10: 3617 | C10: 4194 | D10: 5290 | E10: =E412-SUM(B10:D10) -> 5851 | F10: 4197 | G10: 4894 | H10: 5880 | I10: =I412-SUM(F10:H10) -> 5963 | J10: 5254 | K10: 6459
A11: Sales of services | B11: 3642 | C11: 4010 | D11: 3623 | E11: =E413-SUM(B11:D11) -> 4708 | F11: 3835 | G11: 4217 | H11: 4089 | I11: =I413-SUM(F11:H11) -> 4993 | J11: 4084 | K11: 4645
A12: Total revenues | B12: 7260 | C12: 8204 | D12: 8913 | E12: =E414-SUM(B12:D12) -> 10558 | F12: 8032 | G12: 9111 | H12: 9969 | I12: =I414-SUM(F12:H12) -> 10956 | J12: 9339 | K12: 11104
A13: Cost of equipment | B13: 3693 | C13: 3853 | D13: 5076 | E13: =E415-SUM(B13:D13) -> 5367 | F13: 3915 | G13: 4265 | H13: 5165 | I13: =I415-SUM(F13:H13) -> 5414 | J13: 4714 | K13: 5613
A14: Cost of services | B14: 2417 | C14: 2649 | D14: 2728 | E14: =E416-SUM(B14:D14) -> 3067 | F14: 2647 | G14: 3000 | H14: 2906 | I14: =I416-SUM(F14:H14) -> 3221 | J14: 2843 | K14: 3130
A15: Gross profit | B15: 1150 | C15: 1702 | D15: 1109 | E15: =E417-SUM(B15:D15) -> 2124 | F15: 1470 | G15: 1846 | H15: 1897 | I15: =I417-SUM(F15:H15) -> 2322 | J15: 1781 | K15: 2360
A16: Selling, general and administrative | B16: 1202 | C16: 938 | D16: 1226 | E16: =E418-SUM(B16:D16) -> 1266 | F16: 1188 | G16: 1185 | H16: 1221 | I16: =I418-SUM(F16:H16) -> 1355 | J16: 1298 | K16: 1372
A17: Research and development | B17: 237 | C17: 237 | D17: 243 | E17: =E419-SUM(B17:D17) -> 265 | F17: 239 | G17: 282 | H17: 310 | I17: =I419-SUM(F17:H17) -> 366 | J17: 304 | K17: 334
A18: Operating income (loss) | B18: -289 | C18: 527 | D18: -359 | E18: =E420-SUM(B18:D18) -> 592 | F18: 43 | G18: 378 | H18: 366 | I18: =I420-SUM(F18:H18) -> 601 | J18: 179 | K18: 653
A19: Interest and other financial income (charges), net | B19: -14 | C19: 60 | D19: 36 | E19: =E421-SUM(B19:D19) -> 38 | F19: 56 | G19: 42 | H19: 44 | I19: =I421-SUM(F19:H19) -> 44 | J19: 28 | K19: 73
A20: Non-operating benefit income | B20: 134 | C20: 134 | D20: 130 | E20: =E422-SUM(B20:D20) -> 138 | F20: 115 | G20: 110 | H20: 115 | I20: =I422-SUM(F20:H20) -> 119 | J20: 134 | K20: 119
A21: Other income (expense), net | B21: 73 | C21: 881 | D21: 71 | E21: =E423-SUM(B21:D21) -> 347 | F21: 119 | G21: 115 | H21: 221 | I21: =I423-SUM(F21:H21) -> 340 | J21: 4762 | K21: 80
... A26: Net income (loss) attributable to GE Vernova | B26: -130 | C26: 1294 | D26: -96 | E26: =E428-SUM(B26:D26) -> 484 | F26: 254 | G26: 514 | H26: 452 | I26: =I428-SUM(F26:H26) -> 3664 | J26: 4745 | K26: 668
A27: EPS, basic ($) | B27: -0.47 | C27: 4.72 | D27: -0.35 | E27: =E26/E29 -> 1.7472924 | F27: 0.92 | G27: 1.89 | H27: 1.66 | I27: =I26/I29 -> 13.620818 | J27: 17.65 | K27: 2.49
A28: EPS, diluted ($) | B28: -0.47 | C28: 4.65 | D28: -0.35 | E28: =E26/E30 -> 1.6982456 | F28: 0.91 | G28: 1.86 | H28: 1.64 | I28: =I26/I30 -> 13.372263 | J28: 17.44 | K28: 2.47
A29: Weighted-avg shares, basic (mm) | B29: 274 | C29: 274 | D29: 275 | E29: =4*E429-SUM(B29:D29) -> 277 | F29: 275 | G29: 272 | H29: 272 | I29: =4*I429-SUM(F29:H29) -> 269 | J29: 269 | K29: 268
A30: Weighted-avg shares, diluted (mm) | B30: 274 | C30: 278 | D30: 275 | E30: =4*E430-SUM(B30:D30) -> 285 | F30: 279 | G30: 276 | H30: 275 | I30: =4*I430-SUM(F30:H30) -> 274 | J30: 272 | K30: 270
A32: GROWTH AND MARGINS
A33: Total revenue growth, YoY | F33: =IF(AND(ISNUMBER(F12),ISNUMBER(B12),B12<>0),F12/B12-1,"") -> 0.10633609 | G33: =IF(AND(ISNUMBER(G12),ISNUMBER(C12),C12<>0),G12/C12-1,"") -> 0.11055583 | H33: =IF(AND(ISNUMBER(H12),ISNUMBER(D12),D12<>0),H12/D12-1,"") -> 0.11847863 | I33: =IF(AND(ISNUMBER(I12),ISNUMBER(E12),E12<>0),I12/E12-1,"") -> 0.037696533 | J33: =IF(AND(ISNUMBER(J12),ISNUMBER(F12),F12<>0),J12/F12-1,"") -> 0.1627241 | K33: =IF(AND(ISNUMBER(K12),ISNUMBER(G12),G12<>0),K12/G12-1,"") -> 0.21874657
A34: Equipment revenue growth, YoY | F34: =IF(AND(ISNUMBER(F10),ISNUMBER(B10),B10<>0),F10/B10-1,"") -> 0.16035388 | G34: =IF(AND(ISNUMBER(G10),ISNUMBER(C10),C10<>0),G10/C10-1,"") -> 0.1669051 | H34: =IF(AND(ISNUMBER(H10),ISNUMBER(D10),D10<>0),H10/D10-1,"") -> 0.11153119 | I34: =IF(AND(ISNUMBER(I10),ISNUMBER(E10),E10<>0),I10/E10-1,"") -> 0.019142027 | J34: =IF(AND(ISNUMBER(J10),ISNUMBER(F10),F10<>0),J10/F10-1,"") -> 0.25184656 | K34: =IF(AND(ISNUMBER(K10),ISNUMBER(G10),G10<>0),K10/G10-1,"") -> 0.31977932
A35: Services revenue growth, YoY | F35: =IF(AND(ISNUMBER(F11),ISNUMBER(B11),B11<>0),F11/B11-1,"") -> 0.052992861 | G35: =IF(AND(ISNUMBER(G11),ISNUMBER(C11),C11<>0),G11/C11-1,"") -> 0.051620948 | H35: =IF(AND(ISNUMBER(H11),ISNUMBER(D11),D11<>0),H11/D11-1,"") -> 0.12862269 | I35: =IF(AND(ISNUMBER(I11),ISNUMBER(E11),E11<>0),I11/E11-1,"") -> 0.060535259 | J35: =IF(AND(ISNUMBER(J11),ISNUMBER(F11),F11<>0),J11/F11-1,"") -> 0.064928292 | K35: =IF(AND(ISNUMBER(K11),ISNUMBER(G11),G11<>0),K11/G11-1,"") -> 0.10149395
A36: Gross margin | B36: =IF(AND(ISNUMBER(B15),ISNUMBER(B12),B12<>0),B15/B12,"") -> 0.1584022 | C36: =IF(AND(ISNUMBER(C15),ISNUMBER(C12),C12<>0),C15/C12,"") -> 0.20745978 | D36: =IF(AND(ISNUMBER(D15),ISNUMBER(D12),D12<>0),D15/D12,"") -> 0.124425 | E36: =IF(AND(ISNUMBER(E15),ISNUMBER(E12),E12<>0),E15/E12,"") -> 0.20117446 | F36: =IF(AND(ISNUMBER(F15),ISNUMBER(F12),F12<>0),F15/F12,"") -> 0.18301793 | G36: =IF(AND(ISNUMBER(G15),ISNUMBER(G12),G12<>0),G15/G12,"") -> 0.20261223 | H36: =IF(AND(ISNUMBER(H15),ISNUMBER(H12),H12<>0),H15/H12,"") -> 0.1902899 | I36: =IF(AND(ISNUMBER(I15),ISNUMBER(I12),I12<>0),I15/I12,"") -> 0.21193866 | ... K36: =IF(AND(ISNUMBER(K15),ISNUMBER(K12),K12<>0),K15/K12,"") -> 0.21253602
A37: Equipment gross margin | B37: =IF(ISNUMBER(B10),(B10-B13)/B10,"") -> -0.021011888 | C37: =IF(ISNUMBER(C10),(C10-C13)/C10,"") -> 0.081306629 | D37: =IF(ISNUMBER(D10),(D10-D13)/D10,"") -> 0.040453686 | E37: =IF(ISNUMBER(E10),(E10-E13)/E10,"") -> 0.082720902 | F37: =IF(ISNUMBER(F10),(F10-F13)/F10,"") -> 0.067190851 | G37: =IF(ISNUMBER(G10),(G10-G13)/G10,"") -> 0.12852472 | H37: =IF(ISNUMBER(H10),(H10-H13)/H10,"") -> 0.12159864 | I37: =IF(ISNUMBER(I10),(I10-I13)/I10,"") -> 0.092067751 | ... K37: =IF(ISNUMBER(K10),(K10-K13)/K10,"") -> 0.13098003
A38: Services gross margin | B38: =IF(ISNUMBER(B11),(B11-B14)/B11,"") -> 0.33635365 | C38: =IF(ISNUMBER(C11),(C11-C14)/C11,"") -> 0.3394015 | D38: =IF(ISNUMBER(D11),(D11-D14)/D11,"") -> 0.24703285 | E38: =IF(ISNUMBER(E11),(E11-E14)/E11,"") -> 0.34855565 | F38: =IF(ISNUMBER(F11),(F11-F14)/F11,"") -> 0.30977836 | G38: =IF(ISNUMBER(G11),(G11-G14)/G11,"") -> 0.28859379 | H38: =IF(ISNUMBER(H11),(H11-H14)/H11,"") -> 0.28931279 | I38: =IF(ISNUMBER(I11),(I11-I14)/I11,"") -> 0.35489686 | ... K38: =IF(ISNUMBER(K11),(K11-K14)/K11,"") -> 0.32615716
A39: SG&A as % of revenue | B39: =IF(AND(ISNUMBER(B16),ISNUMBER(B12),B12<>0),B16/B12,"") -> 0.16556474 | C39: =IF(AND(ISNUMBER(C16),ISNUMBER(C12),C12<>0),C16/C12,"") -> 0.11433447 | D39: =IF(AND(ISNUMBER(D16),ISNUMBER(D12),D12<>0),D16/D12,"") -> 0.13755189 | E39: =IF(AND(ISNUMBER(E16),ISNUMBER(E12),E12<>0),E16/E12,"") -> 0.11990907 | F39: =IF(AND(ISNUMBER(F16),ISNUMBER(F12),F12<>0),F16/F12,"") -> 0.14790837 | G39: =IF(AND(ISNUMBER(G16),ISNUMBER(G12),G12<>0),G16/G12,"") -> 0.13006256 | H39: =IF(AND(ISNUMBER(H16),ISNUMBER(H12),H12<>0),H16/H12,"") -> 0.12247969 | I39: =IF(AND(ISNUMBER(I16),ISNUMBER(I12),I12<>0),I16/I12,"") -> 0.12367652 | ... K39: =IF(AND(ISNUMBER(K16),ISNUMBER(K12),K12<>0),K16/K12,"") -> 0.12355908
A40: R&D as % of revenue | B40: =IF(AND(ISNUMBER(B17),ISNUMBER(B12),B12<>0),B17/B12,"") -> 0.032644628 | C40: =IF(AND(ISNUMBER(C17),ISNUMBER(C12),C12<>0),C17/C12,"") -> 0.028888347 | D40: =IF(AND(ISNUMBER(D17),ISNUMBER(D12),D12<>0),D17/D12,"") -> 0.027263548 | E40: =IF(AND(ISNUMBER(E17),ISNUMBER(E12),E12<>0),E17/E12,"") -> 0.025099451 | F40: =IF(AND(ISNUMBER(F17),ISNUMBER(F12),F12<>0),F17/F12,"") -> 0.029755976 | G40: =IF(AND(ISNUMBER(G17),ISNUMBER(G12),G12<>0),G17/G12,"") -> 0.030951597 | H40: =IF(AND(ISNUMBER(H17),ISNUMBER(H12),H12<>0),H17/H12,"") -> 0.031096399 | I40: =IF(AND(ISNUMBER(I17),ISNUMBER(I12),I12<>0),I17/I12,"") -> 0.033406353 | ... K40: =IF(AND(ISNUMBER(K17),ISNUMBER(K12),K12<>0),K17/K12,"") -> 0.030079251
A41: Operating margin | B41: =IF(AND(ISNUMBER(B18),ISNUMBER(B12),B12<>0),B18/B12,"") -> -0.039807163 | C41: =IF(AND(ISNUMBER(C18),ISNUMBER(C12),C12<>0),C18/C12,"") -> 0.064236958 | D41: =IF(AND(ISNUMBER(D18),ISNUMBER(D12),D12<>0),D18/D12,"") -> -0.040278245 | E41: =IF(AND(ISNUMBER(E18),ISNUMBER(E12),E12<>0),E18/E12,"") -> 0.056071226 | F41: =IF(AND(ISNUMBER(F18),ISNUMBER(F12),F12<>0),F18/F12,"") -> 0.0053535857 | G41: =IF(AND(ISNUMBER(G18),ISNUMBER(G12),G12<>0),G18/G12,"") -> 0.041488311 | H41: =IF(AND(ISNUMBER(H18),ISNUMBER(H12),H12<>0),H18/H12,"") -> 0.036713813 | I41: =IF(AND(ISNUMBER(I18),ISNUMBER(I12),I12<>0),I18/I12,"") -> 0.054855787 | ... K41: =IF(AND(ISNUMBER(K18),ISNUMBER(K12),K12<>0),K18/K12,"") -> 0.058807637
A42: Pre-tax income excl. other income (expense) | B42: =B18+B19+B20 -> -169 | C42: =C18+C19+C20 -> 721 | D42: =D18+D19+D20 -> -193 | E42: =E18+E19+E20 -> 768 | F42: =F18+F19+F20 -> 214 | G42: =G18+G19+G20 -> 530 | H42: =H18+H19+H20 -> 525 | I42: =I18+I19+I20 -> 764 | ... K42: =K18+K19+K20 -> 845
A43: Net margin (attributable to GE Vernova) | B43: =IF(AND(ISNUMBER(B26),ISNUMBER(B12),B12<>0),B26/B12,"") -> -0.017906336 | C43: =IF(AND(ISNUMBER(C26),ISNUMBER(C12),C12<>0),C26/C12,"") -> 0.15772794 | D43: =IF(AND(ISNUMBER(D26),ISNUMBER(D12),D12<>0),D26/D12,"") -> -0.010770784 | E43: =IF(AND(ISNUMBER(E26),ISNUMBER(E12),E12<>0),E26/E12,"") -> 0.045842016 | F43: =IF(AND(ISNUMBER(F26),ISNUMBER(F12),F12<>0),F26/F12,"") -> 0.031623506 | G43: =IF(AND(ISNUMBER(G26),ISNUMBER(G12),G12<>0),G26/G12,"") -> 0.056415322 | H43: =IF(AND(ISNUMBER(H26),ISNUMBER(H12),H12<>0),H26/H12,"") -> 0.045340556 | I43: =IF(AND(ISNUMBER(I26),ISNUMBER(I12),I12<>0),I26/I12,"") -> 0.33442862 | ... K43: =IF(AND(ISNUMBER(K26),ISNUMBER(K12),K12<>0),K26/K12,"") -> 0.060158501
A44: Effective tax rate (blank when pre-tax income is negative) | B44: =IF(AND(ISNUMBER(B22),B22>0),B23/B22,"") | C44: =IF(AND(ISNUMBER(C22),C22>0),C23/C22,"") -> 0.20099875 | D44: =IF(AND(ISNUMBER(D22),D22>0),D23/D22,"") | E44: =IF(AND(ISNUMBER(E22),E22>0),E23/E22,"") -> 0.56552962 | F44: =IF(AND(ISNUMBER(F22),F22>0),F23/F22,"") -> 0.20481928 | G44: =IF(AND(ISNUMBER(G22),G22>0),G23/G22,"") -> 0.2372093 | H44: =IF(AND(ISNUMBER(H22),H22>0),H23/H22,"") -> 0.39276139 | I44: =IF(AND(ISNUMBER(I22),I22>0),I23/I22,"") -> -2.321267 | ... K44: =IF(AND(ISNUMBER(K22),K22>0),K23/K22,"") -> 0.29837838
A45: Adjusted EBITDA margin (company-defined) | B45: =IF(ISNUMBER(B57),B57/B12,"") -> 0.026033058 | C45: =IF(ISNUMBER(C57),C57/C12,"") -> 0.063871282 | D45: =IF(ISNUMBER(D57),D57/D12,"") -> 0.027263548 | E45: =IF(ISNUMBER(E57),E57/E12,"") -> 0.10219739 | F45: =IF(ISNUMBER(F57),F57/F12,"") -> 0.05689741 | G45: =IF(ISNUMBER(G57),G57/G12,"") -> 0.084513226 | H45: =IF(ISNUMBER(H57),H57/H12,"") -> 0.081352192 | I45: =IF(ISNUMBER(I57),I57/I12,"") -> 0.10569551 | ... K45: =IF(ISNUMBER(K57),K57/K12,"") -> 0.11257205
A47: ADJUSTED EBITDA BRIDGE (company non-GAAP, three months)
A48: Net income (loss), GAAP | B48: =B293 -> -106 | C48: =C293 -> 1280 | D48: =D293 -> -99 | E48: =E293 -> 484 | F48: =F293 -> 264 | G48: =G293 -> 492 | H48: =H293 -> 453 | I48: =I293 -> 3670 | ... K48: =K293 -> 648
A49: Restructuring and other charges | B49: 148 | C49: 62 | D49: 209 | E49: =E459-SUM(B49:D49) -> 7 | F49: 67 | G49: 42 | H49: 83 | I49: =I459-SUM(F49:H49) -> 85 | J49: 94 | K49: 9
A50: (Gains) losses on purchases and sales of business interests | B50: 5 | C50: -847 | D50: 0 | E50: =E460-SUM(B50:D50) -> -182 | F50: -19 | G50: 0 | H50: -113 | I50: =I460-SUM(F50:H50) -> -149 | J50: -4494 | K50: 48
A51: Separation costs (benefits) | B51: 0 | C51: -91 | D51: 27 | E51: =E461-SUM(B51:D51) -> 55 | F51: 45 | G51: 34 | H51: 43 | I51: =I461-SUM(F51:H51) -> 58 | J51: 23 | K51: 38
A52: Arbitration refund | B52: 0 | C52: -254 | D52: 0 | E52: =E462-SUM(B52:D52) -> 0 | F52: 0 | G52: 0 | H52: 0 | I52: =I462-SUM(F52:H52) -> 0 | J52: 0 | K52: 0
A53: Non-operating benefit income | B53: -134 | C53: -134 | D53: -130 | E53: =E463-SUM(B53:D53) -> -138 | F53: -115 | G53: -110 | H53: -115 | I53: =I463-SUM(F53:H53) -> -119 | J53: -134 | K53: -119
A54: Depreciation and amortization (excl. amounts in restructuring) | B54: 209 | C54: 237 | D54: 289 | E54: =E464-SUM(B54:D54) -> 273 | F54: 203 | G54: 202 | H54: 212 | I54: =I464-SUM(F54:H54) -> 230 | J54: 341 | K54: 418
A55: Interest and other financial (income) charges, net | B55: 4 | C55: -61 | D55: -35 | E55: =E465-SUM(B55:D55) -> -38 | F55: -55 | G55: -41 | H55: -44 | I55: =I465-SUM(F55:H55) -> -45 | J55: -27 | K55: -73
A56: Provision (benefit) for income taxes (excl. Financial Services) | B56: 64 | C56: 333 | D56: -17 | E56: =E466-SUM(B56:D56) -> 615 | F56: 67 | G56: 151 | H56: 292 | I56: =I466-SUM(F56:H56) -> -2572 | J56: 344 | K56: 279
A57: Adjusted EBITDA (as reported) | B57: 189 | C57: 524 | D57: 243 | E57: =E467-SUM(B57:D57) -> 1079 | F57: 457 | G57: 770 | H57: 811 | I57: =I467-SUM(F57:H57) -> 1158 | J57: 896 | K57: 1250
A58: Check: bridge sum less reported (rounding only) | B58: =SUM(B48:B56)-B57 -> 1 | C58: =SUM(C48:C56)-C57 -> 1 | D58: =SUM(D48:D56)-D57 -> 1 | E58: =SUM(E48:E56)-E57 -> -3 | F58: =SUM(F48:F56)-F57 -> 0 | G58: =SUM(G48:G56)-G57 -> 0 | H58: =SUM(H48:H56)-H57 -> 0 | I58: =SUM(I48:I56)-I57 -> 0 | ... K58: =SUM(K48:K56)-K57 -> -2
A60: ORGANIC GROWTH (company non-GAAP, excludes acquisitions, disposals and FX)
A61: Each quarter is taken from its own 10-Q. Segment lines follow the segment structure in that filing (legacy through Q3'25, current from Q1'26).
A62: Total revenue: current period | B62: 7169 | C62: 8087 | D62: 8921 | F62: 8161 | G62: 9044 | H62: 9826 | J62: 8587 | K62: 10149
A63: Total revenue: prior-year base | B63: 6829 | C63: 7938 | D63: 8100 | F63: 7077 | G63: 8074 | H63: 8902 | J63: 7997 | K63: 9068
A64: Total revenue: organic growth | B64: =IF(AND(ISNUMBER(B62),B63<>0),B62/B63-1,"") -> 0.04978767 | C64: =IF(AND(ISNUMBER(C62),C63<>0),C62/C63-1,"") -> 0.018770471 | D64: =IF(AND(ISNUMBER(D62),D63<>0),D62/D63-1,"") -> 0.10135802 | F64: =IF(AND(ISNUMBER(F62),F63<>0),F62/F63-1,"") -> 0.15317225 | G64: =IF(AND(ISNUMBER(G62),G63<>0),G62/G63-1,"") -> 0.12013872 | H64: =IF(AND(ISNUMBER(H62),H63<>0),H62/H63-1,"") -> 0.1037969 | J64: =IF(AND(ISNUMBER(J62),J63<>0),J62/J63-1,"") -> 0.073777667 | K64: =IF(AND(ISNUMBER(K62),K63<>0),K62/K63-1,"") -> 0.11921041
A65: Equipment revenue: current period | B65: 3554 | C65: 4142 | D65: 5296 | F65: 4296 | G65: 4858 | H65: 5792 | J65: 4636 | K65: 5570
A66: Equipment revenue: prior-year base | B66: 3497 | C66: 4303 | D66: 4797 | F66: 3512 | G66: 4130 | H66: 5282 | J66: 4203 | K66: 4900
A67: Equipment revenue: organic growth | B67: =IF(AND(ISNUMBER(B65),B66<>0),B65/B66-1,"") -> 0.016299685 | C67: =IF(AND(ISNUMBER(C65),C66<>0),C65/C66-1,"") -> -0.037415756 | D67: =IF(AND(ISNUMBER(D65),D66<>0),D65/D66-1,"") -> 0.10402335 | F67: =IF(AND(ISNUMBER(F65),F66<>0),F65/F66-1,"") -> 0.22323462 | G67: =IF(AND(ISNUMBER(G65),G66<>0),G65/G66-1,"") -> 0.17627119 | H67: =IF(AND(ISNUMBER(H65),H66<>0),H65/H66-1,"") -> 0.096554335 | J67: =IF(AND(ISNUMBER(J65),J66<>0),J65/J66-1,"") -> 0.10302165 | K67: =IF(AND(ISNUMBER(K65),K66<>0),K65/K66-1,"") -> 0.13673469
A68: Services revenue: current period | B68: 3615 | C68: 3946 | D68: 3625 | F68: 3865 | G68: 4186 | H68: 4034 | J68: 3950 | K68: 4579
A69: Services revenue: prior-year base | B69: 3332 | C69: 3636 | D69: 3303 | F69: 3565 | G69: 3945 | H69: 3620 | J69: 3794 | K69: 4167
A70: Services revenue: organic growth | B70: =IF(AND(ISNUMBER(B68),B69<>0),B68/B69-1,"") -> 0.084933974 | C70: =IF(AND(ISNUMBER(C68),C69<>0),C68/C69-1,"") -> 0.085258526 | D70: =IF(AND(ISNUMBER(D68),D69<>0),D68/D69-1,"") -> 0.097487133 | F70: =IF(AND(ISNUMBER(F68),F69<>0),F68/F69-1,"") -> 0.084151473 | G70: =IF(AND(ISNUMBER(G68),G69<>0),G68/G69-1,"") -> 0.061089987 | H70: =IF(AND(ISNUMBER(H68),H69<>0),H68/H69-1,"") -> 0.11436464 | J70: =IF(AND(ISNUMBER(J68),J69<>0),J68/J69-1,"") -> 0.041117554 | K70: =IF(AND(ISNUMBER(K68),K69<>0),K68/K69-1,"") -> 0.09887209
A71: Power revenue: current period | B71: 3981 | C71: 4324 | D71: 4210 | F71: 4449 | G71: 4731 | H71: 4789 | J71: 4908 | K71: 5444
A72: Power revenue: prior-year base | B72: 3820 | C72: 3946 | D72: 3721 | F72: 3851 | G72: 4325 | H72: 4204 | J72: 4446 | K72: 4781
A73: Power revenue: organic growth | B73: =IF(AND(ISNUMBER(B71),B72<>0),B71/B72-1,"") -> 0.042146597 | C73: =IF(AND(ISNUMBER(C71),C72<>0),C71/C72-1,"") -> 0.095793208 | D73: =IF(AND(ISNUMBER(D71),D72<>0),D71/D72-1,"") -> 0.13141629 | F73: =IF(AND(ISNUMBER(F71),F72<>0),F71/F72-1,"") -> 0.15528434 | G73: =IF(AND(ISNUMBER(G71),G72<>0),G71/G72-1,"") -> 0.093872832 | H73: =IF(AND(ISNUMBER(H71),H72<>0),H71/H72-1,"") -> 0.13915319 | J73: =IF(AND(ISNUMBER(J71),J72<>0),J71/J72-1,"") -> 0.10391363 | K73: =IF(AND(ISNUMBER(K71),K72<>0),K71/K72-1,"") -> 0.13867392
A74: Electrification revenue: current period | B74: 1617 | C74: 1787 | D74: 1932 | F74: 1945 | G74: 2153 | H74: 2537 | J74: 2318 | K74: 2727
A75: Electrification revenue: prior-year base | B75: 1333 | C75: 1506 | D75: 1564 | F75: 1645 | G75: 1788 | H75: 1922 | J75: 1800 | K75: 2106
A76: Electrification revenue: organic growth | B76: =IF(AND(ISNUMBER(B74),B75<>0),B74/B75-1,"") -> 0.21305326 | C76: =IF(AND(ISNUMBER(C74),C75<>0),C74/C75-1,"") -> 0.18658699 | D76: =IF(AND(ISNUMBER(D74),D75<>0),D74/D75-1,"") -> 0.23529412 | F76: =IF(AND(ISNUMBER(F74),F75<>0),F74/F75-1,"") -> 0.18237082 | G76: =IF(AND(ISNUMBER(G74),G75<>0),G74/G75-1,"") -> 0.2041387 | H76: =IF(AND(ISNUMBER(H74),H75<>0),H74/H75-1,"") -> 0.31997919 | J76: =IF(AND(ISNUMBER(J74),J75<>0),J74/J75-1,"") -> 0.28777778 | K76: =IF(AND(ISNUMBER(K74),K75<>0),K74/K75-1,"") -> 0.29487179
A77: Wind revenue: current period | B77: 1636 | C77: 2079 | D77: 2892 | F77: 1886 | G77: 2252 | H77: 2619 | J77: 1385 | K77: 2014
A78: Wind revenue: prior-year base | B78: 1758 | C78: 2604 | D78: 2919 | F78: 1646 | G78: 2064 | H78: 2888 | J78: 1857 | K78: 2261
A79: Wind revenue: organic growth | B79: =IF(AND(ISNUMBER(B77),B78<>0),B77/B78-1,"") -> -0.069397042 | C79: =IF(AND(ISNUMBER(C77),C78<>0),C77/C78-1,"") -> -0.2016129 | D79: =IF(AND(ISNUMBER(D77),D78<>0),D77/D78-1,"") -> -0.0092497431 | F79: =IF(AND(ISNUMBER(F77),F78<>0),F77/F78-1,"") -> 0.14580802 | G79: =IF(AND(ISNUMBER(G77),G78<>0),G77/G78-1,"") -> 0.091085271 | H79: =IF(AND(ISNUMBER(H77),H78<>0),H77/H78-1,"") -> -0.093144044 | J79: =IF(AND(ISNUMBER(J77),J78<>0),J77/J78-1,"") -> -0.2541734 | K79: =IF(AND(ISNUMBER(K77),K78<>0),K77/K78-1,"") -> -0.1092437
A80: Adjusted organic EBITDA | B80: 222 | C80: 584 | D80: 231 | F80: 439 | G80: 737 | H80: 833 | J80: 778 | K80: 1139
A81: Adjusted organic EBITDA margin (as reported, %) | B81: 0.031 | C81: 0.072 | D81: 0.026 | F81: 0.054 | G81: 0.081 | H81: 0.085 | J81: 0.091 | K81: 0.112
A83: SEGMENTS: CONTINUOUS SERIES ON THE CURRENT STRUCTURE (use this block for modelling)
A84: Q1'25, Q2'25, Q1'26, Q2'26 are reported on the current structure. Q1'24 to Q4'24, Q3'25 and Q4'25 were only filed on the legacy structure, so they are ESTIMATES (yellow italic): legacy figure plus the average recast difference (current less legacy) seen in Q1'25 and Q2'25.
A85: Basis | B85: Estimate | C85: Estimate | D85: Estimate | E85: Estimate | F85: Reported | G85: Reported | H85: Estimate | I85: Estimate | J85: Reported | K85: Reported
A86: Segment revenue (includes intersegment sales)
A87: Power | B87: =B109+AVERAGE(F161-F109,G161-G109) -> 4061.5 | C87: =C109+AVERAGE(F161-F109,G161-G109) -> 4481.5 | D87: =D109+AVERAGE(F161-F109,G161-G109) -> 4232.5 | E87: =E109+AVERAGE(F161-F109,G161-G109) -> 5457.5 | F87: =F161 -> 4449 | G87: =G161 -> 4785 | H87: =H109+AVERAGE(F161-F109,G161-G109) -> 4864.5 | I87: =I109+AVERAGE(F161-F109,G161-G109) -> 5774.5 | J87: =J161 -> 4971 | K87: =K161 -> 5477
A88: Electrification | B88: =B110+AVERAGE(F162-F110,G162-G110) -> 1612 | C88: =C110+AVERAGE(F162-F110,G162-G110) -> 1751 | D88: =D110+AVERAGE(F162-F110,G162-G110) -> 1889 | E88: =E110+AVERAGE(F162-F110,G162-G110) -> 2142 | F88: =F162 -> 1840 | G88: =G162 -> 2162 | H88: =H110+AVERAGE(F162-F110,G162-G110) -> 2562 | I88: =I110+AVERAGE(F162-F110,G162-G110) -> 2922 | J88: =J162 -> 2959 | K88: =K162 -> 3637
A89: Wind | B89: =B111+AVERAGE(F163-F111,G163-G111) -> 1639 | C89: =C111+AVERAGE(F163-F111,G163-G111) -> 2062 | D89: =D111+AVERAGE(F163-F111,G163-G111) -> 2891 | E89: =E111+AVERAGE(F163-F111,G163-G111) -> 3109 | F89: =F163 -> 1850 | G89: =G163 -> 2245 | H89: =H111+AVERAGE(F163-F111,G163-G111) -> 2647 | I89: =I111+AVERAGE(F163-F111,G163-G111) -> 2368 | J89: =J163 -> 1432 | K89: =K163 -> 2026
A90: Eliminations and other | B90: =B12-B87-B88-B89 -> -52.5 | C90: =C12-C87-C88-C89 -> -90.5 | D90: =D12-D87-D88-D89 -> -99.5 | E90: =E12-E87-E88-E89 -> -150.5 | F90: =F164 -> -107 | G90: =G164 -> -80 | H90: =H12-H87-H88-H89 -> -104.5 | I90: =I12-I87-I88-I89 -> -108.5 | J90: =J164 -> -25 | K90: =K164 -> -37
A91: Total revenues (income statement) | B91: =B12 -> 7260 | C91: =C12 -> 8204 | D91: =D12 -> 8913 | E91: =E12 -> 10558 | F91: =F12 -> 8032 | G91: =G12 -> 9111 | H91: =H12 -> 9969 | I91: =I12 -> 10956 | ... K91: =K12 -> 11104
A92: Power revenue growth, YoY | F92: =IF(AND(ISNUMBER(F87),ISNUMBER(B87),B87<>0),F87/B87-1,"") -> 0.0954081 | G92: =IF(AND(ISNUMBER(G87),ISNUMBER(C87),C87<>0),G87/C87-1,"") -> 0.067722861 | H92: =IF(AND(ISNUMBER(H87),ISNUMBER(D87),D87<>0),H87/D87-1,"") -> 0.14932073 | I92: =IF(AND(ISNUMBER(I87),ISNUMBER(E87),E87<>0),I87/E87-1,"") -> 0.058085204 | J92: =IF(AND(ISNUMBER(J87),ISNUMBER(F87),F87<>0),J87/F87-1,"") -> 0.11732974 | K92: =IF(AND(ISNUMBER(K87),ISNUMBER(G87),G87<>0),K87/G87-1,"") -> 0.1446186
A93: Electrification revenue growth, YoY | F93: =IF(AND(ISNUMBER(F88),ISNUMBER(B88),B88<>0),F88/B88-1,"") -> 0.14143921 | G93: =IF(AND(ISNUMBER(G88),ISNUMBER(C88),C88<>0),G88/C88-1,"") -> 0.23472302 | H93: =IF(AND(ISNUMBER(H88),ISNUMBER(D88),D88<>0),H88/D88-1,"") -> 0.35627316 | I93: =IF(AND(ISNUMBER(I88),ISNUMBER(E88),E88<>0),I88/E88-1,"") -> 0.36414566 | J93: =IF(AND(ISNUMBER(J88),ISNUMBER(F88),F88<>0),J88/F88-1,"") -> 0.60815217 | K93: =IF(AND(ISNUMBER(K88),ISNUMBER(G88),G88<>0),K88/G88-1,"") -> 0.68223867
A94: Wind revenue growth, YoY | F94: =IF(AND(ISNUMBER(F89),ISNUMBER(B89),B89<>0),F89/B89-1,"") -> 0.12873703 | G94: =IF(AND(ISNUMBER(G89),ISNUMBER(C89),C89<>0),G89/C89-1,"") -> 0.088748788 | H94: =IF(AND(ISNUMBER(H89),ISNUMBER(D89),D89<>0),H89/D89-1,"") -> -0.084399862 | I94: =IF(AND(ISNUMBER(I89),ISNUMBER(E89),E89<>0),I89/E89-1,"") -> -0.2383403 | J94: =IF(AND(ISNUMBER(J89),ISNUMBER(F89),F89<>0),J89/F89-1,"") -> -0.22594595 | K94: =IF(AND(ISNUMBER(K89),ISNUMBER(G89),G89<>0),K89/G89-1,"") -> -0.097550111
A95: Segment EBITDA
A96: Power | B96: =B119+AVERAGE(F171-F119,G171-G119) -> 353 | C96: =C119+AVERAGE(F171-F119,G171-G119) -> 621 | D96: =D119+AVERAGE(F171-F119,G171-G119) -> 507 | E96: =E119+AVERAGE(F171-F119,G171-G119) -> 819 | F96: =F171 -> 517 | G96: =G171 -> 785 | H96: =H119+AVERAGE(F171-F119,G171-G119) -> 653 | I96: =I119+AVERAGE(F171-F119,G171-G119) -> 979 | J96: =J171 -> 811 | K96: =K171 -> 1031
A97: Electrification | B97: =B120+AVERAGE(F172-F120,G172-G120) -> 57.5 | C97: =C120+AVERAGE(F172-F120,G172-G120) -> 120.5 | D97: =D120+AVERAGE(F172-F120,G172-G120) -> 192.5 | E97: =E120+AVERAGE(F172-F120,G172-G120) -> 274.5 | F97: =F172 -> 205 | G97: =G172 -> 314 | H97: =H120+AVERAGE(F172-F120,G172-G120) -> 384.5 | I97: =I120+AVERAGE(F172-F120,G172-G120) -> 495.5 | J97: =J172 -> 528 | K97: =K172 -> 671
A98: Wind | B98: =B121+AVERAGE(F173-F121,G173-G121) -> -173 | C98: =C121+AVERAGE(F173-F121,G173-G121) -> -117 | D98: =D121+AVERAGE(F173-F121,G173-G121) -> -317 | E98: =E121+AVERAGE(F173-F121,G173-G121) -> 19 | F98: =F173 -> -146 | G98: =G173 -> -165 | H98: =H121+AVERAGE(F173-F121,G173-G121) -> -61 | I98: =I121+AVERAGE(F173-F121,G173-G121) -> -226 | J98: =J173 -> -382 | K98: =K173 -> -275
A99: Corporate and other | B99: =B122+AVERAGE(F174-F122,G174-G122) -> -49 | C99: =C122+AVERAGE(F174-F122,G174-G122) -> -101 | D99: =D122+AVERAGE(F174-F122,G174-G122) -> -140 | E99: =E122+AVERAGE(F174-F122,G174-G122) -> -33 | F99: =F174 -> -119 | G99: =G174 -> -164 | H99: =H122+AVERAGE(F174-F122,G174-G122) -> -166 | I99: =I122+AVERAGE(F174-F122,G174-G122) -> -92 | J99: =J174 -> -62 | K99: =K174 -> -177
A100: Adjusted EBITDA (as reported) | B100: =B57 -> 189 | C100: =C57 -> 524 | D100: =D57 -> 243 | E100: =E57 -> 1079 | F100: =F57 -> 457 | G100: =G57 -> 770 | H100: =H57 -> 811 | I100: =I57 -> 1158 | ... K100: =K57 -> 1250
A101: Check: segment EBITDA plus corporate less Adjusted EBITDA (rounding only) | B101: =B96+B97+B98+B99-B100 -> -0.5 | C101: =C96+C97+C98+C99-C100 -> -0.5 | D101: =D96+D97+D98+D99-D100 -> -0.5 | E101: =E96+E97+E98+E99-E100 -> 0.5 | F101: =F96+F97+F98+F99-F100 -> 0 | G101: =G96+G97+G98+G99-G100 -> 0 | H101: =H96+H97+H98+H99-H100 -> -0.5 | I101: =I96+I97+I98+I99-I100 -> -1.5 | ... K101: =K96+K97+K98+K99-K100 -> 0
A102: Power margin | B102: =B96/B87 -> 0.086913702 | C102: =C96/C87 -> 0.13856968 | D102: =D96/D87 -> 0.11978736 | E102: =E96/E87 -> 0.15006871 | F102: =F96/F87 -> 0.11620589 | G102: =G96/G87 -> 0.16405434 | H102: =H96/H87 -> 0.13423785 | I102: =I96/I87 -> 0.16953849 | ... K102: =K96/K87 -> 0.18824174
A103: Electrification margin | B103: =B97/B88 -> 0.035669975 | C103: =C97/C88 -> 0.068817818 | D103: =D97/D88 -> 0.10190577 | E103: =E97/E88 -> 0.12815126 | F103: =F97/F88 -> 0.11141304 | G103: =G97/G88 -> 0.14523589 | H103: =H97/H88 -> 0.15007806 | I103: =I97/I88 -> 0.16957563 | ... K103: =K97/K88 -> 0.18449271
A104: Wind margin | B104: =B98/B89 -> -0.10555217 | C104: =C98/C89 -> -0.056741028 | D104: =D98/D89 -> -0.10965064 | E104: =E98/E89 -> 0.0061112898 | F104: =F98/F89 -> -0.078918919 | G104: =G98/G89 -> -0.073496659 | H104: =H98/H89 -> -0.023044957 | I104: =I98/I89 -> -0.095439189 | ... K104: =K98/K89 -> -0.13573544
A106: SEGMENTS: LEGACY STRUCTURE (as reported through Q3'25)
A107: Power = Gas, Nuclear, Hydro, Steam. Electrification = Grid Solutions, Power Conversion & Storage, Electrification Software. Wind = Onshore, Offshore, LM Wind Power. Q1'24 to Q3'24 are prior-year columns in the 2025 10-Qs.
A108: Segment revenue (includes intersegment sales)
A109: Power | B109: 4035 | C109: 4455 | D109: 4206 | E109: =E432-SUM(B109:D109) -> 5431 | F109: 4423 | G109: 4758 | H109: 4838 | I109: =I432-SUM(F109:H109) -> 5748
A110: Electrification | B110: 1651 | C110: 1790 | D110: 1928 | E110: =E433-SUM(B110:D110) -> 2181 | F110: 1879 | G110: 2201 | H110: 2601 | I110: =I433-SUM(F110:H110) -> 2961
A111: Wind | B111: 1639 | C111: 2062 | D111: 2891 | E111: =E434-SUM(B111:D111) -> 3109 | F111: 1850 | G111: 2245 | H111: 2647 | I111: =I434-SUM(F111:H111) -> 2368
...

Sheet Sheet1
A1: GEV Revenue Segmentation
A2: We assume that the percent of segmentation is delegated uniformaly throughout the annualized year.
B3: Historical | M3: Projected
B4: Fiscal year | C4: 2024 | D4: 2024 | E4: 2024 | F4: 2024 | G4: 2025 | H4: 2025 | I4: 2025 | J4: 2025 | K4: 2026 | L4: 2026 | M4: 2026 | N4: 2026
B5: Quarter | C5: Q1'24 | D5: Q2'24 | E5: Q3'24 | F5: Q4'24 | G5: Q1'25 | H5: Q2'25 | I5: Q3'25 | J5: Q4'25 | K5: Q1'26 | L5: Q2'26 | M5: Q3'26 | N5: Q4'26
B6: Segment basis | C6: Legacy | D6: Legacy | E6: Legacy | F6: Legacy | G6: Legacy | H6: Legacy | I6: Legacy | J6: Legacy | K6: Current | L6: Current
B8: Segment Revenue Summary (US$ millions)
B9: Wind | C9: =C37 -> 1639 | D9: =D37 -> 2062 | E9: =E37 -> 2891 | F9: =F37 -> 3109 | G9: =G37 -> 1850 | H9: =H37 -> 2245 | I9: =I37 -> 2647 | J9: =J37 -> 2368 | ... L9: =L37 -> 2026
B10: Electrification | C10: =C74 -> 1651 | D10: =D74 -> 1790 | E10: =E74 -> 1928 | F10: =F74 -> 2181 | G10: =G74 -> 1879 | H10: =H74 -> 2201 | I10: =I74 -> 2601 | J10: =J74 -> 2961 | ... L10: =L74 -> 3637
B11: Power | C11: =C111 -> 4035 | D11: =D111 -> 4455 | E11: =E111 -> 4206 | F11: =F111 -> 5431 | G11: =G111 -> 4423 | H11: =H111 -> 4758 | I11: =I111 -> 4838 | J11: =J111 -> 5748 | ... L11: =L111 -> 5477
B12: Eliminations and other | C12: ='GEV Quarterly'!B112 -> -65 | D12: ='GEV Quarterly'!C112 -> -103 | E12: ='GEV Quarterly'!D112 -> -112 | F12: ='GEV Quarterly'!E112 -> -162 | G12: ='GEV Quarterly'!F112 -> -119 | H12: ='GEV Quarterly'!G112 -> -92 | I12: ='GEV Quarterly'!H112 -> -119 | J12: ='GEV Quarterly'!I112 -> -121 | K12: ='GEV Quarterly'!J164 -> -25 | L12: ='GEV Quarterly'!K164 -> -37
B13: Total revenues | C13: =SUM(C9:C12) -> 7260 | D13: =SUM(D9:D12) -> 8204 | E13: =SUM(E9:E12) -> 8913 | F13: =SUM(F9:F12) -> 10559 | G13: =SUM(G9:G12) -> 8033 | H13: =SUM(H9:H12) -> 9112 | I13: =SUM(I9:I12) -> 9967 | J13: =SUM(J9:J12) -> 10956 | ... L13: =SUM(L9:L12) -> 11103
B14: Check: total less income statement revenue (rounding only) | C14: =C13-'GEV Quarterly'!B12 -> 0 | D14: =D13-'GEV Quarterly'!C12 -> 0 | E14: =E13-'GEV Quarterly'!D12 -> 0 | F14: =F13-'GEV Quarterly'!E12 -> 1 | G14: =G13-'GEV Quarterly'!F12 -> 1 | H14: =H13-'GEV Quarterly'!G12 -> 1 | I14: =I13-'GEV Quarterly'!H12 -> -2 | J14: =J13-'GEV Quarterly'!I12 -> 0 | ... L14: =L13-'GEV Quarterly'!K12 -> -1
B16: Revenue growth, YoY (%)
B17: Wind | G17: =IF(C9<>0,G9/C9-1,"") -> 0.12873703 | H17: =IF(D9<>0,H9/D9-1,"") -> 0.088748788 | I17: =IF(E9<>0,I9/E9-1,"") -> -0.084399862 | J17: =IF(F9<>0,J9/F9-1,"") -> -0.2383403 | K17: =K9/'GEV Quarterly'!F163-1 -> -0.22594595 | L17: =L9/'GEV Quarterly'!G163-1 -> -0.097550111
B18: Electrification | G18: =IF(C10<>0,G10/C10-1,"") -> 0.13809812 | H18: =IF(D10<>0,H10/D10-1,"") -> 0.22960894 | I18: =IF(E10<>0,I10/E10-1,"") -> 0.34906639 | J18: =IF(F10<>0,J10/F10-1,"") -> 0.35763411 | K18: =K10/'GEV Quarterly'!F162-1 -> 0.60815217 | L18: =L10/'GEV Quarterly'!G162-1 -> 0.68223867
B19: Power | G19: =IF(C11<>0,G11/C11-1,"") -> 0.096158612 | H19: =IF(D11<>0,H11/D11-1,"") -> 0.068013468 | I19: =IF(E11<>0,I11/E11-1,"") -> 0.15026153 | J19: =IF(F11<>0,J11/F11-1,"") -> 0.058368625 | K19: =K11/'GEV Quarterly'!F161-1 -> 0.11732974 | L19: =L11/'GEV Quarterly'!G161-1 -> 0.1446186
B20: Total revenues | G20: =IF(C13<>0,G13/C13-1,"") -> 0.10647383 | H20: =IF(D13<>0,H13/D13-1,"") -> 0.11067772 | I20: =IF(E13<>0,I13/E13-1,"") -> 0.11825424 | J20: =IF(F13<>0,J13/F13-1,"") -> 0.037598257 | K20: =IF(G13<>0,K13/G13-1,"") -> 0.16233039 | L20: =IF(H13<>0,L13/H13-1,"") -> 0.21850307
B22: Ending RPO (US$ millions)
B23: Wind | C23: =C39 -> 26164 | D23: =D39 -> 25773 | E23: =E39 -> 24969 | F23: =F39 -> 22682 | G23: =G39 -> 22160 | H23: =H39 -> 22508 | I23: =I39 -> 21508 | J23: =J39 -> 21630 | ... L23: =L39 -> 20388
B24: Electrification | C24: =C76 -> 18069 | D24: =D76 -> 20679 | E24: =E76 -> 21912 | F24: =F76 -> 23453 | G24: =G76 -> 25462 | H24: =H76 -> 27530 | I24: =I76 -> 30179 | J24: =J76 -> 34667 | ... L24: =L76 -> 44563
B25: Power | C25: =C113 -> 72783 | D25: =D113 -> 69457 | E25: =E113 -> 71303 | F25: =F113 -> 73351 | G25: =G113 -> 76292 | H25: =H113 -> 79065 | I25: =I113 -> 84060 | J25: =J113 -> 94387 | ... L25: =L113 -> 111649
B26: Eliminations and other (derived) | C26: =C27-SUM(C23:C25) -> -723 | D26: =D27-SUM(D23:D25) -> -433 | E26: =E27-SUM(E23:E25) -> -438 | F26: =F27-SUM(F23:F25) -> -463 | G26: =G27-SUM(G23:G25) -> -476 | H26: =H27-SUM(H23:H25) -> -453 | I26: =I27-SUM(I23:I25) -> -478 | J26: =J27-SUM(J23:J25) -> -446 | ... L26: =L27-SUM(L23:L25) -> -316
B27: Total RPO (consolidated, as reported) | C27: ='GEV Quarterly'!B214 -> 116293 | D27: ='GEV Quarterly'!C214 -> 115476 | E27: ='GEV Quarterly'!D214 -> 117746 | F27: ='GEV Quarterly'!E214 -> 119023 | G27: ='GEV Quarterly'!F214 -> 123438 | H27: ='GEV Quarterly'!G214 -> 128650 | I27: ='GEV Quarterly'!H214 -> 135269 | J27: ='GEV Quarterly'!I214 -> 150238 | ... L27: ='GEV Quarterly'!K214 -> 176284
B28: Equipment RPO (consolidated) | C28: ='GEV Quarterly'!B212 -> 42210 | D28: ='GEV Quarterly'!C212 -> 41561 | E28: ='GEV Quarterly'!D212 -> 42069 | F28: ='GEV Quarterly'!E212 -> 43047 | G28: ='GEV Quarterly'!F212 -> 45478 | H28: ='GEV Quarterly'!G212 -> 49712 | I28: ='GEV Quarterly'!H212 -> 54092 | J28: ='GEV Quarterly'!I212 -> 64245 | ... L28: ='GEV Quarterly'!K212 -> 87821
B29: Services RPO (consolidated) | C29: ='GEV Quarterly'!B213 -> 74083 | D29: ='GEV Quarterly'!C213 -> 73915 | E29: ='GEV Quarterly'!D213 -> 75678 | F29: ='GEV Quarterly'!E213 -> 75976 | G29: ='GEV Quarterly'!F213 -> 77959 | H29: ='GEV Quarterly'!G213 -> 78938 | I29: ='GEV Quarterly'!H213 -> 81177 | J29: ='GEV Quarterly'!I213 -> 85993 | ... L29: ='GEV Quarterly'!K213 -> 88463
B31: Segment Revenue Build: RPO Roll-Forward (US$ millions)
B33: Wind
B34: Beginning RPO: | D34: =C39 -> 26164 | E34: =D39 -> 25773 | F34: =E39 -> 24969 | G34: =F39 -> 22682 | H34: =G39 -> 22160 | I34: =H39 -> 22508 | J34: =I39 -> 21508 | K34: =J39 -> 21630 | L34: =K39 -> 21348
B35: (+/-) Segment realignment | K35: ='GEV Quarterly'!I246-'GEV Quarterly'!I233 -> 0
B36: (+) Orders (implied) | D36: ='GEV Quarterly'!C234 -> 1671 | E36: ='GEV Quarterly'!D234 -> 2087 | F36: ='GEV Quarterly'!E234 -> 822 | G36: ='GEV Quarterly'!F234 -> 1328 | H36: ='GEV Quarterly'!G234 -> 2593 | I36: ='GEV Quarterly'!H234 -> 1647 | J36: ='GEV Quarterly'!I234 -> 2490 | K36: ='GEV Quarterly'!J247 -> 1150 | L36: ='GEV Quarterly'!K247 -> 1066
B37: (-) Revenue | C37: ='GEV Quarterly'!B111 -> 1639 | D37: ='GEV Quarterly'!C111 -> 2062 | E37: ='GEV Quarterly'!D111 -> 2891 | F37: ='GEV Quarterly'!E111 -> 3109 | G37: ='GEV Quarterly'!F111 -> 1850 | H37: ='GEV Quarterly'!G111 -> 2245 | I37: ='GEV Quarterly'!H111 -> 2647 | J37: ='GEV Quarterly'!I111 -> 2368 | K37: ='GEV Quarterly'!J163 -> 1432 | L37: ='GEV Quarterly'!K163 -> 2026
B38: (%) of RPO conversion | D38: =IF((D34+D35)<>0,D37/(D34+D35),"") -> 0.078810579 | E38: =IF((E34+E35)<>0,E37/(E34+E35),"") -> 0.11217165 | F38: =IF((F34+F35)<>0,F37/(F34+F35),"") -> 0.1245144 | G38: =IF((G34+G35)<>0,G37/(G34+G35),"") -> 0.081562472 | H38: =IF((H34+H35)<>0,H37/(H34+H35),"") -> 0.10130866 | I38: =IF((I34+I35)<>0,I37/(I34+I35),"") -> 0.11760263 | J38: =IF((J34+J35)<>0,J37/(J34+J35),"") -> 0.11009857 | K38: =IF((K34+K35)<>0,K37/(K34+K35),"") -> 0.066204346 | L38: =IF((L34+L35)<>0,L37/(L34+L35),"") -> 0.094903504
B39: Ending Backlog | C39: ='GEV Quarterly'!B233 -> 26164 | D39: =D34+D35+D36-D37 -> 25773 | E39: =E34+E35+E36-E37 -> 24969 | F39: =F34+F35+F36-F37 -> 22682 | G39: =G34+G35+G36-G37 -> 22160 | H39: =H34+H35+H36-H37 -> 22508 | I39: =I34+I35+I36-I37 -> 21508 | J39: =J34+J35+J36-J37 -> 21630 | K39: =K34+K35+K36-K37 -> 21348 | L39: =L34+L35+L36-L37 -> 20388
B41: Equipment
B42: Beginning RPO: | D42: =C47 -> 13119 | E42: =D47 -> 13147 | F42: =E47 -> 12182 | G42: =F47 -> 10720 | H42: =G47 -> 9676 | I42: =H47 -> 9731 | J42: =I47 -> 8782 | K42: =J47 -> 9112 | L42: =K47 -> 8905
B43: (+/-) Segment realignment | K43: ='GEV Quarterly'!I244-'GEV Quarterly'!I231 -> 0
B44: (+) Orders (implied) | D44: ='GEV Quarterly'!C231-'GEV Quarterly'!B231+'GEV Quarterly'!C149 -> 1696 | E44: ='GEV Quarterly'!D231-'GEV Quarterly'!C231+'GEV Quarterly'!D149 -> 1529 | F44: ='GEV Quarterly'!E231-'GEV Quarterly'!D231+'GEV Quarterly'!E149 -> 1191 | G44: ='GEV Quarterly'!F231-'GEV Quarterly'!E231+'GEV Quarterly'!F149 -> 368 | H44: ='GEV Quarterly'!G231-'GEV Quarterly'!F231+'GEV Quarterly'!G149 -> 1852 | I44: ='GEV Quarterly'!H231-'GEV Quarterly'!G231+'GEV Quarterly'!H149 -> 1254 | J44: ='GEV Quarterly'!I231-'GEV Quarterly'!H231+'GEV Quarterly'!I149 -> 2169 | K44: ='GEV Quarterly'!J244-'GEV Quarterly'!I244+'GEV Quarterly'!J201 -> 682 | L44: ='GEV Quarterly'!K244-'GEV Quarterly'!J244+'GEV Quarterly'!K201 -> 687
B45: (-) Revenue | C45: ='GEV Quarterly'!B149 -> 1232 | D45: ='GEV Quarterly'!C149 -> 1668 | E45: ='GEV Quarterly'!D149 -> 2494 | F45: ='GEV Quarterly'!E149 -> 2653 | G45: ='GEV Quarterly'!F149 -> 1412 | H45: ='GEV Quarterly'!G149 -> 1797 | I45: ='GEV Quarterly'!H149 -> 2203 | J45: ='GEV Quarterly'!I149 -> 1839 | K45: ='GEV Quarterly'!J201 -> 889 | L45: ='GEV Quarterly'!K201 -> 1395
B46: (%) of RPO conversion | D46: =IF((D42+D43)<>0,D45/(D42+D43),"") -> 0.12714384 | E46: =IF((E42+E43)<>0,E45/(E42+E43),"") -> 0.18970107 | F46: =IF((F42+F43)<>0,F45/(F42+F43),"") -> 0.21778033 | G46: =IF((G42+G43)<>0,G45/(G42+G43),"") -> 0.13171642 | H46: =IF((H42+H43)<>0,H45/(H42+H43),"") -> 0.18571724 | I46: =IF((I42+I43)<>0,I45/(I42+I43),"") -> 0.22638989 | J46: =IF((J42+J43)<>0,J45/(J42+J43),"") -> 0.2094056 | K46: =IF((K42+K43)<>0,K45/(K42+K43),"") -> 0.097563652 | L46: =IF((L42+L43)<>0,L45/(L42+L43),"") -> 0.15665357
B47: Ending Backlog | C47: ='GEV Quarterly'!B231 -> 13119 | D47: =D42+D43+D44-D45 -> 13147 | E47: =E42+E43+E44-E45 -> 12182 | F47: =F42+F43+F44-F45 -> 10720 | G47: =G42+G43+G44-G45 -> 9676 | H47: =H42+H43+H44-H45 -> 9731 | I47: =I42+I43+I44-I45 -> 8782 | J47: =J42+J43+J44-J45 -> 9112 | K47: =K42+K43+K44-K45 -> 8905 | L47: =L42+L43+L44-L45 -> 8197
B49: Services
B50: Beginning RPO: | D50: =C55 -> 13045 | E50: =D55 -> 12626 | F50: =E55 -> 12788 | G50: =F55 -> 11962 | H50: =G55 -> 12484 | I50: =H55 -> 12777 | J50: =I55 -> 12726 | K50: =J55 -> 12518 | L50: =K55 -> 12443
B51: (+/-) Segment realignment | K51: ='GEV Quarterly'!I245-'GEV Quarterly'!I232 -> 0
B52: (+) Orders (implied) | D52: ='GEV Quarterly'!C232-'GEV Quarterly'!B232+'GEV Quarterly'!C150 -> -25 | E52: ='GEV Quarterly'!D232-'GEV Quarterly'!C232+'GEV Quarterly'!D150 -> 559 | F52: ='GEV Quarterly'!E232-'GEV Quarterly'!D232+'GEV Quarterly'!E150 -> -370 | G52: ='GEV Quarterly'!F232-'GEV Quarterly'!E232+'GEV Quarterly'!F150 -> 960 | H52: ='GEV Quarterly'!G232-'GEV Quarterly'!F232+'GEV Quarterly'!G150 -> 741 | I52: ='GEV Quarterly'!H232-'GEV Quarterly'!G232+'GEV Quarterly'!H150 -> 394 | J52: ='GEV Quarterly'!I232-'GEV Quarterly'!H232+'GEV Quarterly'!I150 -> 320 | K52: ='GEV Quarterly'!J245-'GEV Quarterly'!I245+'GEV Quarterly'!J202 -> 468 | L52: ='GEV Quarterly'!K245-'GEV Quarterly'!J245+'GEV Quarterly'!K202 -> 380
B53: (-) Revenue | C53: ='GEV Quarterly'!B150 -> 407 | D53: ='GEV Quarterly'!C150 -> 394 | E53: ='GEV Quarterly'!D150 -> 397 | F53: ='GEV Quarterly'!E150 -> 456 | G53: ='GEV Quarterly'!F150 -> 438 | H53: ='GEV Quarterly'!G150 -> 448 | I53: ='GEV Quarterly'!H150 -> 445 | J53: ='GEV Quarterly'!I150 -> 528 | K53: ='GEV Quarterly'!J202 -> 543 | L53: ='GEV Quarterly'!K202 -> 632
B54: (%) of RPO conversion | D54: =IF((D50+D51)<>0,D53/(D50+D51),"") -> 0.030203143 | E54: =IF((E50+E51)<>0,E53/(E50+E51),"") -> 0.031443054 | F54: =IF((F50+F51)<>0,F53/(F50+F51),"") -> 0.03565843 | G54: =IF((G50+G51)<>0,G53/(G50+G51),"") -> 0.036615951 | H54: =IF((H50+H51)<>0,H53/(H50+H51),"") -> 0.035885934 | I54: =IF((I50+I51)<>0,I53/(I50+I51),"") -> 0.034828207 | J54: =IF((J50+J51)<>0,J53/(J50+J51),"") -> 0.041489863 | K54: =IF((K50+K51)<>0,K53/(K50+K51),"") -> 0.043377536 | L54: =IF((L50+L51)<>0,L53/(L50+L51),"") -> 0.05079161
B55: Ending Backlog | C55: ='GEV Quarterly'!B232 -> 13045 | D55: =D50+D51+D52-D53 -> 12626 | E55: =E50+E51+E52-E53 -> 12788 | F55: =F50+F51+F52-F53 -> 11962 | G55: =G50+G51+G52-G53 -> 12484 | H55: =H50+H51+H52-H53 -> 12777 | I55: =I50+I51+I52-I53 -> 12726 | J55: =J50+J51+J52-J53 -> 12518 | K55: =K50+K51+K52-K53 -> 12443 | L55: =L50+L51+L52-L53 -> 12191
B57: Memo
B58: Book-to-bill, total (x) | D58: =IF(D37<>0,D36/D37,"") -> 0.81037827 | E58: =IF(E37<>0,E36/E37,"") -> 0.72189554 | F58: =IF(F37<>0,F36/F37,"") -> 0.2643937 | G58: =IF(G37<>0,G36/G37,"") -> 0.71783784 | H58: =IF(H37<>0,H36/H37,"") -> 1.1550111 | I58: =IF(I37<>0,I36/I37,"") -> 0.62221383 | J58: =IF(J37<>0,J36/J37,"") -> 1.0515203 | K58: =IF(K37<>0,K36/K37,"") -> 0.80307263 | L58: =IF(L37<>0,L36/L37,"") -> 0.52615992
B59: Book-to-bill, equipment (x) | D59: =IF(D45<>0,D44/D45,"") -> 1.0167866 | E59: =IF(E45<>0,E44/E45,"") -> 0.61307137 | F59: =IF(F45<>0,F44/F45,"") -> 0.44892574 | G59: =IF(G45<>0,G44/G45,"") -> 0.26062323 | H59: =IF(H45<>0,H44/H45,"") -> 1.0306066 | I59: =IF(I45<>0,I44/I45,"") -> 0.56922379 | J59: =IF(J45<>0,J44/J45,"") -> 1.1794454 | K59: =IF(K45<>0,K44/K45,"") -> 0.76715411 | L59: =IF(L45<>0,L44/L45,"") -> 0.49247312
B60: Backlog growth, YoY (%) | G60: =IF(C39<>0,G39/C39-1,"") -> -0.1530347 | H60: =IF(D39<>0,H39/D39-1,"") -> -0.12668296 | I60: =IF(E39<>0,I39/E39-1,"") -> -0.13861188 | J60: =IF(F39<>0,J39/F39-1,"") -> -0.04638039 | K60: =K39/'GEV Quarterly'!F246-1 -> -0.036642599 | L60: =L39/'GEV Quarterly'!G246-1 -> -0.094188733
B61: RPO coverage (years of annualised revenue) | C61: =IF(C37<>0,C39/(C37*4),"") -> 3.9908481 | D61: =IF(D37<>0,D39/(D37*4),"") -> 3.1247575 | E61: =IF(E37<>0,E39/(E37*4),"") -> 2.159201 | F61: =IF(F37<>0,F39/(F37*4),"") -> 1.8238984 | G61: =IF(G37<>0,G39/(G37*4),"") -> 2.9945946 | H61: =IF(H37<>0,H39/(H37*4),"") -> 2.5064588 | I61: =IF(I37<>0,I39/(I37*4),"") -> 2.0313563 | J61: =IF(J37<>0,J39/(J37*4),"") -> 2.2835726 | ... L61: =IF(L37<>0,L39/(L37*4),"") -> 2.5157947
B62: Services as % of segment revenue | C62: =IF((C45+C53)<>0,C53/(C45+C53),"") -> 0.24832215 | D62: =IF((D45+D53)<>0,D53/(D45+D53),"") -> 0.19107662 | E62: =IF((E45+E53)<>0,E53/(E45+E53),"") -> 0.13732273 | F62: =IF((F45+F53)<>0,F53/(F45+F53),"") -> 0.14667096 | G62: =IF((G45+G53)<>0,G53/(G45+G53),"") -> 0.23675676 | H62: =IF((H45+H53)<>0,H53/(H45+H53),"") -> 0.19955457 | I62: =IF((I45+I53)<>0,I53/(I45+I53),"") -> 0.16805136 | J62: =IF((J45+J53)<>0,J53/(J45+J53),"") -> 0.22306717 | ... L62: =IF((L45+L53)<>0,L53/(L45+L53),"") -> 0.31179082
B64: Checks
B65: Ending RPO less reported (should be 0) | C65: =ABS(C39-'GEV Quarterly'!B233)+ABS(C47-'GEV Quarterly'!B231)+ABS(C55-'GEV Quarterly'!B232) -> 0 | D65: =ABS(D39-'GEV Quarterly'!C233)+ABS(D47-'GEV Quarterly'!C231)+ABS(D55-'GEV Quarterly'!C232) -> 0 | E65: =ABS(E39-'GEV Quarterly'!D233)+ABS(E47-'GEV Quarterly'!D231)+ABS(E55-'GEV Quarterly'!D232) -> 0 | F65: =ABS(F39-'GEV Quarterly'!E233)+ABS(F47-'GEV Quarterly'!E231)+ABS(F55-'GEV Quarterly'!E232) -> 0 | G65: =ABS(G39-'GEV Quarterly'!F233)+ABS(G47-'GEV Quarterly'!F231)+ABS(G55-'GEV Quarterly'!F232) -> 0 | H65: =ABS(H39-'GEV Quarterly'!G233)+ABS(H47-'GEV Quarterly'!G231)+ABS(H55-'GEV Quarterly'!G232) -> 0 | I65: =ABS(I39-'GEV Quarterly'!H233)+ABS(I47-'GEV Quarterly'!H231)+ABS(I55-'GEV Quarterly'!H232) -> 0 | J65: =ABS(J39-'GEV Quarterly'!I233)+ABS(J47-'GEV Quarterly'!I231)+ABS(J55-'GEV Quarterly'!I232) -> 0 | K65: =ABS(K39-'GEV Quarterly'!J246)+ABS(K47-'GEV Quarterly'!J244)+ABS(K55-'GEV Quarterly'!J245) -> 0 | L65: =ABS(L39-'GEV Quarterly'!K246)+ABS(L47-'GEV Quarterly'!K244)+ABS(L55-'GEV Quarterly'!K245) -> 0
B66: Equipment + services less total RPO (rounding only) | C66: =C47+C55-C39 -> 0 | D66: =D47+D55-D39 -> 0 | E66: =E47+E55-E39 -> 1 | F66: =F47+F55-F39 -> 0 | G66: =G47+G55-G39 -> 0 | H66: =H47+H55-H39 -> 0 | I66: =I47+I55-I39 -> 0 | J66: =J47+J55-J39 -> 0 | ... L66: =L47+L55-L39 -> 0
B67: Equipment + services less total revenue (rounding only) | C67: =C45+C53-C37 -> 0 | D67: =D45+D53-D37 -> 0 | E67: =E45+E53-E37 -> 0 | F67: =F45+F53-F37 -> 0 | G67: =G45+G53-G37 -> 0 | H67: =H45+H53-H37 -> 0 | I67: =I45+I53-I37 -> 1 | J67: =J45+J53-J37 -> -1 | ... L67: =L45+L53-L37 -> 1
B68: *Backlog keeps
B70: Electrification
B71: Beginning RPO: | D71: =C76 -> 18069 | E71: =D76 -> 20679 | F71: =E76 -> 21912 | G71: =F76 -> 23453 | H71: =G76 -> 25462 | I71: =H76 -> 27530 | J71: =I76 -> 30179 | K71: =J76 -> 34667 | L71: =K76 -> 42440
B72: (+/-) Segment realignment | K72: ='GEV Quarterly'!I242-'GEV Quarterly'!I229 -> -425
B73: (+) Orders (implied) | D73: ='GEV Quarterly'!C230 -> 4400 | E73: ='GEV Quarterly'!D230 -> 3161 | F73: ='GEV Quarterly'!E230 -> 3722 | G73: ='GEV Quarterly'!F230 -> 3888 | H73: ='GEV Quarterly'!G230 -> 4269 | I73: ='GEV Quarterly'!H230 -> 5250 | J73: ='GEV Quarterly'!I230 -> 7449 | K73: ='GEV Quarterly'!J243 -> 11157 | L73: ='GEV Quarterly'!K243 -> 5760
B74: (-) Revenue | C74: ='GEV Quarterly'!B110 -> 1651 | D74: ='GEV Quarterly'!C110 -> 1790 | E74: ='GEV Quarterly'!D110 -> 1928 | F74: ='GEV Quarterly'!E110 -> 2181 | G74: ='GEV Quarterly'!F110 -> 1879 | H74: ='GEV Quarterly'!G110 -> 2201 | I74: ='GEV Quarterly'!H110 -> 2601 | J74: ='GEV Quarterly'!I110 -> 2961 | K74: ='GEV Quarterly'!J162 -> 2959 | L74: ='GEV Quarterly'!K162 -> 3637
B75: (%) of RPO conversion | D75: =IF((D71+D72)<>0,D74/(D71+D72),"") -> 0.099064696 | E75: =IF((E71+E72)<>0,E74/(E71+E72),"") -> 0.093234683 | F75: =IF((F71+F72)<>0,F74/(F71+F72),"") -> 0.099534502 | G75: =IF((G71+G72)<>0,G74/(G71+G72),"") -> 0.080117682 | H75: =IF((H71+H72)<>0,H74/(H71+H72),"") -> 0.086442542 | I75: =IF((I71+I72)<>0,I74/(I71+I72),"") -> 0.09447875 | J75: =IF((J71+J72)<>0,J74/(J71+J72),"") -> 0.098114583 | K75: =IF((K71+K72)<>0,K74/(K71+K72),"") -> 0.086414345 | L75: =IF((L71+L72)<>0,L74/(L71+L72),"") -> 0.085697455
B76: Ending Backlog | C76: ='GEV Quarterly'!B229 -> 18069 | D76: =D71+D72+D73-D74 -> 20679 | E76: =E71+E72+E73-E74 -> 21912 | F76: =F71+F72+F73-F74 -> 23453 | G76: =G71+G72+G73-G74 -> 25462 | H76: =H71+H72+H73-H74 -> 27530 | I76: =I71+I72+I73-I74 -> 30179 | J76: =J71+J72+J73-J74 -> 34667 | K76: =K71+K72+K73-K74 -> 42440 | L76: =L71+L72+L73-L74 -> 44563
B78: Equipment
B79: Beginning RPO: | D79: =C84 -> 14849 | E79: =D84 -> 17540 | F79: =E84 -> 18624 | G79: =F84 -> 20005 | H79: =G84 -> 21996 | I79: =H84 -> 23950 | J79: =I84 -> 26455 | K79: =J84 -> 30508 | L79: =K84 -> 38598
B80: (+/-) Segment realignment | K80: ='GEV Quarterly'!I240-'GEV Quarterly'!I227 -> 0
B81: (+) Orders (implied) | D81: ='GEV Quarterly'!C227-'GEV Quarterly'!B227+'GEV Quarterly'!C140 -> 3977 | E81: ='GEV Quarterly'!D227-'GEV Quarterly'!C227+'GEV Quarterly'!D140 -> 2535 | F81: ='GEV Quarterly'!E227-'GEV Quarterly'!D227+'GEV Quarterly'!E140 -> 2948 | G81: ='GEV Quarterly'!F227-'GEV Quarterly'!E227+'GEV Quarterly'!F140 -> 3382 | H81: ='GEV Quarterly'!G227-'GEV Quarterly'!F227+'GEV Quarterly'!G140 -> 3627 | I81: ='GEV Quarterly'!H227-'GEV Quarterly'!G227+'GEV Quarterly'!H140 -> 4540 | J81: ='GEV Quarterly'!I227-'GEV Quarterly'!H227+'GEV Quarterly'!I140 -> 6332 | K81: ='GEV Quarterly'!J240-'GEV Quarterly'!I240+'GEV Quarterly'!J191 -> 10591 | L81: ='GEV Quarterly'!K240-'GEV Quarterly'!J240+'GEV Quarterly'!K191 -> 5121
B82: (-) Revenue | C82: ='GEV Quarterly'!B140 -> 1230 | D82: ='GEV Quarterly'!C140 -> 1286 | E82: ='GEV Quarterly'!D140 -> 1451 | F82: ='GEV Quarterly'!E140 -> 1567 | G82: ='GEV Quarterly'!F140 -> 1391 | H82: ='GEV Quarterly'!G140 -> 1673 | I82: ='GEV Quarterly'!H140 -> 2035 | J82: ='GEV Quarterly'!I140 -> 2279 | K82: ='GEV Quarterly'!J191 -> 2501 | L82: ='GEV Quarterly'!K191 -> 3130
B83: (%) of RPO conversion | D83: =IF((D79+D80)<>0,D82/(D79+D80),"") -> 0.086605159 | E83: =IF((E79+E80)<>0,E82/(E79+E80),"") -> 0.0827252 | F83: =IF((F79+F80)<>0,F82/(F79+F80),"") -> 0.084138746 | G83: =IF((G79+G80)<>0,G82/(G79+G80),"") -> 0.069532617 | H83: =IF((H79+H80)<>0,H82/(H79+H80),"") -> 0.076059284 | I83: =IF((I79+I80)<>0,I82/(I79+I80),"") -> 0.084968685 | J83: =IF((J79+J80)<>0,J82/(J79+J80),"") -> 0.086146286 | K83: =IF((K79+K80)<>0,K82/(K79+K80),"") -> 0.081978497 | L83: =IF((L79+L80)<>0,L82/(L79+L80),"") -> 0.081092285
B84: Ending Backlog | C84: ='GEV Quarterly'!B227 -> 14849 | D84: =D79+D80+D81-D82 -> 17540 | E84: =E79+E80+E81-E82 -> 18624 | F84: =F79+F80+F81-F82 -> 20005 | G84: =G79+G80+G81-G82 -> 21996 | H84: =H79+H80+H81-H82 -> 23950 | I84: =I79+I80+I81-I82 -> 26455 | J84: =J79+J80+J81-J82 -> 30508 | K84: =K79+K80+K81-K82 -> 38598 | L84: =L79+L80+L81-L82 -> 40589
B86: Services
B87: Beginning RPO: | D87: =C92 -> 3221 | E87: =D92 -> 3139 | F87: =E92 -> 3288 | G87: =F92 -> 3448 | H87: =G92 -> 3466 | I87: =H92 -> 3580 | J87: =I92 -> 3725 | K87: =J92 -> 4159 | L87: =K92 -> 3842
B88: (+/-) Segment realignment | K88: ='GEV Quarterly'!I241-'GEV Quarterly'!I228 -> -425
B89: (+) Orders (implied) | D89: ='GEV Quarterly'!C228-'GEV Quarterly'!B228+'GEV Quarterly'!C141 -> 422 | E89: ='GEV Quarterly'!D228-'GEV Quarterly'!C228+'GEV Quarterly'!D141 -> 626 | F89: ='GEV Quarterly'!E228-'GEV Quarterly'!D228+'GEV Quarterly'!E141 -> 773 | G89: ='GEV Quarterly'!F228-'GEV Quarterly'!E228+'GEV Quarterly'!F141 -> 505 | H89: ='GEV Quarterly'!G228-'GEV Quarterly'!F228+'GEV Quarterly'!G141 -> 642 | I89: ='GEV Quarterly'!H228-'GEV Quarterly'!G228+'GEV Quarterly'!H141 -> 711 | J89: ='GEV Quarterly'!I228-'GEV Quarterly'!H228+'GEV Quarterly'!I141 -> 1116 | K89: ='GEV Quarterly'!J241-'GEV Quarterly'!I241+'GEV Quarterly'!J192 -> 567 | L89: ='GEV Quarterly'!K241-'GEV Quarterly'!J241+'GEV Quarterly'!K192 -> 639
B90: (-) Revenue | C90: ='GEV Quarterly'!B141 -> 421 | D90: ='GEV Quarterly'!C141 -> 504 | E90: ='GEV Quarterly'!D141 -> 477 | F90: ='GEV Quarterly'!E141 -> 613 | G90: ='GEV Quarterly'!F141 -> 487 | H90: ='GEV Quarterly'!G141 -> 528 | I90: ='GEV Quarterly'!H141 -> 566 | J90: ='GEV Quarterly'!I141 -> 682 | K90: ='GEV Quarterly'!J192 -> 459 | L90: ='GEV Quarterly'!K192 -> 507
B91: (%) of RPO conversion | D91: =IF((D87+D88)<>0,D90/(D87+D88),"") -> 0.15647314 | E91: =IF((E87+E88)<>0,E90/(E87+E88),"") -> 0.15195922 | F91: =IF((F87+F88)<>0,F90/(F87+F88),"") -> 0.18643552 | G91: =IF((G87+G88)<>0,G90/(G87+G88),"") -> 0.1412413 | H91: =IF((H87+H88)<>0,H90/(H87+H88),"") -> 0.15233699 | I91: =IF((I87+I88)<>0,I90/(I87+I88),"") -> 0.15810056 | J91: =IF((J87+J88)<>0,J90/(J87+J88),"") -> 0.18308725 | K91: =IF((K87+K88)<>0,K90/(K87+K88),"") -> 0.12292448 | L91: =IF((L87+L88)<>0,L90/(L87+L88),"") -> 0.13196252
B92: Ending Backlog | C92: ='GEV Quarterly'!B228 -> 3221 | D92: =D87+D88+D89-D90 -> 3139 | E92: =E87+E88+E89-E90 -> 3288 | F92: =F87+F88+F89-F90 -> 3448 | G92: =G87+G88+G89-G90 -> 3466 | H92: =H87+H88+H89-H90 -> 3580 | I92: =I87+I88+I89-I90 -> 3725 | J92: =J87+J88+J89-J90 -> 4159 | K92: =K87+K88+K89-K90 -> 3842 | L92: =L87+L88+L89-L90 -> 3974
B94: Memo
B95: Book-to-bill, total (x) | D95: =IF(D74<>0,D73/D74,"") -> 2.4581006 | E95: =IF(E74<>0,E73/E74,"") -> 1.6395228 | F95: =IF(F74<>0,F73/F74,"") -> 1.7065566 | G95: =IF(G74<>0,G73/G74,"") -> 2.0691857 | H95: =IF(H74<>0,H73/H74,"") -> 1.9395729 | I95: =IF(I74<>0,I73/I74,"") -> 2.0184544 | J95: =IF(J74<>0,J73/J74,"") -> 2.5157042 | K95: =IF(K74<>0,K73/K74,"") -> 3.7705306 | L95: =IF(L74<>0,L73/L74,"") -> 1.5837228
B96: Book-to-bill, equipment (x) | D96: =IF(D82<>0,D81/D82,"") -> 3.092535 | E96: =IF(E82<>0,E81/E82,"") -> 1.747071 | F96: =IF(F82<>0,F81/F82,"") -> 1.8813019 | G96: =IF(G82<>0,G81/G82,"") -> 2.4313444 | H96: =IF(H82<>0,H81/H82,"") -> 2.1679617 | I96: =IF(I82<>0,I81/I82,"") -> 2.2309582 | J96: =IF(J82<>0,J81/J82,"") -> 2.7784116 | K96: =IF(K82<>0,K81/K82,"") -> 4.2347061 | L96: =IF(L82<>0,L81/L82,"") -> 1.6361022
B97: Backlog growth, YoY (%) | G97: =IF(C76<>0,G76/C76-1,"") -> 0.4091538 | H97: =IF(D76<>0,H76/D76-1,"") -> 0.33130229 | I97: =IF(E76<>0,I76/E76-1,"") -> 0.37728185 | J97: =IF(F76<>0,J76/F76-1,"") -> 0.47814778 | K97: =K76/'GEV Quarterly'!F242-1 -> 0.6952944 | L97: =L76/'GEV Quarterly'!G242-1 -> 0.64329965
B98: RPO coverage (years of annualised revenue) | C98: =IF(C74<>0,C76/(C74*4),"") -> 2.736069 | D98: =IF(D74<>0,D76/(D74*4),"") -> 2.8881285 | E98: =IF(E74<>0,E76/(E74*4),"") -> 2.8412863 | F98: =IF(F74<>0,F76/(F74*4),"") -> 2.688331 | G98: =IF(G74<>0,G76/(G74*4),"") -> 3.3877062 | H98: =IF(H74<>0,H76/(H74*4),"") -> 3.1269877 | I98: =IF(I74<>0,I76/(I74*4),"") -> 2.9007113 | J98: =IF(J74<>0,J76/(J74*4),"") -> 2.9269672 | ... L98: =IF(L74<>0,L76/(L74*4),"") -> 3.0631702
B99: Services as % of segment revenue | C99: =IF((C82+C90)<>0,C90/(C82+C90),"") -> 0.25499697 | D99: =IF((D82+D90)<>0,D90/(D82+D90),"") -> 0.28156425 | E99: =IF((E82+E90)<>0,E90/(E82+E90),"") -> 0.24740664 | F99: =IF((F82+F90)<>0,F90/(F82+F90),"") -> 0.28119266 | G99: =IF((G82+G90)<>0,G90/(G82+G90),"") -> 0.25931842 | H99: =IF((H82+H90)<>0,H90/(H82+H90),"") -> 0.23989096 | I99: =IF((I82+I90)<>0,I90/(I82+I90),"") -> 0.21760861 | J99: =IF((J82+J90)<>0,J90/(J82+J90),"") -> 0.23032759 | ... L99: =IF((L82+L90)<>0,L90/(L82+L90),"") -> 0.1394006
B101: Checks
B102: Ending RPO less reported (should be 0) | C102: =ABS(C76-'GEV Quarterly'!B229)+ABS(C84-'GEV Quarterly'!B227)+ABS(C92-'GEV Quarterly'!B228) -> 0 | D102: =ABS(D76-'GEV Quarterly'!C229)+ABS(D84-'GEV Quarterly'!C227)+ABS(D92-'GEV Quarterly'!C228) -> 0 | E102: =ABS(E76-'GEV Quarterly'!D229)+ABS(E84-'GEV Quarterly'!D227)+ABS(E92-'GEV Quarterly'!D228) -> 0 | F102: =ABS(F76-'GEV Quarterly'!E229)+ABS(F84-'GEV Quarterly'!E227)+ABS(F92-'GEV Quarterly'!E228) -> 0 | G102: =ABS(G76-'GEV Quarterly'!F229)+ABS(G84-'GEV Quarterly'!F227)+ABS(G92-'GEV Quarterly'!F228) -> 0 | H102: =ABS(H76-'GEV Quarterly'!G229)+ABS(H84-'GEV Quarterly'!G227)+ABS(H92-'GEV Quarterly'!G228) -> 0 | I102: =ABS(I76-'GEV Quarterly'!H229)+ABS(I84-'GEV Quarterly'!H227)+ABS(I92-'GEV Quarterly'!H228) -> 0 | J102: =ABS(J76-'GEV Quarterly'!I229)+ABS(J84-'GEV Quarterly'!I227)+ABS(J92-'GEV Quarterly'!I228) -> 0 | K102: =ABS(K76-'GEV Quarterly'!J242)+ABS(K84-'GEV Quarterly'!J240)+ABS(K92-'GEV Quarterly'!J241) -> 0 | L102: =ABS(L76-'GEV Quarterly'!K242)+ABS(L84-'GEV Quarterly'!K240)+ABS(L92-'GEV Quarterly'!K241) -> 0
B103: Equipment + services less total RPO (rounding only) | C103: =C84+C92-C76 -> 1 | D103: =D84+D92-D76 -> 0 | E103: =E84+E92-E76 -> 0 | F103: =F84+F92-F76 -> 0 | G103: =G84+G92-G76 -> 0 | H103: =H84+H92-H76 -> 0 | I103: =I84+I92-I76 -> 1 | J103: =J84+J92-J76 -> 0 | ... L103: =L84+L92-L76 -> 0
B104: Equipment + services less total revenue (rounding only) | C104: =C82+C90-C74 -> 0 | D104: =D82+D90-D74 -> 0 | E104: =E82+E90-E74 -> 0 | F104: =F82+F90-F74 -> -1 | G104: =G82+G90-G74 -> -1 | H104: =H82+H90-H74 -> 0 | I104: =I82+I90-I74 -> 0 | J104: =J82+J90-J74 -> 0 | ... L104: =L82+L90-L74 -> 0
B107: Power
B108: Beginning RPO: | D108: =C113 -> 72783 | E108: =D113 -> 69457 | F108: =E113 -> 71303 | G108: =F113 -> 73351 | H108: =G113 -> 76292 | I108: =H113 -> 79065 | J108: =I113 -> 84060 | K108: =J113 -> 94387 | L108: =K113 -> 99694
B109: (+/-) Segment realignment | K109: ='GEV Quarterly'!I238-'GEV Quarterly'!I225 -> 161
B110: (+) Orders (implied) | D110: ='GEV Quarterly'!C226 -> 1129 | E110: ='GEV Quarterly'!D226 -> 6052 | F110: ='GEV Quarterly'!E226 -> 7479 | G110: ='GEV Quarterly'!F226 -> 7364 | H110: ='GEV Quarterly'!G226 -> 7531 | I110: ='GEV Quarterly'!H226 -> 9833 | J110: ='GEV Quarterly'!I226 -> 16075 | K110: ='GEV Quarterly'!J239 -> 10117 | L110: ='GEV Quarterly'!K239 -> 17432
B111: (-) Revenue | C111: ='GEV Quarterly'!B109 -> 4035 | D111: ='GEV Quarterly'!C109 -> 4455 | E111: ='GEV Quarterly'!D109 -> 4206 | F111: ='GEV Quarterly'!E109 -> 5431 | G111: ='GEV Quarterly'!F109 -> 4423 | H111: ='GEV Quarterly'!G109 -> 4758 | I111: ='GEV Quarterly'!H109 -> 4838 | J111: ='GEV Quarterly'!I109 -> 5748 | K111: ='GEV Quarterly'!J161 -> 4971 | L111: ='GEV Quarterly'!K161 -> 5477
B112: (%) of RPO conversion | D112: =IF((D108+D109)<>0,D111/(D108+D109),"") -> 0.061209348 | E112: =IF((E108+E109)<>0,E111/(E108+E109),"") -> 0.060555452 | F112: =IF((F108+F109)<>0,F111/(F108+F109),"") -> 0.076167903 | G112: =IF((G108+G109)<>0,G111/(G108+G109),"") -> 0.06029911 | H112: =IF((H108+H109)<>0,H111/(H108+H109),"") -> 0.062365648 | I112: =IF((I108+I109)<>0,I111/(I108+I109),"") -> 0.06119016 | J112: =IF((J108+J109)<>0,J111/(J108+J109),"") -> 0.068379729 | K112: =IF((K108+K109)<>0,K111/(K108+K109),"") -> 0.052576469 | L112: =IF((L108+L109)<>0,L111/(L108+L109),"") -> 0.054938111
B113: Ending Backlog | C113: ='GEV Quarterly'!B225 -> 72783 | D113: =D108+D109+D110-D111 -> 69457 | E113: =E108+E109+E110-E111 -> 71303 | F113: =F108+F109+F110-F111 -> 73351 | G113: =G108+G109+G110-G111 -> 76292 | H113: =H108+H109+H110-H111 -> 79065 | I113: =I108+I109+I110-I111 -> 84060 | J113: =J108+J109+J110-J111 -> 94387 | K113: =K108+K109+K110-K111 -> 99694 | L113: =L108+L109+L110-L111 -> 111649
B115: Equipment
B116: Beginning RPO: | D116: =C121 -> 14394 | E116: =D121 -> 10978 | F116: =E121 -> 11392 | G116: =F121 -> 12461 | H116: =G121 -> 13920 | I116: =H121 -> 16133 | J116: =I121 -> 18977 | K116: =J121 -> 24707 | L116: =K121 -> 28530
B117: (+/-) Segment realignment | K117: ='GEV Quarterly'!I236-'GEV Quarterly'!I223 -> 0
...

Sheet Revenue
C2: GE Vernova (GEV)
C3: Revenue build, quarterly
C4: US$ millions unless stated. Blue = input, black = formula, orange = assumption, grey = projection. Annual columns add up the quarters.
C5: Scenario | D5: ='Key Drivers'!D5 -> Base | E5: Change on 'Key Drivers'
F6: Annual: historical | H6: Annual: projected | N6: Quarterly: historical | X6: Quarterly: projected
C7: Fiscal period | D7: Unit | E7: Note | F7: FY2024A | G7: FY2025A | H7: FY2026E | I7: FY2027E | J7: FY2028E | K7: FY2029E | L7: FY2030E | N7: Q1'24 | O7: Q2'24 | P7: Q3'24 | Q7: Q4'24 | R7: Q1'25 | S7: Q2'25 | T7: Q3'25 | U7: Q4'25 | V7: Q1'26 | W7: Q2'26 | X7: Q3'26 | Y7: Q4'26 | Z7: Q1'27 | AA7: Q2'27 | AB7: Q3'27 | AC7: Q4'27 | AD7: Q1'28 | AE7: Q2'28 | AF7: Q3'28 | AG7: Q4'28 | AH7: Q1'29 | AI7: Q2'29 | AJ7: Q3'29 | AK7: Q4'29 | AL7: Q1'30 | AM7: Q2'30 | AN7: Q3'30 | AO7: Q4'30
C8: Period end | F8: 45657 | G8: 46022 | H8: 46387 | I8: 46752 | J8: 47118 | K8: 47483 | L8: 47848 | N8: 45382 | O8: 45473 | P8: 45565 | Q8: 45657 | R8: 45747 | S8: 45838 | T8: 45930 | U8: 46022 | V8: 46112 | W8: 46203 | X8: 46295 | Y8: 46387 | Z8: 46477 | AA8: 46568 | AB8: 46660 | AC8: 46752 | AD8: 46843 | AE8: 46934 | AF8: 47026 | AG8: 47118 | AH8: 47208 | AI8: 47299 | AJ8: 47391 | AK8: 47483 | AL8: 47573 | AM8: 47664 | AN8: 47756 | AO8: 47848
C10: Revenue summary
C11: Power: equipment (gas turbine led) | E11: Gas GW shipped x revenue per GW | F11: =F69 -> 5708 | G11: =G69 -> 6686 | H11: =H69 -> 9347.4304 | I11: =I69 -> 12605.151 | J11: =J69 -> 14675.73 | K11: =K69 -> 16934.498 | L11: =L69 -> 19222.087 | N11: =N69 -> 1201 | O11: =O69 -> 1285 | P11: =P69 -> 1426 | Q11: =Q69 -> 1796 | R11: =R69 -> 1491 | S11: =S69 -> 1504 | T11: =T69 -> 1744 | U11: =U69 -> 1947 | ... AO11: =AO69 -> 5034.3573
C12: Power: services | E12: Installed-base growth | F12: =F73 -> 12525 | G12: =G73 -> 13187 | H12: =H73 -> 14032.36 | I12: =I73 -> 14733.978 | J12: =J73 -> 15397.007 | K12: =K73 -> 16012.887 | L12: =L73 -> 16653.403 | N12: =N73 -> 2860.5 | O12: =O73 -> 3196.5 | P12: =P73 -> 2806.5 | Q12: =Q73 -> 3661.5 | R12: =R73 -> 2958 | S12: =S73 -> 3281 | T12: =T73 -> 3120.5 | U12: =U73 -> 3827.5 | ... AO12: =AO73 -> 4860.3914
C13: Electrification: equipment | E13: Backlog conversion; data-centre orders | F13: =F91 -> 5534 | G13: =G91 -> 7378 | H13: =H91 -> 12631.042 | I13: =I91 -> 14584.605 | J13: =J91 -> 16832.977 | K13: =K91 -> 18984.914 | L13: =L91 -> 20935.524 | N13: =N91 -> 1230 | O13: =O91 -> 1286 | P13: =P91 -> 1451 | Q13: =Q91 -> 1567 | R13: =R91 -> 1391 | S13: =S91 -> 1673 | T13: =T91 -> 2035 | U13: =U91 -> 2279 | ... AO13: =AO91 -> 5549.3515
C14: Electrification: services | F14: =F98 -> 1860 | G14: =G98 -> 2108 | H14: =H98 -> 2181.8 | I14: =I98 -> 2290.89 | J14: =J98 -> 2405.4345 | K14: =K98 -> 2525.7062 | L14: =L98 -> 2651.9915 | N14: =N98 -> 382 | O14: =O98 -> 465 | P14: =P98 -> 438 | Q14: =Q98 -> 575 | R14: =R98 -> 449 | S14: =S98 -> 489 | T14: =T98 -> 527 | U14: =U98 -> 643 | ... AO14: =AO98 -> 812.83334
C15: Wind: equipment | E15: GW shipped x revenue per GW | F15: =F105 -> 8047 | G15: =G105 -> 7251 | H15: =H105 -> 5641.5283 | I15: =I105 -> 4408.4346 | J15: =J105 -> 3881.6832 | K15: =K105 -> 3689.8824 | L15: =L105 -> 3726.7812 | N15: =N105 -> 1232 | O15: =O105 -> 1668 | P15: =P105 -> 2494 | Q15: =Q105 -> 2653 | R15: =R105 -> 1412 | S15: =S105 -> 1797 | T15: =T105 -> 2203 | U15: =U105 -> 1839 | ... AO15: =AO105 -> 1043.4987
C16: Wind: services | F16: =F107 -> 1654 | G16: =G107 -> 1859 | H16: =H107 -> 2390.25 | I16: =I107 -> 2485.86 | J16: =J107 -> 2560.4358 | K16: =K107 -> 2637.2489 | L16: =L107 -> 2716.3663 | N16: =N107 -> 407 | O16: =O107 -> 394 | P16: =P107 -> 397 | Q16: =Q107 -> 456 | R16: =R107 -> 438 | S16: =S107 -> 448 | T16: =T107 -> 444 | U16: =U107 -> 529 | ... AO16: =AO107 -> 751.46836
C17: Eliminations and other | F17: =SUM(N17:Q17) -> -393 | G17: =SUM(R17:U17) -> -400 | H17: =SUM(V17:Y17) -> -190.61205 | I17: =SUM(Z17:AC17) -> -255.54459 | J17: =SUM(AD17:AG17) -> -278.76634 | K17: =SUM(AH17:AK17) -> -303.92569 | L17: =SUM(AL17:AO17) -> -329.53076 | N17: ='GEV Quarterly'!B90 -> -52.5 | O17: ='GEV Quarterly'!C90 -> -90.5 | P17: ='GEV Quarterly'!D90 -> -99.5 | Q17: ='GEV Quarterly'!E90 -> -150.5 | R17: ='GEV Quarterly'!F90 -> -107 | S17: ='GEV Quarterly'!G90 -> -80 | T17: ='GEV Quarterly'!H90 -> -104.5 | U17: ='GEV Quarterly'!I90 -> -108.5 | ... W17: ='GEV Quarterly'!K90 -> -37 | X17: =-'Key Drivers'!H97*SUM(X11:X16) -> -59.964846 | Y17: =-'Key Drivers'!H97*SUM(Y11:Y16) -> -68.647208 | Z17: =-'Key Drivers'!I97*SUM(Z11:Z16) -> -56.861659 | AA17: =-'Key Drivers'!I97*SUM(AA11:AA16) -> -62.66408 | AB17: =-'Key Drivers'!I97*SUM(AB11:AB16) -> -64.456989 | AC17: =-'Key Drivers'!I97*SUM(AC11:AC16) -> -71.561864 | AD17: =-'Key Drivers'!J97*SUM(AD11:AD16) -> -62.678985 | AE17: =-'Key Drivers'!J97*SUM(AE11:AE16) -> -68.360475 | AF17: =-'Key Drivers'!J97*SUM(AF11:AF16) -> -70.19334 | AG17: =-'Key Drivers'!J97*SUM(AG11:AG16) -> -77.533539 | AH17: =-'Key Drivers'!K97*SUM(AH11:AH16) -> -68.937771 | AI17: =-'Key Drivers'!K97*SUM(AI11:AI16) -> -74.707971 | AJ17: =-'Key Drivers'!K97*SUM(AJ11:AJ16) -> -76.329401 | AK17: =-'Key Drivers'!K97*SUM(AK11:AK16) -> -83.950544 | AL17: =-'Key Drivers'!L97*SUM(AL11:AL16) -> -75.482798 | AM17: =-'Key Drivers'!L97*SUM(AM11:AM16) -> -81.138869 | AN17: =-'Key Drivers'!L97*SUM(AN11:AN16) -> -82.649595 | AO17: =-'Key Drivers'!L97*SUM(AO11:AO16) -> -90.259503
C18: Total revenues | F18: =SUM(F11:F17) -> 34935 | G18: =SUM(G11:G17) -> 38069 | H18: =SUM(H11:H17) -> 46033.799 | I18: =SUM(I11:I17) -> 50853.374 | J18: =SUM(J11:J17) -> 55474.501 | K18: =SUM(K11:K17) -> 60481.212 | L18: =SUM(L11:L17) -> 65576.622 | N18: =SUM(N11:N17) -> 7260 | O18: =SUM(O11:O17) -> 8204 | P18: =SUM(P11:P17) -> 8913 | Q18: =SUM(Q11:Q17) -> 10558 | R18: =SUM(R11:R17) -> 8032 | S18: =SUM(S11:S17) -> 9112 | T18: =SUM(T11:T17) -> 9969 | U18: =SUM(U11:U17) -> 10956 | ... AO18: =SUM(AO11:AO17) -> 17961.641
C19: Growth, YoY | G19: =G18/F18-1 -> 0.08970946 | H19: =H18/G18-1 -> 0.20922007 | I19: =I18/H18-1 -> 0.10469645 | J19: =J18/I18-1 -> 0.090871602 | K19: =K18/J18-1 -> 0.09025246 | L19: =L18/K18-1 -> 0.084247826 | R19: =R18/N18-1 -> 0.10633609 | S19: =S18/O18-1 -> 0.11067772 | T19: =T18/P18-1 -> 0.11847863 | U19: =U18/Q18-1 -> 0.037696533 | V19: =V18/R18-1 -> 0.1624751 | W19: =W18/S18-1 -> 0.21850307 | X19: =X18/T18-1 -> 0.19701117 | Y19: =Y18/U18-1 -> 0.2468779 | ... AO19: =AO18/AK18-1 -> 0.07515091
C20: Check vs reported revenue (rounding) | E20: Actual quarters only | F20: =SUM(N20:Q20) -> 0 | G20: =SUM(R20:U20) -> 1 | H20: =SUM(V20:Y20) -> -3 | N20: =N18-'GEV Quarterly'!B12 -> 0 | O20: =O18-'GEV Quarterly'!C12 -> 0 | P20: =P18-'GEV Quarterly'!D12 -> 0 | Q20: =Q18-'GEV Quarterly'!E12 -> 0 | R20: =R18-'GEV Quarterly'!F12 -> 0 | S20: =S18-'GEV Quarterly'!G12 -> 1 | T20: =T18-'GEV Quarterly'!H12 -> 0 | U20: =U18-'GEV Quarterly'!I12 -> 0 | ... W20: =W18-'GEV Quarterly'!K12 -> -1
C22: Power | F22: =F11+F12 -> 18233 | G22: =G11+G12 -> 19873 | H22: =H11+H12 -> 23379.79 | I22: =I11+I12 -> 27339.129 | J22: =J11+J12 -> 30072.737 | K22: =K11+K12 -> 32947.385 | L22: =L11+L12 -> 35875.49 | N22: =N11+N12 -> 4061.5 | O22: =O11+O12 -> 4481.5 | P22: =P11+P12 -> 4232.5 | Q22: =Q11+Q12 -> 5457.5 | R22: =R11+R12 -> 4449 | S22: =S11+S12 -> 4785 | T22: =T11+T12 -> 4864.5 | U22: =U11+U12 -> 5774.5 | ... AO22: =AO11+AO12 -> 9894.7487
C23: Electrification | F23: =F13+F14 -> 7394 | G23: =G13+G14 -> 9486 | H23: =H13+H14 -> 14812.842 | I23: =I13+I14 -> 16875.495 | J23: =J13+J14 -> 19238.412 | K23: =K13+K14 -> 21510.621 | L23: =L13+L14 -> 23587.516 | N23: =N13+N14 -> 1612 | O23: =O13+O14 -> 1751 | P23: =P13+P14 -> 1889 | Q23: =Q13+Q14 -> 2142 | R23: =R13+R14 -> 1840 | S23: =S13+S14 -> 2162 | T23: =T13+T14 -> 2562 | U23: =U13+U14 -> 2922 | ... AO23: =AO13+AO14 -> 6362.1849
C24: Wind | F24: =F15+F16 -> 9701 | G24: =G15+G16 -> 9110 | H24: =H15+H16 -> 8031.7783 | I24: =I15+I16 -> 6894.2946 | J24: =J15+J16 -> 6442.119 | K24: =K15+K16 -> 6327.1312 | L24: =L15+L16 -> 6443.1475 | N24: =N15+N16 -> 1639 | O24: =O15+O16 -> 2062 | P24: =P15+P16 -> 2891 | Q24: =Q15+Q16 -> 3109 | R24: =R15+R16 -> 1850 | S24: =S15+S16 -> 2245 | T24: =T15+T16 -> 2647 | U24: =U15+U16 -> 2368 | ... AO24: =AO15+AO16 -> 1794.9671
C25: Power growth, YoY | G25: =G22/F22-1 -> 0.0899468 | H25: =H22/G22-1 -> 0.17646004 | I25: =I22/H22-1 -> 0.16934875 | J25: =J22/I22-1 -> 0.099988864 | K25: =K22/J22-1 -> 0.09558985 | L25: =L22/K22-1 -> 0.088872135 | R25: =R22/N22-1 -> 0.0954081 | S25: =S22/O22-1 -> 0.067722861 | T25: =T22/P22-1 -> 0.14932073 | U25: =U22/Q22-1 -> 0.058085204 | V25: =V22/R22-1 -> 0.11732974 | W25: =W22/S22-1 -> 0.1446186 | X25: =X22/T22-1 -> 0.19240847 | Y25: =Y22/U22-1 -> 0.23496743 | ... AO25: =AO22/AK22-1 -> 0.079565421
C26: Electrification growth, YoY | G26: =G23/F23-1 -> 0.28293211 | H26: =H23/G23-1 -> 0.56154777 | I26: =I23/H23-1 -> 0.13924763 | J26: =J23/I23-1 -> 0.14002057 | K26: =K23/J23-1 -> 0.11810793 | L26: =L23/K23-1 -> 0.096552066 | R26: =R23/N23-1 -> 0.14143921 | S26: =S23/O23-1 -> 0.23472302 | T26: =T23/P23-1 -> 0.35627316 | U26: =U23/Q23-1 -> 0.36414566 | V26: =V23/R23-1 -> 0.60815217 | W26: =W23/S23-1 -> 0.68223867 | X26: =X23/T23-1 -> 0.52257834 | Y26: =Y23/U23-1 -> 0.47706927 | ... AO26: =AO23/AK23-1 -> 0.085351044
C27: Wind growth, YoY | G27: =G24/F24-1 -> -0.060921554 | H27: =H24/G24-1 -> -0.11835584 | I27: =I24/H24-1 -> -0.14162289 | J27: =J24/I24-1 -> -0.06558693 | K27: =K24/J24-1 -> -0.017849366 | L27: =L24/K24-1 -> 0.018336318 | R27: =R24/N24-1 -> 0.12873703 | S27: =S24/O24-1 -> 0.088748788 | T27: =T24/P24-1 -> -0.084399862 | U27: =U24/Q24-1 -> -0.2383403 | V27: =V24/R24-1 -> -0.22594595 | W27: =W24/S24-1 -> -0.097550111 | X27: =X24/T24-1 -> -0.13424535 | Y27: =Y24/U24-1 -> -0.03626448 | ... AO27: =AO24/AK24-1 -> 0.018277768
C28: Equipment as % of revenue | F28: =(F11+F13+F15)/F18 -> 0.55213969 | G28: =(G11+G13+G15)/G18 -> 0.55990438 | H28: =(H11+H13+H15)/H18 -> 0.59999395 | I28: =(I11+I13+I15)/I18 -> 0.62135878 | J28: =(J11+J13+J15)/J18 -> 0.63795779 | K28: =(K11+K13+K15)/K18 -> 0.65490247 | L28: =(L11+L13+L15)/L18 -> 0.66920788 | N28: =(N11+N13+N15)/N18 -> 0.50454545 | O28: =(O11+O13+O15)/O18 -> 0.51669917 | P28: =(P11+P13+P15)/P18 -> 0.60260294 | Q28: =(Q11+Q13+Q15)/Q18 -> 0.56980489 | R28: =(R11+R13+R15)/R18 -> 0.53461155 | S28: =(S11+S13+S15)/S18 -> 0.54587357 | T28: =(T11+T13+T15)/T18 -> 0.60006019 | U28: =(U11+U13+U15)/U18 -> 0.55357795 | ... AO28: =(AO11+AO13+AO15)/AO18 -> 0.64733548
C29: Data-centre-exposed equipment, % of revenue | F29: =(F11+F13)/F18 -> 0.32179762 | G29: =(G11+G13)/G18 -> 0.36943445 | H29: =(H11+H13)/H18 -> 0.47744208 | I29: =(I11+I13)/I18 -> 0.53466965 | J29: =(J11+J13)/J18 -> 0.56798541 | K29: =(K11+K13)/K18 -> 0.59389373 | L29: =(L11+L13)/L18 -> 0.61237694 | N29: =(N11+N13)/N18 -> 0.33484848 | O29: =(O11+O13)/O18 -> 0.31338372 | P29: =(P11+P13)/P18 -> 0.32278694 | Q29: =(Q11+Q13)/Q18 -> 0.31852624 | R29: =(R11+R13)/R18 -> 0.35881474 | S29: =(S11+S13)/S18 -> 0.34866111 | T29: =(T11+T13)/T18 -> 0.37907513 | U29: =(U11+U13)/U18 -> 0.38572472 | ... AO29: =(AO11+AO13)/AO18 -> 0.58923952
C31: 1. Data-centre demand
C32: Microsoft | D32: $B | E32: Calendar-year capex; FY26E per Jul-26 guide | F32: 74.5 | G32: 108.3 | H32: 175
C33: Amazon | D33: $B | E33: Annual driver; orders phased by quarter | F33: 83.9 | G33: 134.8 | H33: 220
C34: Alphabet | D34: $B | F34: 52.9 | G34: 93 | H34: 200
C35: Meta | D35: $B | F35: 38.4 | G35: 72.6 | H35: 137.5
C36: Hyperscaler capex, big four | D36: $B | E36: FY27E+ = prior year x (1 + scenario growth) | F36: =SUM(F32:F35) -> 249.7 | G36: =SUM(G32:G35) -> 408.7 | H36: =SUM(H32:H35) -> 732.5 | I36: =H36*(1+'Key Drivers'!I11) -> 915.625 | J36: =I36*(1+'Key Drivers'!J11) -> 1007.1875 | K36: =J36*(1+'Key Drivers'!K11) -> 1057.5469 | L36: =K36*(1+'Key Drivers'!L11) -> 1089.2733
C37: Growth, YoY | G37: =G36/F36-1 -> 0.63676412 | H37: =H36/G36-1 -> 0.79226817 | I37: =I36/H36-1 -> 0.25 | J37: =J36/I36-1 -> 0.1 | K37: =K36/J36-1 -> 0.05 | L37: =L36/K36-1 -> 0.03
C39: Gas Power equipment revenue as % of hyperscaler capex | F39: =F69/(F36*1000) -> 0.022859431 | G39: =G69/(G36*1000) -> 0.016359188 | H39: =H69/(H36*1000) -> 0.012760997 | I39: =I69/(I36*1000) -> 0.013766717 | J39: =J69/(J36*1000) -> 0.014571001 | K39: =K69/(K36*1000) -> 0.016013 | L39: =L69/(L36*1000) -> 0.017646708
C40: Electrification equipment, % of hyperscaler capex | F40: =F91/(F36*1000) -> 0.022162595 | G40: =G91/(G36*1000) -> 0.018052361 | H40: =H91/(H36*1000) -> 0.017243744 | I40: =I91/(I36*1000) -> 0.015928579 | J40: =J91/(J36*1000) -> 0.016712854 | K40: =K91/(K36*1000) -> 0.017951842 | L40: =L91/(L36*1000) -> 0.019219717
C41: Data-centre-exposed equipment, % of capex | E41: Falls when capex outgrows what GEV can build | F41: =(F69+F91)/(F36*1000) -> 0.045022026 | G41: =(G69+G91)/(G36*1000) -> 0.034411549 | H41: =(H69+H91)/(H36*1000) -> 0.030004741 | I41: =(I69+I91)/(I36*1000) -> 0.029695296 | J41: =(J69+J91)/(J36*1000) -> 0.031283855 | K41: =(K69+K91)/(K36*1000) -> 0.033964842 | L41: =(L69+L91)/(L36*1000) -> 0.036866424
C43: 2. Power: gas turbines
C44: Slot reservation agreements (SRAs), not in RPO
C45: Opening SRAs | D45: GW | H45: =V45 -> 43 | I45: =Z45 -> 65.7072 | J45: =AD45 -> 68.328091 | K45: =AH45 -> 65.746196 | L45: =AL45 -> 61.501498 | V45: =U49 -> 43 | W45: =V49 -> 56 | X45: =W49 -> 63 | Y45: =X49 -> 64.44 | Z45: =Y49 -> 65.7072 | AA45: =Z49 -> 66.472212 | AB45: =AA49 -> 67.15881 | AC45: =AB49 -> 67.775032 | ... AO45: =AN49 -> 57.977038
C46: (+) New reservations signed | D46: GW | E46: Q1-Q2'26 derived from closing balance | H46: =SUM(V46:Y46) -> 54.2 | I46: =SUM(Z46:AC46) -> 30 | J46: =SUM(AD46:AG46) -> 25 | K46: =SUM(AH46:AK46) -> 22 | L46: =SUM(AL46:AO46) -> 20 | V46: =V49-V45+V47 -> 19.1 | W46: =W49-W45+W47 -> 17.1 | X46: ='Key Drivers'!H32 -> 9 | Y46: ='Key Drivers'!H32 -> 9 | Z46: ='Key Drivers'!I32 -> 7.5 | AA46: ='Key Drivers'!I32 -> 7.5 | AB46: ='Key Drivers'!I32 -> 7.5 | AC46: ='Key Drivers'!I32 -> 7.5 | AD46: ='Key Drivers'!J32 -> 6.25 | AE46: ='Key Drivers'!J32 -> 6.25 | AF46: ='Key Drivers'!J32 -> 6.25 | AG46: ='Key Drivers'!J32 -> 6.25 | AH46: ='Key Drivers'!K32 -> 5.5 | AI46: ='Key Drivers'!K32 -> 5.5 | AJ46: ='Key Drivers'!K32 -> 5.5 | AK46: ='Key Drivers'!K32 -> 5.5 | AL46: ='Key Drivers'!L32 -> 5 | AM46: ='Key Drivers'!L32 -> 5 | AN46: ='Key Drivers'!L32 -> 5 | AO46: ='Key Drivers'!L32 -> 5
C47: (-) Converted to firm orders | D47: GW | H47: =SUM(V47:Y47) -> 31.4928 | I47: =SUM(Z47:AC47) -> 25.375759 | J47: =SUM(AD47:AG47) -> 25.563708 | K47: =SUM(AH47:AK47) -> 24.324355 | L47: =SUM(AL47:AO47) -> 22.67683 | V47: =V53 -> 6.1 | W47: =W53 -> 10.1 | X47: =X45*'Key Drivers'!H37 -> 7.56 | Y47: =Y45*'Key Drivers'!H37 -> 7.7328 | Z47: =Z45*'Key Drivers'!I37 -> 6.242184 | AA47: =AA45*'Key Drivers'!I37 -> 6.3148601 | AB47: =AB45*'Key Drivers'!I37 -> 6.380087 | AC47: =AC45*'Key Drivers'!I37 -> 6.4386281 | AD47: =AD45*'Key Drivers'!J37 -> 6.4911687 | AE47: =AE45*'Key Drivers'!J37 -> 6.4195739 | AF47: =AF45*'Key Drivers'!J37 -> 6.3553176 | AG47: =AG45*'Key Drivers'!J37 -> 6.2976475 | AH47: =AH45*'Key Drivers'!K37 -> 6.2458886 | AI47: =AI45*'Key Drivers'!K37 -> 6.1281851 | AJ47: =AJ45*'Key Drivers'!K37 -> 6.0225461 | AK47: =AK45*'Key Drivers'!K37 -> 5.9277351 | AL47: =AL45*'Key Drivers'!L37 -> 5.8426423 | AM47: =AM45*'Key Drivers'!L37 -> 5.7187714 | AN47: =AN45*'Key Drivers'!L37 -> 5.6075974 | AO47: =AO45*'Key Drivers'!L37 -> 5.5078186
C48: (-) Lapsed or cancelled | D48: GW | H48: =SUM(V48:Y48) -> 0 | I48: =SUM(Z48:AC48) -> 2.0033494 | J48: =SUM(AD48:AG48) -> 2.0181874 | K48: =SUM(AH48:AK48) -> 1.9203438 | L48: =SUM(AL48:AO48) -> 1.790276 | X48: =X45*'Key Drivers'!H42 -> 0 | Y48: =Y45*'Key Drivers'!H42 -> 0 | Z48: =Z45*'Key Drivers'!I42 -> 0.492804 | AA48: =AA45*'Key Drivers'!I42 -> 0.49854159 | AB48: =AB45*'Key Drivers'!I42 -> 0.50369108 | AC48: =AC45*'Key Drivers'!I42 -> 0.50831274 | AD48: =AD45*'Key Drivers'!J42 -> 0.51246069 | AE48: =AE45*'Key Drivers'!J42 -> 0.50680847 | AF48: =AF45*'Key Drivers'!J42 -> 0.5017356 | AG48: =AG45*'Key Drivers'!J42 -> 0.4971827 | AH48: =AH45*'Key Drivers'!K42 -> 0.49309647 | AI48: =AI45*'Key Drivers'!K42 -> 0.48380408 | AJ48: =AJ45*'Key Drivers'!K42 -> 0.47546417 | AK48: =AK45*'Key Drivers'!K42 -> 0.46797909 | AL48: =AL45*'Key Drivers'!L42 -> 0.46126123 | AM48: =AM45*'Key Drivers'!L42 -> 0.45148196 | AN48: =AN45*'Key Drivers'!L42 -> 0.44270506 | AO48: =AO45*'Key Drivers'!L42 -> 0.43482779
C49: Closing SRAs | D49: GW | E49: Dec-25 43, Mar-26 56, Jun-26 63 GW | G49: =U49 -> 43 | H49: =Y49 -> 65.7072 | I49: =AC49 -> 68.328091 | J49: =AG49 -> 65.746196 | K49: =AK49 -> 61.501498 | L49: =AO49 -> 57.034392 | U49: 43 | V49: 56 | W49: 63 | X49: =X45+X46-X47-X48 -> 64.44 | Y49: =Y45+Y46-Y47-Y48 -> 65.7072 | Z49: =Z45+Z46-Z47-Z48 -> 66.472212 | AA49: =AA45+AA46-AA47-AA48 -> 67.15881 | AB49: =AB45+AB46-AB47-AB48 -> 67.775032 | AC49: =AC45+AC46-AC47-AC48 -> 68.328091 | AD49: =AD45+AD46-AD47-AD48 -> 67.574462 | AE49: =AE45+AE46-AE47-AE48 -> 66.89808 | ... AO49: =AO45+AO46-AO47-AO48 -> 57.034392
C51: Firm gas backlog (in RPO)
C52: Opening firm backlog | D52: GW | H52: =V52 -> 40 | I52: =Z52 -> 63.033833 | J52: =AD52 -> 74.542301 | K52: =AH52 -> 83.634677 | L52: =AL52 -> 88.689385 | V52: =U58 -> 40 | W52: =V58 -> 44 | X52: =W58 -> 53 | Y52: =X58 -> 58.17375 | Z52: =Y58 -> 63.033833 | AA52: =Z58 -> 66.047225 | AB52: =AA58 -> 68.943526 | AC52: =AB58 -> 71.808433 | ... AO52: =AN58 -> 89.599917
C53: (+) Orders from SRA conversions | D53: GW | H53: =SUM(V53:Y53) -> 31.4928 | I53: =SUM(Z53:AC53) -> 25.375759 | J53: =SUM(AD53:AG53) -> 25.563708 | K53: =SUM(AH53:AK53) -> 24.324355 | L53: =SUM(AL53:AO53) -> 22.67683 | V53: =V55-V54 -> 6.1 | W53: =W55-W54 -> 10.1 | X53: =X47 -> 7.56 | Y53: =Y47 -> 7.7328 | Z53: =Z47 -> 6.242184 | AA53: =AA47 -> 6.3148601 | AB53: =AB47 -> 6.380087 | AC53: =AC47 -> 6.4386281 | AD53: =AD47 -> 6.4911687 | AE53: =AE47 -> 6.4195739 | ... AO53: =AO47 -> 5.5078186
C54: (+) Direct firm orders | D54: GW | E54: Q2'26: 2 GW (company). Q1'26: estimate | H54: =SUM(V54:Y54) -> 8 | I54: =SUM(Z54:AC54) -> 6 | J54: =SUM(AD54:AG54) -> 6 | K54: =SUM(AH54:AK54) -> 6 | L54: =SUM(AL54:AO54) -> 6 | V54: 2 | W54: 2 | X54: ='Key Drivers'!H47 -> 2 | Y54: ='Key Drivers'!H47 -> 2 | Z54: ='Key Drivers'!I47 -> 1.5 | AA54: ='Key Drivers'!I47 -> 1.5 | AB54: ='Key Drivers'!I47 -> 1.5 | AC54: ='Key Drivers'!I47 -> 1.5 | AD54: ='Key Drivers'!J47 -> 1.5 | AE54: ='Key Drivers'!J47 -> 1.5 | AF54: ='Key Drivers'!J47 -> 1.5 | AG54: ='Key Drivers'!J47 -> 1.5 | AH54: ='Key Drivers'!K47 -> 1.5 | AI54: ='Key Drivers'!K47 -> 1.5 | AJ54: ='Key Drivers'!K47 -> 1.5 | AK54: ='Key Drivers'!K47 -> 1.5 | AL54: ='Key Drivers'!L47 -> 1.5 | AM54: ='Key Drivers'!L47 -> 1.5 | AN54: ='Key Drivers'!L47 -> 1.5 | AO54: ='Key Drivers'!L47 -> 1.5
C55: Gas turbine orders, total | D55: GW | E55: Actuals: GEV Quarterly row 256 | F55: =SUM(N55:Q55) -> 20.2 | G55: =SUM(R55:U55) -> 29.8 | H55: =SUM(V55:Y55) -> 39.4928 | I55: =SUM(Z55:AC55) -> 31.375759 | J55: =SUM(AD55:AG55) -> 31.563708 | K55: =SUM(AH55:AK55) -> 30.324355 | L55: =SUM(AL55:AO55) -> 28.67683 | N55: ='GEV Quarterly'!B256 -> 4.9 | O55: ='GEV Quarterly'!C256 -> 4.1 | P55: ='GEV Quarterly'!D256 -> 5.1 | Q55: ='GEV Quarterly'!E256 -> 6.1 | R55: ='GEV Quarterly'!F256 -> 7.1 | S55: ='GEV Quarterly'!G256 -> 5.1 | T55: ='GEV Quarterly'!H256 -> 7.4 | U55: ='GEV Quarterly'!I256 -> 10.2 | ... W55: ='GEV Quarterly'!K256 -> 12.1 | X55: =X53+X54 -> 9.56 | Y55: =Y53+Y54 -> 9.7328 | Z55: =Z53+Z54 -> 7.742184 | AA55: =AA53+AA54 -> 7.8148601 | AB55: =AB53+AB54 -> 7.880087 | AC55: =AC53+AC54 -> 7.9386281 | AD55: =AD53+AD54 -> 7.9911687 | AE55: =AE53+AE54 -> 7.9195739 | ... AO55: =AO53+AO54 -> 7.0078186
C56: (-) Cancelled or deferred out | D56: GW | E56: Actuals: reconciling item | H56: =SUM(V56:Y56) -> -0.16103281 | I56: =SUM(Z56:AC56) -> 0.33729127 | J56: =SUM(AD56:AG56) -> 0.39133145 | K56: =SUM(AH56:AK56) -> 0.42964713 | L56: =SUM(AL56:AO56) -> 0.44647848 | V56: =V52+V55-V57-V58 -> -0.1 | W56: =W52+W55-W57-W58 -> -0.2 | X56: =X52*'Key Drivers'!H52 -> 0.06625 | Y56: =Y52*'Key Drivers'!H52 -> 0.072717188 | Z56: =Z52*'Key Drivers'!I52 -> 0.078792291 | AA56: =AA52*'Key Drivers'!I52 -> 0.082559031 | AB56: =AB52*'Key Drivers'!I52 -> 0.086179407 | AC56: =AC52*'Key Drivers'!I52 -> 0.089760541 | AD56: =AD52*'Key Drivers'!J52 -> 0.093177876 | AE56: =AE52*'Key Drivers'!J52 -> 0.096495364 | AF56: =AF52*'Key Drivers'!J52 -> 0.099489213 | AG56: =AG52*'Key Drivers'!J52 -> 0.102169 | AH56: =AH52*'Key Drivers'!K52 -> 0.10454335 | AI56: =AI52*'Key Drivers'!K52 -> 0.10673503 | AJ56: =AJ52*'Key Drivers'!K52 -> 0.10848934 | AK56: =AK52*'Key Drivers'!K52 -> 0.10987941 | AL56: =AL52*'Key Drivers'!L52 -> 0.11086173 | AM56: =AM52*'Key Drivers'!L52 -> 0.11162146 | AN56: =AN52*'Key Drivers'!L52 -> 0.11199539 | AO56: =AO52*'Key Drivers'!L52 -> 0.1119999
C57: (-) Shipments | D57: GW | E57: Forecast: MIN(capacity x ship %, backlog) | F57: =SUM(N57:Q57) -> 11.9 | G57: =SUM(R57:U57) -> 15.3 | H57: =SUM(V57:Y57) -> 16.62 | I57: =SUM(Z57:AC57) -> 19.53 | J57: =SUM(AD57:AG57) -> 22.08 | K57: =SUM(AH57:AK57) -> 24.84 | L57: =SUM(AL57:AO57) -> 27.6 | N57: ='GEV Quarterly'!B262 -> 2.3 | O57: ='GEV Quarterly'!C262 -> 1.5 | P57: ='GEV Quarterly'!D262 -> 3.3 | Q57: ='GEV Quarterly'!E262 -> 4.8 | R57: ='GEV Quarterly'!F262 -> 3 | S57: ='GEV Quarterly'!G262 -> 5.2 | T57: ='GEV Quarterly'!H262 -> 4 | U57: ='GEV Quarterly'!I262 -> 3.1 | ... W57: ='GEV Quarterly'!K262 -> 3.3 | X57: =MIN(X60*X61,X52-X56) -> 4.32 | Y57: =MIN(Y60*Y61,Y52-Y56) -> 4.8 | Z57: =MIN(Z60*Z61,Z52-Z56) -> 4.65 | AA57: =MIN(AA60*AA61,AA52-AA56) -> 4.836 | AB57: =MIN(AB60*AB61,AB52-AB56) -> 4.929 | AC57: =MIN(AC60*AC61,AC52-AC56) -> 5.115 | AD57: =MIN(AD60*AD61,AD52-AD56) -> 5.244 | AE57: =MIN(AE60*AE61,AE52-AE56) -> 5.428 | ... AO57: =MIN(AO60*AO61,AO52-AO56) -> 7.176
C58: Closing firm backlog | D58: GW | E58: Dec-25 40, Mar-26 44, Jun-26 53 GW | G58: =U58 -> 40 | H58: =Y58 -> 63.033833 | I58: =AC58 -> 74.542301 | J58: =AG58 -> 83.634677 | K58: =AK58 -> 88.689385 | L58: =AO58 -> 89.319736 | U58: 40 | V58: 44 | W58: 53 | X58: =X52+X55-X56-X57 -> 58.17375 | Y58: =Y52+Y55-Y56-Y57 -> 63.033833 | Z58: =Z52+Z55-Z56-Z57 -> 66.047225 | AA58: =AA52+AA55-AA56-AA57 -> 68.943526 | AB58: =AB52+AB55-AB56-AB57 -> 71.808433 | AC58: =AC52+AC55-AC56-AC57 -> 74.542301 | AD58: =AD52+AD55-AD56-AD57 -> 77.196292 | AE58: =AE52+AE55-AE56-AE57 -> 79.59137 | ... AO58: =AO52+AO55-AO56-AO57 -> 89.319736
C60: Factory capacity | D60: GW | E60: Fixed plan (Key Drivers). FY26E = H2 only | H60: =SUM(V60:Y60) -> 9.5 | I60: =SUM(Z60:AC60) -> 21 | J60: =SUM(AD60:AG60) -> 24 | K60: =SUM(AH60:AK60) -> 27 | L60: =SUM(AL60:AO60) -> 30 | X60: ='Key Drivers'!X95 -> 4.5 | Y60: ='Key Drivers'!Y95 -> 5 | Z60: ='Key Drivers'!Z95 -> 5 | AA60: ='Key Drivers'!AA95 -> 5.2 | AB60: ='Key Drivers'!AB95 -> 5.3 | AC60: ='Key Drivers'!AC95 -> 5.5 | AD60: ='Key Drivers'!AD95 -> 5.7 | AE60: ='Key Drivers'!AE95 -> 5.9 | ... AO60: ='Key Drivers'!AO95 -> 7.8
C61: Shipments as % of capacity | I61: =I57/I60 -> 0.93 | J61: =J57/J60 -> 0.92 | K61: =K57/K60 -> 0.92 | L61: =L57/L60 -> 0.92 | X61: ='Key Drivers'!H57 -> 0.96 | Y61: ='Key Drivers'!H57 -> 0.96 | Z61: ='Key Drivers'!I57 -> 0.93 | AA61: ='Key Drivers'!I57 -> 0.93 | AB61: ='Key Drivers'!I57 -> 0.93 | AC61: ='Key Drivers'!I57 -> 0.93 | AD61: ='Key Drivers'!J57 -> 0.92 | AE61: ='Key Drivers'!J57 -> 0.92 | AF61: ='Key Drivers'!J57 -> 0.92 | AG61: ='Key Drivers'!J57 -> 0.92 | AH61: ='Key Drivers'!K57 -> 0.92 | AI61: ='Key Drivers'!K57 -> 0.92 | AJ61: ='Key Drivers'!K57 -> 0.92 | AK61: ='Key Drivers'!K57 -> 0.92 | AL61: ='Key Drivers'!L57 -> 0.92 | AM61: ='Key Drivers'!L57 -> 0.92 | AN61: ='Key Drivers'!L57 -> 0.92 | AO61: ='Key Drivers'!L57 -> 0.92
C62: Book-to-bill (GW ordered / GW shipped) | D62: x | F62: =F55/F57 -> 1.697479 | G62: =G55/G57 -> 1.9477124 | H62: =H55/H57 -> 2.3762214 | I62: =I55/I57 -> 1.6065417 | J62: =J55/J57 -> 1.4295157 | K62: =K55/K57 -> 1.2207872 | L62: =L55/L57 -> 1.0390156 | N62: =N55/N57 -> 2.1304348 | O62: =O55/O57 -> 2.7333333 | P62: =P55/P57 -> 1.5454545 | Q62: =Q55/Q57 -> 1.2708333 | R62: =R55/R57 -> 2.3666667 | S62: =S55/S57 -> 0.98076923 | T62: =T55/T57 -> 1.85 | U62: =U55/U57 -> 3.2903226 | ... AO62: =AO55/AO57 -> 0.97656335
C63: Firm backlog + SRAs | D63: GW | E63: Company target: at least 125 GW by YE26 | G63: =G58+G49 -> 83 | H63: =H58+H49 -> 128.74103 | I63: =I58+I49 -> 142.87039 | J63: =J58+J49 -> 149.38087 | K63: =K58+K49 -> 150.19088 | L63: =L58+L49 -> 146.35413 | U63: =U58+U49 -> 83 | V63: =V58+V49 -> 100 | W63: =W58+W49 -> 116 | X63: =X58+X49 -> 122.61375 | Y63: =Y58+Y49 -> 128.74103 | Z63: =Z58+Z49 -> 132.51944 | AA63: =AA58+AA49 -> 136.10234 | AB63: =AB58+AB49 -> 139.58347 | ... AO63: =AO58+AO49 -> 146.35413
C64: Firm backlog in years of shipments | D64: yrs | E64: Quarterly columns use annualised shipments | G64: =G58/G57 -> 2.6143791 | H64: =H58/H57 -> 3.7926494 | I64: =I58/I57 -> 3.8168101 | J64: =J58/J57 -> 3.7878024 | K64: =K58/K57 -> 3.5704261 | L64: =L58/L57 -> 3.2362223 | U64: =U58/(U57*4) -> 3.2258065 | V64: =V58/(V57*4) -> 2.6190476 | W64: =W58/(W57*4) -> 4.0151515 | X64: =X58/(X57*4) -> 3.3665365 | Y64: =Y58/(Y57*4) -> 3.2830121 | Z64: =Z58/(Z57*4) -> 3.550926 | AA64: =AA58/(AA57*4) -> 3.564078 | AB64: =AB58/(AB57*4) -> 3.64214 | ... AO64: =AO58/(AO57*4) -> 3.1117522
C65: Firm backlog + SRAs in years of shipments | D65: yrs | G65: =G63/G57 -> 5.4248366 | H65: =H63/H57 -> 7.7461512 | I65: =I63/I57 -> 7.3154323 | J65: =J63/J57 -> 6.7654381 | K65: =K63/K57 -> 6.0463318 | L65: =L63/L57 -> 5.3026858 | U65: =U63/(U57*4) -> 6.6935484 | V65: =V63/(V57*4) -> 5.952381 | W65: =W63/(W57*4) -> 8.7878788 | X65: =X63/(X57*4) -> 7.0957031 | Y65: =Y63/(Y57*4) -> 6.7052621 | Z65: =Z63/(Z57*4) -> 7.1247009 | AA65: =AA63/(AA57*4) -> 7.0358941 | AB65: =AB63/(AB57*4) -> 7.0797051 | ... AO65: =AO63/(AO57*4) -> 5.0987363
C67: Power equipment revenue per GW shipped | D67: $mm/GW | E67: Quarterly actuals are noisy | F67: =F69/F57 -> 479.66387 | G67: =G69/G57 -> 436.99346 | H67: =H69/H57 -> 562.4206 | I67: =I69/I57 -> 645.42502 | J67: =J69/J57 -> 664.66168 | K67: =K69/K57 -> 681.74308 | L67: =L69/L57 -> 696.45243 | N67: =N69/N57 -> 522.17391 | O67: =O69/O57 -> 856.66667 | P67: =P69/P57 -> 432.12121 | Q67: =Q69/Q57 -> 374.16667 | R67: =R69/R57 -> 497 | S67: =S69/S57 -> 289.23077 | T67: =T69/T57 -> 436 | U67: =U69/U57 -> 628.06452 | ... W67: =W69/W57 -> 595.45455 | X67: =((V69+W69)/(V57+W57))*(1+'Key Drivers'!H62) -> 569.8 | Y67: =X67*(1+'Key Drivers'!H62) -> 632.478 | Z67: =Y67*(1+'Key Drivers'!I62) -> 637.53782 | AA67: =Z67*(1+'Key Drivers'!I62) -> 642.63813 | AB67: =AA67*(1+'Key Drivers'!I62) -> 647.77923 | AC67: =AB67*(1+'Key Drivers'!I62) -> 652.96147 | AD67: =AC67*(1+'Key Drivers'!J62) -> 657.5322 | AE67: =AD67*(1+'Key Drivers'!J62) -> 662.13492 | AF67: =AE67*(1+'Key Drivers'!J62) -> 666.76987 | AG67: =AF67*(1+'Key Drivers'!J62) -> 671.43725 | AH67: =AG67*(1+'Key Drivers'!K62) -> 675.46588 | AI67: =AH67*(1+'Key Drivers'!K62) -> 679.51867 | AJ67: =AI67*(1+'Key Drivers'!K62) -> 683.59579 | AK67: =AJ67*(1+'Key Drivers'!K62) -> 687.69736 | AL67: =AK67*(1+'Key Drivers'!L62) -> 691.13585 | AM67: =AL67*(1+'Key Drivers'!L62) -> 694.59153 | AN67: =AM67*(1+'Key Drivers'!L62) -> 698.06448 | AO67: =AN67*(1+'Key Drivers'!L62) -> 701.55481
C68: Growth, YoY | G68: =G67/F67-1 -> -0.088958966 | H68: =H67/G67-1 -> 0.28702291 | I68: =I67/H67-1 -> 0.14758424 | J68: =J67/I67-1 -> 0.029804651 | K68: =K67/J67-1 -> 0.025699384 | L68: =L67/K67-1 -> 0.021576091 | R68: =R67/N67-1 -> -0.048209825 | S68: =S67/O67-1 -> -0.66237653 | T68: =T67/P67-1 -> 0.0089761571 | U68: =U67/Q67-1 -> 0.67856886 | V68: =V67/R67-1 -> -0.096962729 | W68: =W67/S67-1 -> 1.0587524 | X68: =X67/T67-1 -> 0.30688073 | Y68: =Y67/U67-1 -> 0.0070271186 | ... AO68: =AO67/AK67-1 -> 0.020150501
C69: Power equipment revenue | E69: GW shipped x revenue per GW | F69: =SUM(N69:Q69) -> 5708 | G69: =SUM(R69:U69) -> 6686 | H69: =SUM(V69:Y69) -> 9347.4304 | I69: =SUM(Z69:AC69) -> 12605.151 | J69: =SUM(AD69:AG69) -> 14675.73 | K69: =SUM(AH69:AK69) -> 16934.498 | L69: =SUM(AL69:AO69) -> 19222.087 | N69: ='GEV Quarterly'!B130 -> 1201 | O69: ='GEV Quarterly'!C130 -> 1285 | P69: ='GEV Quarterly'!D130 -> 1426 | Q69: ='GEV Quarterly'!E130 -> 1796 | R69: ='GEV Quarterly'!F130 -> 1491 | S69: ='GEV Quarterly'!G130 -> 1504 | T69: ='GEV Quarterly'!H130 -> 1744 | U69: ='GEV Quarterly'!I130 -> 1947 | V69: ='GEV Quarterly'!J182 -> 1885 | W69: ='GEV Quarterly'!K182 -> 1965 | X69: =X57*X67 -> 2461.536 | Y69: =Y57*Y67 -> 3035.8944 | Z69: =Z57*Z67 -> 2964.5509 | AA69: =AA57*AA67 -> 3107.798 | AB69: =AB57*AB67 -> 3192.9038 | AC69: =AC57*AC67 -> 3339.8979 | AD69: =AD57*AD67 -> 3448.0988 | AE69: =AE57*AE67 -> 3594.0684 | ... AO69: =AO57*AO67 -> 5034.3573
C70: Growth, YoY | G70: =G69/F69-1 -> 0.17133847 | H70: =H69/G69-1 -> 0.39806019 | I70: =I69/H69-1 -> 0.34851505 | J70: =J69/I69-1 -> 0.16426455 | K70: =K69/J69-1 -> 0.15391181 | L70: =L69/K69-1 -> 0.13508455 | R70: =R69/N69-1 -> 0.24146545 | S70: =S69/O69-1 -> 0.17042802 | T70: =T69/P69-1 -> 0.2230014 | U70: =U69/Q69-1 -> 0.084075724 | V70: =V69/R69-1 -> 0.26425218 | W70: =W69/S69-1 -> 0.30651596 | X70: =X69/T69-1 -> 0.41143119 | Y70: =Y69/U69-1 -> 0.5592678 | ... AO70: =AO69/AK69-1 -> 0.12072872
C72: Power: services
C73: Power services revenue | E73: Power revenue less equipment | F73: =SUM(N73:Q73) -> 12525 | G73: =SUM(R73:U73) -> 13187 | H73: =SUM(V73:Y73) -> 14032.36 | I73: =SUM(Z73:AC73) -> 14733.978 | J73: =SUM(AD73:AG73) -> 15397.007 | K73: =SUM(AH73:AK73) -> 16012.887 | L73: =SUM(AL73:AO73) -> 16653.403 | N73: ='GEV Quarterly'!B87-'GEV Quarterly'!B130 -> 2860.5 | O73: ='GEV Quarterly'!C87-'GEV Quarterly'!C130 -> 3196.5 | P73: ='GEV Quarterly'!D87-'GEV Quarterly'!D130 -> 2806.5 | Q73: ='GEV Quarterly'!E87-'GEV Quarterly'!E130 -> 3661.5 | R73: ='GEV Quarterly'!F87-'GEV Quarterly'!F130 -> 2958 | S73: ='GEV Quarterly'!G87-'GEV Quarterly'!G130 -> 3281 | T73: ='GEV Quarterly'!H87-'GEV Quarterly'!H130 -> 3120.5 | U73: ='GEV Quarterly'!I87-'GEV Quarterly'!I130 -> 3827.5 | V73: ='GEV Quarterly'!J87-'GEV Quarterly'!J182 -> 3086 | W73: ='GEV Quarterly'!K87-'GEV Quarterly'!K182 -> 3512 | X73: =T73*(1+'Key Drivers'!H68) -> 3338.935 | Y73: =U73*(1+'Key Drivers'!H68) -> 4095.425 | Z73: =V73*(1+'Key Drivers'!I68) -> 3240.3 | AA73: =W73*(1+'Key Drivers'!I68) -> 3687.6 | AB73: =X73*(1+'Key Drivers'!I68) -> 3505.8818 | AC73: =Y73*(1+'Key Drivers'!I68) -> 4300.1962 | AD73: =Z73*(1+'Key Drivers'!J68) -> 3386.1135 | AE73: =AA73*(1+'Key Drivers'!J68) -> 3853.542 | AF73: =AB73*(1+'Key Drivers'!J68) -> 3663.6464 | AG73: =AC73*(1+'Key Drivers'!J68) -> 4493.7051 | AH73: =AD73*(1+'Key Drivers'!K68) -> 3521.558 | AI73: =AE73*(1+'Key Drivers'!K68) -> 4007.6837 | AJ73: =AF73*(1+'Key Drivers'!K68) -> 3810.1923 | AK73: =AG73*(1+'Key Drivers'!K68) -> 4673.4533 | AL73: =AH73*(1+'Key Drivers'!L68) -> 3662.4204 | AM73: =AI73*(1+'Key Drivers'!L68) -> 4167.991 | AN73: =AJ73*(1+'Key Drivers'!L68) -> 3962.6 | AO73: =AK73*(1+'Key Drivers'!L68) -> 4860.3914
C74: Growth, YoY | G74: =G73/F73-1 -> 0.052854291 | H74: =H73/G73-1 -> 0.064105559 | I74: =I73/H73-1 -> 0.05 | J74: =J73/I73-1 -> 0.045 | K74: =K73/J73-1 -> 0.04 | L74: =L73/K73-1 -> 0.04 | R74: =R73/N73-1 -> 0.03408495 | S74: =S73/O73-1 -> 0.026435163 | T74: =T73/P73-1 -> 0.11188313 | U74: =U73/Q73-1 -> 0.045336611 | V74: =V73/R73-1 -> 0.043272481 | W74: =W73/S73-1 -> 0.070405364 | X74: =X73/T73-1 -> 0.07 | Y74: =Y73/U73-1 -> 0.07 | ... AO74: =AO73/AK73-1 -> 0.04
C75: Power services RPO (period end) | E75: Dec-25, Mar-26 and Jun-26 only | G75: =U75 -> 69841 | U75: ='GEV Quarterly'!I237 -> 69841 | V75: ='GEV Quarterly'!J237 -> 71164 | W75: ='GEV Quarterly'!K237 -> 72388
C77: 3. Electrification
C78: Hyperscaler capex | E78: Annual driver | F78: =F36*1000 -> 249700 | G78: =G36*1000 -> 408700 | H78: =H36*1000 -> 732500 | I78: =I36*1000 -> 915625 | J78: =J36*1000 -> 1007187.5 | K78: =K36*1000 -> 1057546.9 | L78: =L36*1000 -> 1089273.3
C79: Data-centre orders as % of capex | E79: Scenario driver (Key Drivers). Annual rate | G79: =G82/G78 -> 0.005872278 | H79: ='Key Drivers'!H16 -> 0.0143 | I79: ='Key Drivers'!I16 -> 0.0145 | J79: ='Key Drivers'!J16 -> 0.0145 | K79: ='Key Drivers'!K16 -> 0.014 | L79: ='Key Drivers'!L16 -> 0.014
C80: Data-centre orders, annual target (capex x rate) | E80: H2 = target less H1 actual | H80: =H78*H79 -> 10474.75 | I80: =I78*I79 -> 13276.562 | J80: =J78*J79 -> 14604.219 | K80: =K78*K79 -> 14805.656 | L80: =L78*L79 -> 15249.826
C81: Other equipment orders, annual target | E81: FY25 = implied orders less data-centre | G81: =G84-G82 -> 15481 | H81: =G81*(1+'Key Drivers'!H21) -> 14242.52 | I81: =H81*(1+'Key Drivers'!I21) -> 14954.646 | J81: =I81*(1+'Key Drivers'!J21) -> 15702.378 | K81: =J81*(1+'Key Drivers'!K21) -> 16330.473 | L81: =K81*(1+'Key Drivers'!L21) -> 16820.388
C82: Data-centre orders (Electrification) | E82: Annual target x quarterly phasing | G82: 2400 | H82: =SUM(V82:Y82) -> 10474.75 | I82: =SUM(Z82:AC82) -> 13276.562 | J82: =SUM(AD82:AG82) -> 14604.219 | K82: =SUM(AH82:AK82) -> 14805.656 | L82: =SUM(AL82:AO82) -> 15249.826 | V82: 2300 | W82: 2700 | X82: =(H80-SUM(V82:W82))*'Key Drivers'!$H$100/('Key Drivers'!$H$100+'Key Drivers'!$I$100) -> 2412.6017 | Y82: =(H80-SUM(V82:W82))*'Key Drivers'!$I$100/('Key Drivers'!$H$100+'Key Drivers'!$I$100) -> 3062.1483 | Z82: =I80*'Key Drivers'!$F$100 -> 2655.3125 | AA82: =I80*'Key Drivers'!$G$100 -> 2788.0781 | AB82: =I80*'Key Drivers'!$H$100 -> 3451.9062 | AC82: =I80*'Key Drivers'!$I$100 -> 4381.2656 | AD82: =J80*'Key Drivers'!$F$100 -> 2920.8438 | AE82: =J80*'Key Drivers'!$G$100 -> 3066.8859 | AF82: =J80*'Key Drivers'!$H$100 -> 3797.0969 | AG82: =J80*'Key Drivers'!$I$100 -> 4819.3922 | AH82: =K80*'Key Drivers'!$F$100 -> 2961.1312 | AI82: =K80*'Key Drivers'!$G$100 -> 3109.1878 | AJ82: =K80*'Key Drivers'!$H$100 -> 3849.4706 | AK82: =K80*'Key Drivers'!$I$100 -> 4885.8666 | AL82: =L80*'Key Drivers'!$F$100 -> 3049.9652 | AM82: =L80*'Key Drivers'!$G$100 -> 3202.4634 | AN82: =L80*'Key Drivers'!$H$100 -> 3964.9547 | AO82: =L80*'Key Drivers'!$I$100 -> 5032.4426
C83: Other equipment orders (grid, power conversion, other) | G83: =G81 -> 15481 | H83: =SUM(V83:Y83) -> 14242.52 | I83: =SUM(Z83:AC83) -> 14954.646 | J83: =SUM(AD83:AG83) -> 15702.378 | K83: =SUM(AH83:AK83) -> 16330.473 | L83: =SUM(AL83:AO83) -> 16820.388 | V83: =V84-V82 -> 3291 | W83: =W84-W82 -> 2421 | X83: =(H81-SUM(V83:W83))*'Key Drivers'!$H$100/('Key Drivers'!$H$100+'Key Drivers'!$I$100) -> 3759.2122 | Y83: =(H81-SUM(V83:W83))*'Key Drivers'!$I$100/('Key Drivers'!$H$100+'Key Drivers'!$I$100) -> 4771.3078 | Z83: =I81*'Key Drivers'!$F$100 -> 2990.9292 | AA83: =I81*'Key Drivers'!$G$100 -> 3140.4757 | AB83: =I81*'Key Drivers'!$H$100 -> 3888.208 | AC83: =I81*'Key Drivers'!$I$100 -> 4935.0332 | AD83: =J81*'Key Drivers'!$F$100 -> 3140.4757 | AE83: =J81*'Key Drivers'!$G$100 -> 3297.4994 | AF83: =J81*'Key Drivers'!$H$100 -> 4082.6184 | AG83: =J81*'Key Drivers'!$I$100 -> 5181.7848 | AH83: =K81*'Key Drivers'!$F$100 -> 3266.0947 | AI83: =K81*'Key Drivers'!$G$100 -> 3429.3994 | AJ83: =K81*'Key Drivers'!$H$100 -> 4245.9231 | AK83: =K81*'Key Drivers'!$I$100 -> 5389.0562 | AL83: =L81*'Key Drivers'!$F$100 -> 3364.0775 | AM83: =L81*'Key Drivers'!$G$100 -> 3532.2814 | AN83: =L81*'Key Drivers'!$H$100 -> 4373.3008 | AO83: =L81*'Key Drivers'!$I$100 -> 5550.7279
C84: Organic equipment orders | E84: Change in RPO + revenue - acquired | G84: =SUM(R84:U84) -> 17881 | H84: =SUM(V84:Y84) -> 24717.27 | I84: =SUM(Z84:AC84) -> 28231.209 | J84: =SUM(AD84:AG84) -> 30306.597 | K84: =SUM(AH84:AK84) -> 31136.13 | L84: =SUM(AL84:AO84) -> 32070.214 | O84: =O92-N92-O89+O91 -> 3977 | P84: =P92-O92-P89+P91 -> 2535 | Q84: =Q92-P92-Q89+Q91 -> 2948 | R84: =R92-Q92-R89+R91 -> 3382 | S84: =S92-R92-S89+S91 -> 3627 | T84: =T92-S92-T89+T91 -> 4540 | U84: =U92-T92-U89+U91 -> 6332 | V84: =V92-U92-V89+V91 -> 5591 | W84: =W92-V92-W89+W91 -> 5121 | X84: =X82+X83 -> 6171.8139 | Y84: =Y82+Y83 -> 7833.4561 | Z84: =Z82+Z83 -> 5646.2417 | AA84: =AA82+AA83 -> 5928.5538 | AB84: =AB82+AB83 -> 7340.1142 | AC84: =AC82+AC83 -> 9316.2988 | AD84: =AD82+AD83 -> 6061.3194 | AE84: =AE82+AE83 -> 6364.3854 | ... AO84: =AO82+AO83 -> 10583.17
C85: Data-centre share of equipment orders | G85: =G82/G84 -> 0.13422068 | H85: =H82/H84 -> 0.42378264 | I85: =I82/I84 -> 0.47027964 | J85: =J82/J84 -> 0.4818825 | K85: =K82/K84 -> 0.4755137 | L85: =L82/L84 -> 0.4755137 | V85: =V82/V84 -> 0.41137542 | W85: =W82/W84 -> 0.52724077 | X85: =X82/X84 -> 0.39090642 | Y85: =Y82/Y84 -> 0.39090642 | Z85: =Z82/Z84 -> 0.47027964 | AA85: =AA82/AA84 -> 0.47027964 | AB85: =AB82/AB84 -> 0.47027964 | AC85: =AC82/AC84 -> 0.47027964 | ... AO85: =AO82/AO84 -> 0.4755137
C87: Equipment backlog roll-forward
C88: Opening equipment backlog (RPO) | G88: =R88 -> 20005 | H88: =V88 -> 30508 | I88: =Z88 -> 47594.228 | J88: =AD88 -> 61240.831 | K88: =AH88 -> 74714.451 | L88: =AL88 -> 86865.666 | O88: =N92 -> 14849 | P88: =O92 -> 17540 | Q88: =P92 -> 18624 | R88: =Q92 -> 20005 | S88: =R92 -> 21996 | T88: =S92 -> 23950 | U88: =T92 -> 26455 | V88: =U92 -> 30508 | ... AO88: =AN92 -> 92966.537
C89: (+) Acquired backlog (Prolec GE) | E89: Consolidated Q1'26; $5B per Q2'26 release | H89: =SUM(V89:Y89) -> 5000 | V89: 5000
C90: (+) Organic equipment orders | G90: =SUM(R90:U90) -> 17881 | H90: =SUM(V90:Y90) -> 24717.27 | I90: =SUM(Z90:AC90) -> 28231.209 | J90: =SUM(AD90:AG90) -> 30306.597 | K90: =SUM(AH90:AK90) -> 31136.13 | L90: =SUM(AL90:AO90) -> 32070.214 | O90: =O84 -> 3977 | P90: =P84 -> 2535 | Q90: =Q84 -> 2948 | R90: =R84 -> 3382 | S90: =S84 -> 3627 | T90: =T84 -> 4540 | U90: =U84 -> 6332 | V90: =V84 -> 5591 | ... AO90: =AO84 -> 10583.17
C91: (-) Equipment revenue | E91: % of opening backlog + in-quarter orders | F91: =SUM(N91:Q91) -> 5534 | G91: =SUM(R91:U91) -> 7378 | H91: =SUM(V91:Y91) -> 12631.042 | I91: =SUM(Z91:AC91) -> 14584.605 | J91: =SUM(AD91:AG91) -> 16832.977 | K91: =SUM(AH91:AK91) -> 18984.914 | L91: =SUM(AL91:AO91) -> 20935.524 | N91: ='GEV Quarterly'!B140 -> 1230 | O91: ='GEV Quarterly'!C140 -> 1286 | P91: ='GEV Quarterly'!D140 -> 1451 | Q91: ='GEV Quarterly'!E140 -> 1567 | R91: ='GEV Quarterly'!F140 -> 1391 | S91: ='GEV Quarterly'!G140 -> 1673 | T91: ='GEV Quarterly'!H140 -> 2035 | U91: ='GEV Quarterly'!I140 -> 2279 | V91: ='GEV Quarterly'!J191 -> 2501 | W91: ='GEV Quarterly'!K191 -> 3130 | X91: ='Key Drivers'!H26*(X88+X89)+'Key Drivers'!H96*X90 -> 3352.7657 | Y91: ='Key Drivers'!H26*(Y88+Y89)+'Key Drivers'!H96*Y90 -> 3647.2764 | Z91: ='Key Drivers'!I26*(Z88+Z89)+'Key Drivers'!I96*Z90 -> 3328.3427 | AA91: ='Key Drivers'!I26*(AA88+AA89)+'Key Drivers'!I96*AA90 -> 3490.8038 | AB91: ='Key Drivers'!I26*(AB88+AB89)+'Key Drivers'!I96*AB90 -> 3717.3978 | AC91: ='Key Drivers'!I26*(AC88+AC89)+'Key Drivers'!I96*AC90 -> 4048.0609 | AD91: ='Key Drivers'!J26*(AD88+AD89)+'Key Drivers'!J96*AD90 -> 3916.275 | AE91: ='Key Drivers'!J26*(AE88+AE89)+'Key Drivers'!J96*AE90 -> 4057.9859 | AF91: ='Key Drivers'!J26*(AF88+AF89)+'Key Drivers'!J96*AF90 -> 4269.83 | AG91: ='Key Drivers'!J26*(AG88+AG89)+'Key Drivers'!J96*AG90 -> 4588.8863 | AH91: ='Key Drivers'!K26*(AH88+AH89)+'Key Drivers'!K96*AH90 -> 4495.3706 | AI91: ='Key Drivers'!K26*(AI88+AI89)+'Key Drivers'!K96*AI90 -> 4607.9225 | AJ91: ='Key Drivers'!K26*(AJ88+AJ89)+'Key Drivers'!K96*AJ90 -> 4793.8801 | AK91: ='Key Drivers'!K26*(AK88+AK89)+'Key Drivers'!K96*AK90 -> 5087.7413 | AL91: ='Key Drivers'!L26*(AL88+AL89)+'Key Drivers'!L96*AL90 -> 5011.4481 | AM91: ='Key Drivers'!L26*(AM88+AM89)+'Key Drivers'!L96*AM90 -> 5103.2233 | AN91: ='Key Drivers'!L26*(AN88+AN89)+'Key Drivers'!L96*AN90 -> 5271.501 | AO91: ='Key Drivers'!L26*(AO88+AO89)+'Key Drivers'!L96*AO90 -> 5549.3515
C92: Closing equipment backlog (RPO) | E92: Legacy basis to Q4'25, current after | F92: =Q92 -> 20005 | G92: =U92 -> 30508 | H92: =Y92 -> 47594.228 | I92: =AC92 -> 61240.831 | J92: =AG92 -> 74714.451 | K92: =AK92 -> 86865.666 | L92: =AO92 -> 98000.356 | N92: ='GEV Quarterly'!B227 -> 14849 | O92: ='GEV Quarterly'!C227 -> 17540 | P92: ='GEV Quarterly'!D227 -> 18624 | Q92: ='GEV Quarterly'!E227 -> 20005 | R92: ='GEV Quarterly'!F227 -> 21996 | S92: ='GEV Quarterly'!G227 -> 23950 | T92: ='GEV Quarterly'!H227 -> 26455 | U92: ='GEV Quarterly'!I227 -> 30508 | V92: ='GEV Quarterly'!J240 -> 38598 | W92: ='GEV Quarterly'!K240 -> 40589 | X92: =X88+X89+X90-X91 -> 43408.048 | Y92: =Y88+Y89+Y90-Y91 -> 47594.228 | Z92: =Z88+Z89+Z90-Z91 -> 49912.127 | AA92: =AA88+AA89+AA90-AA91 -> 52349.877 | AB92: =AB88+AB89+AB90-AB91 -> 55972.593 | AC92: =AC88+AC89+AC90-AC91 -> 61240.831 | AD92: =AD88+AD89+AD90-AD91 -> 63385.876 | AE92: =AE88+AE89+AE90-AE91 -> 65692.275 | ... AO92: =AO88+AO89+AO90-AO91 -> 98000.356
C93: Revenue as % of opening backlog (incl. in-quarter orders) | E93: Quarterly per quarter; annual per year | G93: =G91/(G88+G89) -> 0.3688078 | H93: =H91/(H88+H89) -> 0.35572384 | I93: =I91/(I88+I89) -> 0.30643643 | J93: =J91/(J88+J89) -> 0.27486526 | K93: =K91/(K88+K89) -> 0.25409963 | L93: =L91/(L88+L89) -> 0.24101034 | O93: =O91/(O88+O89) -> 0.086605159 | P93: =P91/(P88+P89) -> 0.0827252 | Q93: =Q91/(Q88+Q89) -> 0.084138746 | R93: =R91/(R88+R89) -> 0.069532617 | S93: =S91/(S88+S89) -> 0.076059284 | T93: =T91/(T88+T89) -> 0.084968685 | U93: =U91/(U88+U89) -> 0.086146286 | V93: =V91/(V88+V89) -> 0.070434832 | ... AO93: =AO91/(AO88+AO89) -> 0.059691925
C94: Closing backlog in years of revenue | D94: yrs | E94: Quarterly columns use annualised revenue | F94: =F92/F91 -> 3.6149259 | G94: =G92/G91 -> 4.1349959 | H94: =H92/H91 -> 3.7680365 | I94: =I92/I91 -> 4.1990051 | J94: =J92/J91 -> 4.4385761 | K94: =K92/K91 -> 4.57551 | L94: =L92/L91 -> 4.6810558 | N94: =N92/(N91*4) -> 3.0180894 | O94: =O92/(O91*4) -> 3.4097978 | P94: =P92/(P91*4) -> 3.2088215 | Q94: =Q92/(Q91*4) -> 3.1916082 | R94: =R92/(R91*4) -> 3.953271 | S94: =S92/(S91*4) -> 3.5789002 | T94: =T92/(T91*4) -> 3.25 | U94: =U92/(U91*4) -> 3.3466433 | ... AO94: =AO92/(AO91*4) -> 4.4149463
C95: Book-to-bill (organic orders / revenue) | D95: x | G95: =G84/G91 -> 2.4235565 | H95: =H84/H91 -> 1.956867 | I95: =I84/I91 -> 1.9356855 | J95: =J84/J91 -> 1.80043 | K95: =K84/K91 -> 1.6400458 | L95: =L84/L91 -> 1.5318563 | O95: =O84/O91 -> 3.092535 | P95: =P84/P91 -> 1.747071 | Q95: =Q84/Q91 -> 1.8813019 | R95: =R84/R91 -> 2.4313444 | S95: =S84/S91 -> 2.1679617 | T95: =T84/T91 -> 2.2309582 | U95: =U84/U91 -> 2.7784116 | V95: =V84/V91 -> 2.2355058 | ... AO95: =AO84/AO91 -> 1.9071004
C96: Equipment revenue growth, YoY | G96: =G91/F91-1 -> 0.33321287 | H96: =H91/G91-1 -> 0.71198728 | I96: =I91/H91-1 -> 0.15466365 | J96: =J91/I91-1 -> 0.15416064 | K96: =K91/J91-1 -> 0.12784056 | L96: =L91/K91-1 -> 0.10274524 | R96: =R91/N91-1 -> 0.13089431 | S96: =S91/O91-1 -> 0.30093313 | T96: =T91/P91-1 -> 0.40248105 | U96: =U91/Q91-1 -> 0.45437141 | V96: =V91/R91-1 -> 0.79798706 | W96: =W91/S91-1 -> 0.87089062 | X96: =X91/T91-1 -> 0.64755071 | Y96: =Y91/U91-1 -> 0.60038456 | ... AO96: =AO91/AK91-1 -> 0.090729895
C98: Electrification services revenue | E98: Segment revenue less equipment | F98: =SUM(N98:Q98) -> 1860 | G98: =SUM(R98:U98) -> 2108 | H98: =SUM(V98:Y98) -> 2181.8 | I98: =SUM(Z98:AC98) -> 2290.89 | J98: =SUM(AD98:AG98) -> 2405.4345 | K98: =SUM(AH98:AK98) -> 2525.7062 | L98: =SUM(AL98:AO98) -> 2651.9915 | N98: ='GEV Quarterly'!B88-'GEV Quarterly'!B140 -> 382 | O98: ='GEV Quarterly'!C88-'GEV Quarterly'!C140 -> 465 | P98: ='GEV Quarterly'!D88-'GEV Quarterly'!D140 -> 438 | Q98: ='GEV Quarterly'!E88-'GEV Quarterly'!E140 -> 575 | R98: ='GEV Quarterly'!F88-'GEV Quarterly'!F140 -> 449 | S98: ='GEV Quarterly'!G88-'GEV Quarterly'!G140 -> 489 | T98: ='GEV Quarterly'!H88-'GEV Quarterly'!H140 -> 527 | U98: ='GEV Quarterly'!I88-'GEV Quarterly'!I140 -> 643 | V98: ='GEV Quarterly'!J88-'GEV Quarterly'!J191 -> 458 | W98: ='GEV Quarterly'!K88-'GEV Quarterly'!K191 -> 507 | X98: =T98*(1+'Key Drivers'!H73) -> 548.08 | Y98: =U98*(1+'Key Drivers'!H73) -> 668.72 | Z98: =V98*(1+'Key Drivers'!I73) -> 480.9 | AA98: =W98*(1+'Key Drivers'!I73) -> 532.35 | AB98: =X98*(1+'Key Drivers'!I73) -> 575.484 | AC98: =Y98*(1+'Key Drivers'!I73) -> 702.156 | AD98: =Z98*(1+'Key Drivers'!J73) -> 504.945 | AE98: =AA98*(1+'Key Drivers'!J73) -> 558.9675 | AF98: =AB98*(1+'Key Drivers'!J73) -> 604.2582 | AG98: =AC98*(1+'Key Drivers'!J73) -> 737.2638 | AH98: =AD98*(1+'Key Drivers'!K73) -> 530.19225 | AI98: =AE98*(1+'Key Drivers'!K73) -> 586.91588 | AJ98: =AF98*(1+'Key Drivers'!K73) -> 634.47111 | AK98: =AG98*(1+'Key Drivers'!K73) -> 774.12699 | AL98: =AH98*(1+'Key Drivers'!L73) -> 556.70186 | AM98: =AI98*(1+'Key Drivers'!L73) -> 616.26167 | AN98: =AJ98*(1+'Key Drivers'!L73) -> 666.19467 | AO98: =AK98*(1+'Key Drivers'!L73) -> 812.83334
C99: Growth, YoY | G99: =G98/F98-1 -> 0.13333333 | H99: =H98/G98-1 -> 0.035009488 | I99: =I98/H98-1 -> 0.05 | J99: =J98/I98-1 -> 0.05 | K99: =K98/J98-1 -> 0.05 | L99: =L98/K98-1 -> 0.05 | R99: =R98/N98-1 -> 0.17539267 | S99: =S98/O98-1 -> 0.051612903 | T99: =T98/P98-1 -> 0.20319635 | U99: =U98/Q98-1 -> 0.11826087 | V99: =V98/R98-1 -> 0.020044543 | W99: =W98/S98-1 -> 0.036809816 | X99: =X98/T98-1 -> 0.04 | Y99: =Y98/U98-1 -> 0.04 | ... AO99: =AO98/AK98-1 -> 0.05
C101: 4. Wind
C102: Wind turbine shipments | D102: GW | E102: Annual driver x quarterly phasing | F102: =SUM(N102:Q102) -> 7.8 | G102: =SUM(R102:U102) -> 6.9 | H102: =SUM(V102:Y102) -> 5 | I102: =SUM(Z102:AC102) -> 3.9 | J102: =SUM(AD102:AG102) -> 3.4 | K102: =SUM(AH102:AK102) -> 3.2 | L102: =SUM(AL102:AO102) -> 3.2 | N102: ='GEV Quarterly'!B271 -> 1.1 | O102: ='GEV Quarterly'!C271 -> 1.6 | P102: ='GEV Quarterly'!D271 -> 2.4 | Q102: ='GEV Quarterly'!E271 -> 2.7 | R102: ='GEV Quarterly'!F271 -> 1.3 | S102: ='GEV Quarterly'!G271 -> 1.7 | T102: ='GEV Quarterly'!H271 -> 2.1 | U102: ='GEV Quarterly'!I271 -> 1.8 | ... W102: ='GEV Quarterly'!K271 -> 1.4 | X102: =('Key Drivers'!H79-SUM(V102:W102))*'Key Drivers'!$H$101/('Key Drivers'!$H$101+'Key Drivers'!$I$101) -> 1.5517241 | Y102: =('Key Drivers'!H79-SUM(V102:W102))*'Key Drivers'!$I$101/('Key Drivers'!$H$101+'Key Drivers'!$I$101) -> 1.4482759 | Z102: ='Key Drivers'!I79*'Key Drivers'!$F$101 -> 0.702 | AA102: ='Key Drivers'!I79*'Key Drivers'!$G$101 -> 0.936 | AB102: ='Key Drivers'!I79*'Key Drivers'!$H$101 -> 1.17 | AC102: ='Key Drivers'!I79*'Key Drivers'!$I$101 -> 1.092 | AD102: ='Key Drivers'!J79*'Key Drivers'!$F$101 -> 0.612 | AE102: ='Key Drivers'!J79*'Key Drivers'!$G$101 -> 0.816 | AF102: ='Key Drivers'!J79*'Key Drivers'!$H$101 -> 1.02 | AG102: ='Key Drivers'!J79*'Key Drivers'!$I$101 -> 0.952 | AH102: ='Key Drivers'!K79*'Key Drivers'!$F$101 -> 0.576 | AI102: ='Key Drivers'!K79*'Key Drivers'!$G$101 -> 0.768 | AJ102: ='Key Drivers'!K79*'Key Drivers'!$H$101 -> 0.96 | AK102: ='Key Drivers'!K79*'Key Drivers'!$I$101 -> 0.896 | AL102: ='Key Drivers'!L79*'Key Drivers'!$F$101 -> 0.576 | AM102: ='Key Drivers'!L79*'Key Drivers'!$G$101 -> 0.768 | AN102: ='Key Drivers'!L79*'Key Drivers'!$H$101 -> 0.96 | AO102: ='Key Drivers'!L79*'Key Drivers'!$I$101 -> 0.896
C103: Equipment revenue per GW applied to projected quarters | D103: $mm/GW | E103: Prior year level x (1 + scenario growth) | G103: =G104 -> 1050.8696 | H103: =G103*(1+'Key Drivers'!H84) -> 1119.1761 | I103: =H103*(1+'Key Drivers'!I84) -> 1130.3678 | J103: =I103*(1+'Key Drivers'!J84) -> 1141.6715 | K103: =J103*(1+'Key Drivers'!K84) -> 1153.0882 | L103: =K103*(1+'Key Drivers'!L84) -> 1164.6191
C104: Equipment revenue per GW | D104: $mm/GW | F104: =F105/F102 -> 1031.6667 | G104: =G105/G102 -> 1050.8696 | H104: =H105/H102 -> 1128.3057 | I104: =I105/I102 -> 1130.3678 | J104: =J105/J102 -> 1141.6715 | K104: =K105/K102 -> 1153.0882 | L104: =L105/L102 -> 1164.6191 | N104: =N105/N102 -> 1120 | O104: =O105/O102 -> 1042.5 | P104: =P105/P102 -> 1039.1667 | Q104: =Q105/Q102 -> 982.59259 | R104: =R105/R102 -> 1086.1538 | S104: =S105/S102 -> 1057.0588 | T104: =T105/T102 -> 1049.0476 | U104: =U105/U102 -> 1021.6667 | ... W104: =W105/W102 -> 996.42857 | X104: =H103 -> 1119.1761 | Y104: =H103 -> 1119.1761 | Z104: =I103 -> 1130.3678 | AA104: =I103 -> 1130.3678 | AB104: =I103 -> 1130.3678 | AC104: =I103 -> 1130.3678 | AD104: =J103 -> 1141.6715 | AE104: =J103 -> 1141.6715 | AF104: =J103 -> 1141.6715 | AG104: =J103 -> 1141.6715 | AH104: =K103 -> 1153.0882 | AI104: =K103 -> 1153.0882 | AJ104: =K103 -> 1153.0882 | AK104: =K103 -> 1153.0882 | AL104: =L103 -> 1164.6191 | AM104: =L103 -> 1164.6191 | AN104: =L103 -> 1164.6191 | AO104: =L103 -> 1164.6191
C105: Wind equipment revenue | F105: =SUM(N105:Q105) -> 8047 | G105: =SUM(R105:U105) -> 7251 | H105: =SUM(V105:Y105) -> 5641.5283 | I105: =SUM(Z105:AC105) -> 4408.4346 | J105: =SUM(AD105:AG105) -> 3881.6832 | K105: =SUM(AH105:AK105) -> 3689.8824 | L105: =SUM(AL105:AO105) -> 3726.7812 | N105: ='GEV Quarterly'!B149 -> 1232 | O105: ='GEV Quarterly'!C149 -> 1668 | P105: ='GEV Quarterly'!D149 -> 2494 | Q105: ='GEV Quarterly'!E149 -> 2653 | R105: ='GEV Quarterly'!F149 -> 1412 | S105: ='GEV Quarterly'!G149 -> 1797 | T105: ='GEV Quarterly'!H149 -> 2203 | U105: ='GEV Quarterly'!I149 -> 1839 | V105: ='GEV Quarterly'!J201 -> 889 | W105: ='GEV Quarterly'!K201 -> 1395 | X105: =X102*X104 -> 1736.6525 | Y105: =Y102*Y104 -> 1620.8757 | Z105: =Z102*Z104 -> 793.51823 | AA105: =AA102*AA104 -> 1058.0243 | AB105: =AB102*AB104 -> 1322.5304 | AC105: =AC102*AC104 -> 1234.3617 | AD105: =AD102*AD104 -> 698.70297 | AE105: =AE102*AE104 -> 931.60397 | ... AO105: =AO102*AO104 -> 1043.4987
C106: Growth, YoY | G106: =G105/F105-1 -> -0.098918852 | H106: =H105/G105-1 -> -0.22196549 | I106: =I105/H105-1 -> -0.2185744 | J106: =J105/I105-1 -> -0.11948718 | K106: =K105/J105-1 -> -0.049411765 | L106: =L105/K105-1 -> 0.01 | R106: =R105/N105-1 -> 0.1461039 | S106: =S105/O105-1 -> 0.077338129 | T106: =T105/P105-1 -> -0.11668003 | U106: =U105/Q105-1 -> -0.30682247 | V106: =V105/R105-1 -> -0.3703966 | W106: =W105/S105-1 -> -0.22370618 | X106: =X105/T105-1 -> -0.21168745 | Y106: =Y105/U105-1 -> -0.11861027 | ... AO106: =AO105/AK105-1 -> 0.01
C107: Wind services revenue | F107: =SUM(N107:Q107) -> 1654 | G107: =SUM(R107:U107) -> 1859 | H107: =SUM(V107:Y107) -> 2390.25 | I107: =SUM(Z107:AC107) -> 2485.86 | J107: =SUM(AD107:AG107) -> 2560.4358 | K107: =SUM(AH107:AK107) -> 2637.2489 | L107: =SUM(AL107:AO107) -> 2716.3663 | N107: ='GEV Quarterly'!B89-'GEV Quarterly'!B149 -> 407 | O107: ='GEV Quarterly'!C89-'GEV Quarterly'!C149 -> 394 | P107: ='GEV Quarterly'!D89-'GEV Quarterly'!D149 -> 397 | Q107: ='GEV Quarterly'!E89-'GEV Quarterly'!E149 -> 456 | R107: ='GEV Quarterly'!F89-'GEV Quarterly'!F149 -> 438 | S107: ='GEV Quarterly'!G89-'GEV Quarterly'!G149 -> 448 | T107: ='GEV Quarterly'!H89-'GEV Quarterly'!H149 -> 444 | U107: ='GEV Quarterly'!I89-'GEV Quarterly'!I149 -> 529 | V107: ='GEV Quarterly'!J89-'GEV Quarterly'!J201 -> 543 | W107: ='GEV Quarterly'!K89-'GEV Quarterly'!K201 -> 631 | X107: =T107*(1+'Key Drivers'!H89) -> 555 | Y107: =U107*(1+'Key Drivers'!H89) -> 661.25 | Z107: =V107*(1+'Key Drivers'!I89) -> 564.72 | AA107: =W107*(1+'Key Drivers'!I89) -> 656.24 | AB107: =X107*(1+'Key Drivers'!I89) -> 577.2 | AC107: =Y107*(1+'Key Drivers'!I89) -> 687.7 | AD107: =Z107*(1+'Key Drivers'!J89) -> 581.6616 | AE107: =AA107*(1+'Key Drivers'!J89) -> 675.9272 | AF107: =AB107*(1+'Key Drivers'!J89) -> 594.516 | AG107: =AC107*(1+'Key Drivers'!J89) -> 708.331 | AH107: =AD107*(1+'Key Drivers'!K89) -> 599.11145 | AI107: =AE107*(1+'Key Drivers'!K89) -> 696.20502 | AJ107: =AF107*(1+'Key Drivers'!K89) -> 612.35148 | AK107: =AG107*(1+'Key Drivers'!K89) -> 729.58093 | AL107: =AH107*(1+'Key Drivers'!L89) -> 617.08479 | AM107: =AI107*(1+'Key Drivers'!L89) -> 717.09117 | AN107: =AJ107*(1+'Key Drivers'!L89) -> 630.72202 | AO107: =AK107*(1+'Key Drivers'!L89) -> 751.46836
C108: Growth, YoY | G108: =G107/F107-1 -> 0.12394196 | H108: =H107/G107-1 -> 0.28577192 | I108: =I107/H107-1 -> 0.04 | J108: =J107/I107-1 -> 0.03 | K108: =K107/J107-1 -> 0.03 | L108: =L107/K107-1 -> 0.03 | R108: =R107/N107-1 -> 0.076167076 | S108: =S107/O107-1 -> 0.13705584 | T108: =T107/P107-1 -> 0.11838791 | U108: =U107/Q107-1 -> 0.16008772 | V108: =V107/R107-1 -> 0.23972603 | W108: =W107/S107-1 -> 0.40848214 | X108: =X107/T107-1 -> 0.25 | Y108: =Y107/U107-1 -> 0.25 | ... AO108: =AO107/AK107-1 -> 0.03
C110: 5. Old orders vs new orders
C111: Gas shipments by order vintage (oldest slots ship first)
C112: Tier 1: Dec-25 firm backlog, already in RPO
C113: Undelivered, start of period | D113: GW | H113: =V113 -> 40 | I113: =Z113 -> 23.38 | J113: =AD113 -> 3.85 | K113: =AH113 -> 0 | L113: =AL113 -> 0 | V113: =U58 -> 40 | W113: =V115 -> 35.8 | X113: =W115 -> 32.5 | Y113: =X115 -> 28.18 | Z113: =Y115 -> 23.38 | AA113: =Z115 -> 18.73 | AB113: =AA115 -> 13.894 | AC113: =AB115 -> 8.965 | AD113: =AC115 -> 3.85 | ... AO113: =AN115 -> 0
C114: (-) Delivered in period | D114: GW | H114: =SUM(V114:Y114) -> 16.62 | I114: =SUM(Z114:AC114) -> 19.53 | J114: =SUM(AD114:AG114) -> 3.85 | K114: =SUM(AH114:AK114) -> 0 | L114: =SUM(AL114:AO114) -> 0 | V114: =MIN(V57,V113) -> 4.2 | W114: =MIN(W57,W113) -> 3.3 | X114: =MIN(X57,X113) -> 4.32 | Y114: =MIN(Y57,Y113) -> 4.8 | Z114: =MIN(Z57,Z113) -> 4.65 | AA114: =MIN(AA57,AA113) -> 4.836 | AB114: =MIN(AB57,AB113) -> 4.929 | AC114: =MIN(AC57,AC113) -> 5.115 | ... AO114: =MIN(AO57,AO113) -> 0
C115: Undelivered, end of period | D115: GW | H115: =Y115 -> 23.38 | I115: =AC115 -> 3.85 | J115: =AG115 -> 0 | K115: =AK115 -> 0 | L115: =AO115 -> 0 | V115: =V113-V114 -> 35.8 | W115: =W113-W114 -> 32.5 | X115: =X113-X114 -> 28.18 | Y115: =Y113-Y114 -> 23.38 | Z115: =Z113-Z114 -> 18.73 | AA115: =AA113-AA114 -> 13.894 | AB115: =AB113-AB114 -> 8.965 | AC115: =AC113-AC114 -> 3.85 | ... AO115: =AO113-AO114 -> 0
...

Sheet Key Drivers
C2: GE Vernova (GEV)
C3: Key drivers and scenario switch
C4: US$ millions unless stated. Blue = input, black = formula, orange = assumption, grey = projection. Annual columns add up the quarters.
C5: Scenario | D5: Base | E5: =IF(D5="Base","Base: build-out continues at a Street-like pace. FY28E revenue lands near the thesis base case ($55B).",IF(D5="Bull","Bull: faster build-out, SRAs convert, pricing holds. FY28E revenue lands near the thesis bull case ($58B).","Bear: build-out stalls after 2026. Capex flat then down, SRAs lapse, deliveries slip. FY28E revenue lands near the thesis bear case ($50B).")) -> Base: build-out continues at a Street-like pace. FY28E revenue lands near the thesis base case ($55B).
C6: <- change the scenario in the orange cell (Base / Bull / Bear) | F6: Annual: historical | H6: Annual: projected | N6: Quarterly: historical | X6: Quarterly: projected
C7: Fiscal period | D7: Unit | E7: Note | F7: FY2024A | G7: FY2025A | H7: FY2026E | I7: FY2027E | J7: FY2028E | K7: FY2029E | L7: FY2030E | N7: Q1'24 | O7: Q2'24 | P7: Q3'24 | Q7: Q4'24 | R7: Q1'25 | S7: Q2'25 | T7: Q3'25 | U7: Q4'25 | V7: Q1'26 | W7: Q2'26 | X7: Q3'26 | Y7: Q4'26 | Z7: Q1'27 | AA7: Q2'27 | AB7: Q3'27 | AC7: Q4'27 | AD7: Q1'28 | AE7: Q2'28 | AF7: Q3'28 | AG7: Q4'28 | AH7: Q1'29 | AI7: Q2'29 | AJ7: Q3'29 | AK7: Q4'29 | AL7: Q1'30 | AM7: Q2'30 | AN7: Q3'30 | AO7: Q4'30
C8: Period end | F8: 45657 | G8: 46022 | H8: 46387 | I8: 46752 | J8: 47118 | K8: 47483 | L8: 47848 | N8: 45382 | O8: 45473 | P8: 45565 | Q8: 45657 | R8: 45747 | S8: 45838 | T8: 45930 | U8: 46022 | V8: 46112 | W8: 46203 | X8: 46295 | Y8: 46387 | Z8: 46477 | AA8: 46568 | AB8: 46660 | AC8: 46752 | AD8: 46843 | AE8: 46934 | AF8: 47026 | AG8: 47118 | AH8: 47208 | AI8: 47299 | AJ8: 47391 | AK8: 47483 | AL8: 47573 | AM8: 47664 | AN8: 47756 | AO8: 47848
C10: 1. Data-centre demand
C11: Hyperscaler capex growth, YoY | E11: FY26E = guide $732.5B; Street ~$1T FY27 | G11: =Revenue!G37 -> 0.63676412 | H11: =Revenue!H37 -> 0.79226817 | I11: =INDEX(I12:I14,MATCH($D$5,$C12:$C14,0)) -> 0.25 | J11: =INDEX(J12:J14,MATCH($D$5,$C12:$C14,0)) -> 0.1 | K11: =INDEX(K12:K14,MATCH($D$5,$C12:$C14,0)) -> 0.05 | L11: =INDEX(L12:L14,MATCH($D$5,$C12:$C14,0)) -> 0.03
C12: Base | I12: 0.25 | J12: 0.1 | K12: 0.05 | L12: 0.03
C13: Bull | I13: 0.37 | J13: 0.12 | K13: 0.08 | L13: 0.05
C14: Bear | I14: 0 | J14: -0.1 | K14: -0.05 | L14: 0
C16: Data-centre orders, % of hyperscaler capex | E16: H1'26 >$5B on ~$733B capex; annual rate | G16: =Revenue!G79 -> 0.005872278 | H16: =INDEX(H17:H19,MATCH($D$5,$C17:$C19,0)) -> 0.0143 | I16: =INDEX(I17:I19,MATCH($D$5,$C17:$C19,0)) -> 0.0145 | J16: =INDEX(J17:J19,MATCH($D$5,$C17:$C19,0)) -> 0.0145 | K16: =INDEX(K17:K19,MATCH($D$5,$C17:$C19,0)) -> 0.014 | L16: =INDEX(L17:L19,MATCH($D$5,$C17:$C19,0)) -> 0.014
C17: Base | H17: 0.0143 | I17: 0.0145 | J17: 0.0145 | K17: 0.014 | L17: 0.014
C18: Bull | H18: 0.0147 | I18: 0.015 | J18: 0.0152 | K18: 0.0152 | L18: 0.0152
C19: Bear | H19: 0.014 | I19: 0.0125 | J19: 0.0115 | K19: 0.011 | L19: 0.011
C21: Other Electrification equipment orders, YoY | E21: Grid, power conversion, other | H21: =INDEX(H22:H24,MATCH($D$5,$C22:$C24,0)) -> -0.08 | I21: =INDEX(I22:I24,MATCH($D$5,$C22:$C24,0)) -> 0.05 | J21: =INDEX(J22:J24,MATCH($D$5,$C22:$C24,0)) -> 0.05 | K21: =INDEX(K22:K24,MATCH($D$5,$C22:$C24,0)) -> 0.04 | L21: =INDEX(L22:L24,MATCH($D$5,$C22:$C24,0)) -> 0.03
C22: Base | H22: -0.08 | I22: 0.05 | J22: 0.05 | K22: 0.04 | L22: 0.03
C23: Bull | H23: -0.06 | I23: 0.06 | J23: 0.06 | K23: 0.05 | L23: 0.04
C24: Bear | H24: -0.09 | I24: 0.01 | J24: -0.02 | K24: -0.01 | L24: 0
C26: Electrification backlog delivered, % per quarter | E26: Per quarter, on opening backlog | G26: =(SUM(Revenue!R91:U91)-$H$96*SUM(Revenue!R90:U90))/(SUM(Revenue!R88:U88)+SUM(Revenue!R89:U89)) -> 0.070168063 | H26: =INDEX(H27:H29,MATCH($D$5,$C27:$C29,0)) -> 0.075 | I26: =INDEX(I27:I29,MATCH($D$5,$C27:$C29,0)) -> 0.064 | J26: =INDEX(J27:J29,MATCH($D$5,$C27:$C29,0)) -> 0.059 | K26: =INDEX(K27:K29,MATCH($D$5,$C27:$C29,0)) -> 0.056 | L26: =INDEX(L27:L29,MATCH($D$5,$C27:$C29,0)) -> 0.054
C27: Base | H27: 0.075 | I27: 0.064 | J27: 0.059 | K27: 0.056 | L27: 0.054
C28: Bull | H28: 0.077 | I28: 0.066 | J28: 0.06 | K28: 0.057 | L28: 0.055
C29: Bear | H29: 0.073 | I29: 0.06 | J29: 0.054 | K29: 0.051 | L29: 0.049
C31: 2. Gas Power
C32: New slot reservation agreements signed, per quarter | D32: GW | E32: Per quarter; Q2'26 was 18 GW | H32: =INDEX(H33:H35,MATCH($D$5,$C33:$C35,0)) -> 9 | I32: =INDEX(I33:I35,MATCH($D$5,$C33:$C35,0)) -> 7.5 | J32: =INDEX(J33:J35,MATCH($D$5,$C33:$C35,0)) -> 6.25 | K32: =INDEX(K33:K35,MATCH($D$5,$C33:$C35,0)) -> 5.5 | L32: =INDEX(L33:L35,MATCH($D$5,$C33:$C35,0)) -> 5
C33: Base | H33: 9 | I33: 7.5 | J33: 6.25 | K33: 5.5 | L33: 5
C34: Bull | H34: 10.9 | I34: 9 | J34: 8 | K34: 7 | L34: 6.5
C35: Bear | H35: 5.9 | I35: 3 | J35: 1.5 | K35: 1 | L35: 1
C37: SRAs converting to firm orders, % per quarter | E37: Per quarter; Q2'26 was 17.9% (10 of 56 GW) | H37: =INDEX(H38:H40,MATCH($D$5,$C38:$C40,0)) -> 0.12 | I37: =INDEX(I38:I40,MATCH($D$5,$C38:$C40,0)) -> 0.095 | J37: =INDEX(J38:J40,MATCH($D$5,$C38:$C40,0)) -> 0.095 | K37: =INDEX(K38:K40,MATCH($D$5,$C38:$C40,0)) -> 0.095 | L37: =INDEX(L38:L40,MATCH($D$5,$C38:$C40,0)) -> 0.095
C38: Base | H38: 0.12 | I38: 0.095 | J38: 0.095 | K38: 0.095 | L38: 0.095
C39: Bull | H39: 0.125 | I39: 0.105 | J39: 0.105 | K39: 0.105 | L39: 0.105
C40: Bear | H40: 0.11 | I40: 0.0625 | J40: 0.0625 | K40: 0.0625 | L40: 0.0625
C42: SRAs lapsing or cancelled, % per quarter | E42: Per quarter | H42: =INDEX(H43:H45,MATCH($D$5,$C43:$C45,0)) -> 0 | I42: =INDEX(I43:I45,MATCH($D$5,$C43:$C45,0)) -> 0.0075 | J42: =INDEX(J43:J45,MATCH($D$5,$C43:$C45,0)) -> 0.0075 | K42: =INDEX(K43:K45,MATCH($D$5,$C43:$C45,0)) -> 0.0075 | L42: =INDEX(L43:L45,MATCH($D$5,$C43:$C45,0)) -> 0.0075
C43: Base | H43: 0 | I43: 0.0075 | J43: 0.0075 | K43: 0.0075 | L43: 0.0075
C44: Bull | H44: 0 | I44: 0.0025 | J44: 0.0025 | K44: 0.0025 | L44: 0.0025
C45: Bear | H45: 0 | I45: 0.03 | J45: 0.03 | K45: 0.03 | L45: 0.03
C47: Direct firm orders (no prior SRA), per quarter | D47: GW | E47: Per quarter; Q2'26 was 2 GW | H47: =INDEX(H48:H50,MATCH($D$5,$C48:$C50,0)) -> 2 | I47: =INDEX(I48:I50,MATCH($D$5,$C48:$C50,0)) -> 1.5 | J47: =INDEX(J48:J50,MATCH($D$5,$C48:$C50,0)) -> 1.5 | K47: =INDEX(K48:K50,MATCH($D$5,$C48:$C50,0)) -> 1.5 | L47: =INDEX(L48:L50,MATCH($D$5,$C48:$C50,0)) -> 1.5
C48: Base | H48: 2 | I48: 1.5 | J48: 1.5 | K48: 1.5 | L48: 1.5
C49: Bull | H49: 2 | I49: 2 | J49: 2 | K49: 2 | L49: 2
C50: Bear | H50: 1.5 | I50: 1 | J50: 0.75 | K50: 0.75 | L50: 0.75
C52: Firm backlog cancelled or deferred, % per quarter | E52: Per quarter; hits newest slots first | H52: =INDEX(H53:H55,MATCH($D$5,$C53:$C55,0)) -> 0.00125 | I52: =INDEX(I53:I55,MATCH($D$5,$C53:$C55,0)) -> 0.00125 | J52: =INDEX(J53:J55,MATCH($D$5,$C53:$C55,0)) -> 0.00125 | K52: =INDEX(K53:K55,MATCH($D$5,$C53:$C55,0)) -> 0.00125 | L52: =INDEX(L53:L55,MATCH($D$5,$C53:$C55,0)) -> 0.00125
C53: Base | H53: 0.00125 | I53: 0.00125 | J53: 0.00125 | K53: 0.00125 | L53: 0.00125
C54: Bull | H54: 0 | I54: 0 | J54: 0 | K54: 0 | L54: 0
C55: Bear | H55: 0.0025 | I55: 0.005 | J55: 0.01 | K55: 0.0125 | L55: 0.0125
C57: Shipments as % of factory capacity | E57: Bear: customers push delivery dates out. | H57: =INDEX(H58:H60,MATCH($D$5,$C58:$C60,0)) -> 0.96 | I57: =INDEX(I58:I60,MATCH($D$5,$C58:$C60,0)) -> 0.93 | J57: =INDEX(J58:J60,MATCH($D$5,$C58:$C60,0)) -> 0.92 | K57: =INDEX(K58:K60,MATCH($D$5,$C58:$C60,0)) -> 0.92 | L57: =INDEX(L58:L60,MATCH($D$5,$C58:$C60,0)) -> 0.92
C58: Base | H58: 0.96 | I58: 0.93 | J58: 0.92 | K58: 0.92 | L58: 0.92
C59: Bull | H59: 0.98 | I59: 0.96 | J59: 0.95 | K59: 0.95 | L59: 0.95
C60: Bear | H60: 0.955 | I60: 0.9 | J60: 0.86 | K60: 0.84 | L60: 0.84
C62: Power revenue per GW shipped, QoQ growth | E62: Per quarter; H1'26A avg $513mm/GW | H62: =INDEX(H63:H65,MATCH($D$5,$C63:$C65,0)) -> 0.11 | I62: =INDEX(I63:I65,MATCH($D$5,$C63:$C65,0)) -> 0.008 | J62: =INDEX(J63:J65,MATCH($D$5,$C63:$C65,0)) -> 0.007 | K62: =INDEX(K63:K65,MATCH($D$5,$C63:$C65,0)) -> 0.006 | L62: =INDEX(L63:L65,MATCH($D$5,$C63:$C65,0)) -> 0.005
C63: Base | H63: 0.11 | I63: 0.008 | J63: 0.007 | K63: 0.006 | L63: 0.005
C64: Bull | H64: 0.12 | I64: 0.01 | J64: 0.008 | K64: 0.007 | L64: 0.006
C65: Bear | H65: 0.1 | I65: 0.005 | J65: 0.003 | K65: 0.001 | L65: 0
C67: 3. Services
C68: Power services growth, YoY | E68: H1'26A +5.8% YoY | G68: =Revenue!G74 -> 0.052854291 | H68: =INDEX(H69:H71,MATCH($D$5,$C69:$C71,0)) -> 0.07 | I68: =INDEX(I69:I71,MATCH($D$5,$C69:$C71,0)) -> 0.05 | J68: =INDEX(J69:J71,MATCH($D$5,$C69:$C71,0)) -> 0.045 | K68: =INDEX(K69:K71,MATCH($D$5,$C69:$C71,0)) -> 0.04 | L68: =INDEX(L69:L71,MATCH($D$5,$C69:$C71,0)) -> 0.04
C69: Base | H69: 0.07 | I69: 0.05 | J69: 0.045 | K69: 0.04 | L69: 0.04
C70: Bull | H70: 0.072 | I70: 0.052 | J70: 0.047 | K70: 0.043 | L70: 0.043
C71: Bear | H71: 0.065 | I71: 0.035 | J71: 0.025 | K71: 0.025 | L71: 0.025
C73: Electrification services growth, YoY | E73: H1'26A +3% YoY. | G73: =Revenue!G99 -> 0.13333333 | H73: =INDEX(H74:H76,MATCH($D$5,$C74:$C76,0)) -> 0.04 | I73: =INDEX(I74:I76,MATCH($D$5,$C74:$C76,0)) -> 0.05 | J73: =INDEX(J74:J76,MATCH($D$5,$C74:$C76,0)) -> 0.05 | K73: =INDEX(K74:K76,MATCH($D$5,$C74:$C76,0)) -> 0.05 | L73: =INDEX(L74:L76,MATCH($D$5,$C74:$C76,0)) -> 0.05
C74: Base | H74: 0.04 | I74: 0.05 | J74: 0.05 | K74: 0.05 | L74: 0.05
C75: Bull | H75: 0.05 | I75: 0.07 | J75: 0.07 | K75: 0.06 | L75: 0.06
C76: Bear | H76: 0.03 | I76: 0.02 | J76: 0.01 | K76: 0.01 | L76: 0.01
C78: 4. Wind
C79: Wind turbine shipments, full year | D79: GW | E79: FY25A 6.9 GW; H1'26A 2.0 GW | H79: =INDEX(H80:H82,MATCH($D$5,$C80:$C82,0)) -> 5 | I79: =INDEX(I80:I82,MATCH($D$5,$C80:$C82,0)) -> 3.9 | J79: =INDEX(J80:J82,MATCH($D$5,$C80:$C82,0)) -> 3.4 | K79: =INDEX(K80:K82,MATCH($D$5,$C80:$C82,0)) -> 3.2 | L79: =INDEX(L80:L82,MATCH($D$5,$C80:$C82,0)) -> 3.2
C80: Base | H80: 5 | I80: 3.9 | J80: 3.4 | K80: 3.2 | L80: 3.2
C81: Bull | H81: 5.2 | I81: 4.6 | J81: 4.3 | K81: 4.2 | L81: 4.2
C82: Bear | H82: 4.8 | I82: 3.5 | J82: 2.9 | K82: 2.5 | L82: 2.4
C84: Wind equipment revenue per GW, growth YoY (annual level) | E84: FY25A $1,051mm/GW; H1'26A $1,142mm/GW | H84: =INDEX(H85:H87,MATCH($D$5,$C85:$C87,0)) -> 0.065 | I84: =INDEX(I85:I87,MATCH($D$5,$C85:$C87,0)) -> 0.01 | J84: =INDEX(J85:J87,MATCH($D$5,$C85:$C87,0)) -> 0.01 | K84: =INDEX(K85:K87,MATCH($D$5,$C85:$C87,0)) -> 0.01 | L84: =INDEX(L85:L87,MATCH($D$5,$C85:$C87,0)) -> 0.01
C85: Base | H85: 0.065 | I85: 0.01 | J85: 0.01 | K85: 0.01 | L85: 0.01
C86: Bull | H86: 0.07 | I86: 0.02 | J86: 0.02 | K86: 0.02 | L86: 0.02
C87: Bear | H87: 0.06 | I87: 0 | J87: 0 | K87: 0 | L87: 0
C89: Wind services growth, YoY | E89: H1'26A +33% YoY | H89: =INDEX(H90:H92,MATCH($D$5,$C90:$C92,0)) -> 0.25 | I89: =INDEX(I90:I92,MATCH($D$5,$C90:$C92,0)) -> 0.04 | J89: =INDEX(J90:J92,MATCH($D$5,$C90:$C92,0)) -> 0.03 | K89: =INDEX(K90:K92,MATCH($D$5,$C90:$C92,0)) -> 0.03 | L89: =INDEX(L90:L92,MATCH($D$5,$C90:$C92,0)) -> 0.03
C90: Base | H90: 0.25 | I90: 0.04 | J90: 0.03 | K90: 0.03 | L90: 0.03
C91: Bull | H91: 0.26 | I91: 0.06 | J91: 0.05 | K91: 0.05 | L91: 0.05
C92: Bear | H92: 0.24 | I92: 0.01 | J92: 0 | K92: 0 | L92: 0
C94: 5. Fixed assumptions
C95: Gas factory capacity per quarter | D95: GW | E95: 5 GW/qtr from Q3'26; 24 GW/yr in 2028 | H95: =SUM(X95:Y95) -> 9.5 | I95: =SUM(Z95:AC95) -> 21 | J95: =SUM(AD95:AG95) -> 24 | K95: =SUM(AH95:AK95) -> 27 | L95: =SUM(AL95:AO95) -> 30 | X95: 4.5 | Y95: 5 | Z95: 5 | AA95: 5.2 | AB95: 5.3 | AC95: 5.5 | AD95: 5.7 | AE95: 5.9 | AF95: 6.1 | AG95: 6.3 | AH95: 6.4 | AI95: 6.65 | AJ95: 6.85 | AK95: 7.1 | AL95: 7.2 | AM95: 7.4 | AN95: 7.6 | AO95: 7.8
C96: Orders delivered in the quarter booked, % | E96: Book-and-ship share of new orders | H96: 0.05 | I96: 0.05 | J96: 0.05 | K96: 0.05 | L96: 0.05
C97: Eliminations and other, % of segment revenue | E97: FY25A 1.0%; H1'26A 0.3%. | H97: 0.005 | I97: 0.005 | J97: 0.005 | K97: 0.005 | L97: 0.005
C99: Quarterly phasing of annual flows (share of the year) | F99: Q1 | G99: Q2 | H99: Q3 | I99: Q4 | J99: Total
C100: Electrification equipment orders | E100: FY25 phasing 19/20/25/35%, smoothed | F100: 0.2 | G100: 0.21 | H100: 0.26 | I100: 0.33 | J100: =SUM(F100:I100) -> 1
C101: Wind turbine shipments | E101: Annual driver x quarterly phasing | F101: 0.18 | G101: 0.24 | H101: 0.3 | I101: 0.28 | J101: =SUM(F101:I101) -> 1
C103: 6. Margin, cash flow and exit multiple
C104: Adjusted EBITDA margin | E104: FY26E guide 12-14%; Street FY28E 21.6% | G104: =SUM('GEV Quarterly'!F57:I57)/Revenue!G18 -> 0.083952823 | H104: =INDEX(H105:H107,MATCH($D$5,$C105:$C107,0)) -> 0.13 | I104: =INDEX(I105:I107,MATCH($D$5,$C105:$C107,0)) -> 0.146 | J104: =INDEX(J105:J107,MATCH($D$5,$C105:$C107,0)) -> 0.16 | K104: =INDEX(K105:K107,MATCH($D$5,$C105:$C107,0)) -> 0.16 | L104: =INDEX(L105:L107,MATCH($D$5,$C105:$C107,0)) -> 0.16
C105: Base | H105: 0.13 | I105: 0.146 | J105: 0.16 | K105: 0.16 | L105: 0.16
C106: Bull | H106: 0.134 | I106: 0.158 | J106: 0.18 | K106: 0.185 | L106: 0.185
C107: Bear | H107: 0.126 | I107: 0.13 | J107: 0.13 | K107: 0.125 | L107: 0.12
C109: Power deposits, % of Power RPO (year end) | E109: Dec-25 58.9%, Jun-26 65.7% | G109: ='GEV Quarterly'!I287/'GEV Quarterly'!I236 -> 0.58890193 | H109: =INDEX(H110:H112,MATCH($D$5,$C110:$C112,0)) -> 0.59 | I109: =INDEX(I110:I112,MATCH($D$5,$C110:$C112,0)) -> 0.56 | J109: =INDEX(J110:J112,MATCH($D$5,$C110:$C112,0)) -> 0.53 | K109: =INDEX(K110:K112,MATCH($D$5,$C110:$C112,0)) -> 0.5 | L109: =INDEX(L110:L112,MATCH($D$5,$C110:$C112,0)) -> 0.48
C110: Base | H110: 0.59 | I110: 0.56 | J110: 0.53 | K110: 0.5 | L110: 0.48
C111: Bull | H111: 0.6 | I111: 0.6 | J111: 0.58 | K111: 0.56 | L111: 0.54
C112: Bear | H112: 0.595 | I112: 0.5 | J112: 0.45 | K112: 0.41 | L112: 0.38
C114: Exit multiple at Dec-28 (EV / next-12-month EBITDA) | D114: x | E114: Thesis: 20x base, 30x bull, 16x bear | J114: =INDEX(J115:J117,MATCH($D$5,$C115:$C117,0)) -> 20
C115: Base | J115: 20
C116: Bull | J116: 30
C117: Bear | J117: 16
C119: Fixed cash-flow assumptions (same in every scenario)
C120: Depreciation and amortisation, % of revenue | E120: H1'26A 3.7%; FY25A 2.2% | H120: 0.035 | I120: 0.033 | J120: 0.031 | K120: 0.03 | L120: 0.03
C121: Capital expenditures, % of revenue | E121: FY25A 3.4%; H1'26A 3.8% | H121: 0.032 | I121: 0.032 | J121: 0.03 | K121: 0.03 | L121: 0.03
C122: Working capital build, % of revenue change | E122: FY25A 125%; H1'26A 60% | H122: 0.6 | I122: 0.5 | J122: 0.4 | K122: 0.3 | L122: 0.25
C123: Pension and other cash outflows, % of revenue | E123: FY25A 4.7%; H1'26A 10.4% | H123: 0.025 | I123: 0.02 | J123: 0.015 | K123: 0.015 | L123: 0.015
...

Sheet Regular DCF
C2: GE Vernova (GEV)
C3: Regular DCF: quarterly, 6-month view
C4: US$ millions unless stated. Blue = input, black = formula, orange = assumption, grey = projection.
C5: Scenario | E5: ='Key Drivers'!D5 -> Base
F6: Actual | H6: Projected quarters | S6: Fiscal year
C7: Fiscal period | E7: Note | F7: Q1'26A | G7: Q2'26A | H7: Q3'26E | I7: Q4'26E | J7: Q1'27E | K7: Q2'27E | L7: Q3'27E | M7: Q4'27E | N7: Q1'28E | O7: Q2'28E | P7: Q3'28E | Q7: Q4'28E | S7: FY2026E | T7: FY2027E | U7: FY2028E | V7: FY2029E
C8: Period end | F8: 46112 | G8: 46203 | H8: 46295 | I8: 46387 | J8: 46477 | K8: 46568 | L8: 46660 | M8: 46752 | N8: 46843 | O8: 46934 | P8: 47026 | Q8: 47118 | S8: 46387 | T8: 46752 | U8: 47118 | V8: 47483
C10: Cash flow
C11: Revenue | E11: Revenue tab | F11: =Revenue!V18 -> 9337 | G11: =Revenue!W18 -> 11103 | H11: =Revenue!X18 -> 11933.004 | I11: =Revenue!Y18 -> 13660.794 | J11: =Revenue!Z18 -> 11315.47 | K11: =Revenue!AA18 -> 12470.152 | L11: =Revenue!AB18 -> 12826.941 | M11: =Revenue!AC18 -> 14240.811 | ... Q11: =Revenue!AG18 -> 15429.174 | S11: =SUM(F11:I11) -> 46033.799 | T11: =SUM(J11:M11) -> 50853.374 | U11: =SUM(N11:Q11) -> 55474.501 | V11: =Revenue!K18 -> 60481.212
C12: Growth, YoY | F12: =F11/Revenue!R18-1 -> 0.1624751 | G12: =G11/Revenue!S18-1 -> 0.21850307 | H12: =H11/Revenue!T18-1 -> 0.19701117 | I12: =I11/Revenue!U18-1 -> 0.2468779 | J12: =J11/Revenue!V18-1 -> 0.2118957 | K12: =K11/Revenue!W18-1 -> 0.12313357 | L12: =L11/Revenue!X18-1 -> 0.074912937 | M12: =M11/Revenue!Y18-1 -> 0.04245848 | ... Q12: =Q11/Revenue!AC18-1 -> 0.083447733 | S12: =S11/Revenue!$G$18-1 -> 0.20922007 | T12: =T11/S11-1 -> 0.10469645 | U12: =U11/T11-1 -> 0.090871602 | V12: =V11/U11-1 -> 0.09025246
C13: Adjusted EBITDA | E13: Revenue x margin (Key Drivers) | F13: ='GEV Quarterly'!J57 -> 896 | G13: ='GEV Quarterly'!K57 -> 1250 | H13: =H11*($S11*'Key Drivers'!$H$104-SUM($F13:$G13))/SUM($H11:$I11) -> 1789.6355 | I13: =I11*($S11*'Key Drivers'!$H$104-SUM($F13:$G13))/SUM($H11:$I11) -> 2048.7583 | J13: =J11*'Key Drivers'!$I$104 -> 1652.0586 | K13: =K11*'Key Drivers'!$I$104 -> 1820.6422 | L13: =L11*'Key Drivers'!$I$104 -> 1872.7334 | M13: =M11*'Key Drivers'!$I$104 -> 2079.1584 | N13: =N11*'Key Drivers'!$J$104 -> 1995.6989 | O13: =O11*'Key Drivers'!$J$104 -> 2176.5975 | P13: =P11*'Key Drivers'!$J$104 -> 2234.956 | Q13: =Q11*'Key Drivers'!$J$104 -> 2468.6679 | S13: =SUM(F13:I13) -> 5984.3938 | T13: =SUM(J13:M13) -> 7424.5926 | U13: =SUM(N13:Q13) -> 8875.9202 | V13: =V11*'Key Drivers'!$K$104 -> 9676.9939
C14: Margin | E14: H2'26 = FY26E less H1 actual | F14: =F13/F11 -> 0.095962301 | G14: =G13/G11 -> 0.11258218 | H14: =H13/H11 -> 0.14997359 | I14: =I13/I11 -> 0.14997359 | J14: =J13/J11 -> 0.146 | K14: =K13/K11 -> 0.146 | L14: =L13/L11 -> 0.146 | M14: =M13/M11 -> 0.146 | ... Q14: =Q13/Q11 -> 0.16 | S14: =S13/S11 -> 0.13 | T14: =T13/T11 -> 0.146 | U14: =U13/U11 -> 0.16 | V14: =V13/V11 -> 0.16
C15: D&A | F15: ='GEV Quarterly'!J54 -> 341 | G15: ='GEV Quarterly'!K54 -> 418 | H15: =H11*'Key Drivers'!$H$120 -> 417.65515 | I15: =I11*'Key Drivers'!$H$120 -> 478.1278 | J15: =J11*'Key Drivers'!$I$120 -> 373.41051 | K15: =K11*'Key Drivers'!$I$120 -> 411.51502 | L15: =L11*'Key Drivers'!$I$120 -> 423.28905 | M15: =M11*'Key Drivers'!$I$120 -> 469.94676 | N15: =N11*'Key Drivers'!$J$120 -> 386.66666 | O15: =O11*'Key Drivers'!$J$120 -> 421.71577 | P15: =P11*'Key Drivers'!$J$120 -> 433.02272 | Q15: =Q11*'Key Drivers'!$J$120 -> 478.3044 | S15: =SUM(F15:I15) -> 1654.783 | T15: =SUM(J15:M15) -> 1678.1613 | U15: =SUM(N15:Q15) -> 1719.7095
C16: Adjusted EBIT | F16: =F13-F15 -> 555 | G16: =G13-G15 -> 832 | H16: =H13-H15 -> 1371.9803 | I16: =I13-I15 -> 1570.6305 | J16: =J13-J15 -> 1278.6481 | K16: =K13-K15 -> 1409.1272 | L16: =L13-L15 -> 1449.4443 | M16: =M13-M15 -> 1609.2116 | ... Q16: =Q13-Q15 -> 1990.3635 | S16: =S13-S15 -> 4329.6109 | T16: =T13-T15 -> 5746.4312 | U16: =U13-U15 -> 7156.2107
C17: Taxes | F17: =F16*'Key Drivers'!$H$124 -> 138.75 | G17: =G16*'Key Drivers'!$H$124 -> 208 | H17: =H16*'Key Drivers'!$H$124 -> 342.99508 | I17: =I16*'Key Drivers'!$H$124 -> 392.65764 | J17: =J16*'Key Drivers'!$I$124 -> 319.66203 | K17: =K16*'Key Drivers'!$I$124 -> 352.28179 | L17: =L16*'Key Drivers'!$I$124 -> 362.36108 | M17: =M16*'Key Drivers'!$I$124 -> 402.30291 | N17: =N16*'Key Drivers'!$J$124 -> 402.25805 | O17: =O16*'Key Drivers'!$J$124 -> 438.72044 | P17: =P16*'Key Drivers'!$J$124 -> 450.48331 | Q17: =Q16*'Key Drivers'!$J$124 -> 497.59087 | S17: =SUM(F17:I17) -> 1082.4027 | T17: =SUM(J17:M17) -> 1436.6078 | U17: =SUM(N17:Q17) -> 1789.0527
C18: NOPAT | F18: =F16-F17 -> 416.25 | G18: =G16-G17 -> 624 | H18: =H16-H17 -> 1028.9853 | I18: =I16-I17 -> 1177.9729 | J18: =J16-J17 -> 958.98609 | K18: =K16-K17 -> 1056.8454 | L18: =L16-L17 -> 1087.0832 | M18: =M16-M17 -> 1206.9087 | ... Q18: =Q16-Q17 -> 1492.7726 | S18: =S16-S17 -> 3247.2082 | T18: =T16-T17 -> 4309.8234 | U18: =U16-U17 -> 5367.158
C19: Add back: D&A | F19: =F15 -> 341 | G19: =G15 -> 418 | H19: =H15 -> 417.65515 | I19: =I15 -> 478.1278 | J19: =J15 -> 373.41051 | K19: =K15 -> 411.51502 | L19: =L15 -> 423.28905 | M19: =M15 -> 469.94676 | ... Q19: =Q15 -> 478.3044 | S19: =S15 -> 1654.783 | T19: =T15 -> 1678.1613 | U19: =U15 -> 1719.7095
C20: Capex | F20: ='GEV Quarterly'!J308 -> -397 | G20: ='GEV Quarterly'!K308 -> -386 | H20: =-H11*'Key Drivers'!$H$121 -> -381.85614 | I20: =-I11*'Key Drivers'!$H$121 -> -437.14542 | J20: =-J11*'Key Drivers'!$I$121 -> -362.09504 | K20: =-K11*'Key Drivers'!$I$121 -> -399.04486 | L20: =-L11*'Key Drivers'!$I$121 -> -410.46211 | M20: =-M11*'Key Drivers'!$I$121 -> -455.70595 | N20: =-N11*'Key Drivers'!$J$121 -> -374.19354 | O20: =-O11*'Key Drivers'!$J$121 -> -408.11203 | P20: =-P11*'Key Drivers'!$J$121 -> -419.05424 | Q20: =-Q11*'Key Drivers'!$J$121 -> -462.87523 | S20: =SUM(F20:I20) -> -1602.0016 | T20: =SUM(J20:M20) -> -1627.308 | U20: =SUM(N20:Q20) -> -1664.235
C21: Working capital | E21: % of revenue change | F21: =SUM('GEV Quarterly'!J301:J304) -> -264 | G21: =SUM('GEV Quarterly'!K301:K304) -> -1732 | H21: =-'Key Drivers'!$H$122*(H11-Revenue!T18) -> -1178.4026 | I21: =-'Key Drivers'!$H$122*(I11-Revenue!U18) -> -1622.8766 | J21: =-'Key Drivers'!$I$122*(J11-Revenue!V18) -> -989.23506 | K21: =-'Key Drivers'!$I$122*(K11-Revenue!W18) -> -683.57601 | L21: =-'Key Drivers'!$I$122*(L11-Revenue!X18) -> -446.9682 | M21: =-'Key Drivers'!$I$122*(M11-Revenue!Y18) -> -290.00828 | N21: =-'Key Drivers'!$J$122*(N11-Revenue!Z18) -> -463.05912 | O21: =-'Key Drivers'!$J$122*(O11-Revenue!AA18) -> -453.43298 | P21: =-'Key Drivers'!$J$122*(P11-Revenue!AB18) -> -456.61356 | Q21: =-'Key Drivers'!$J$122*(Q11-Revenue!AC18) -> -475.34536 | S21: =SUM(F21:I21) -> -4797.2792 | T21: =SUM(J21:M21) -> -2409.7876 | U21: =SUM(N21:Q21) -> -1848.451
C22: Customer deposits | E22: Change in balance below | F22: ='GEV Quarterly'!J305 -> 5574 | G22: ='GEV Quarterly'!K305 -> 8121 | H22: =H41-G41 -> 1924.3537 | I22: =I41-H41 -> 1495.7801 | J22: =J41-I41 -> 1417.4699 | K22: =K41-J41 -> 1223.4016 | L22: =L41-K41 -> 1400.6517 | M22: =M41-L41 -> 1700.4108 | N22: =N41-M41 -> 1100.8719 | O22: =O41-N41 -> 985.10238 | ... Q22: =Q41-P41 -> 1425.4347 | S22: =SUM(F22:I22) -> 17115.134 | T22: =SUM(J22:M22) -> 5741.9341 | U22: =SUM(N22:Q22) -> 4645.0897
C23: Pension and other | F23: =SUM('GEV Quarterly'!J297:J298)+'GEV Quarterly'!J306 -> -627 | G23: =SUM('GEV Quarterly'!K297:K298)+'GEV Quarterly'!K306 -> -1493 | H23: =-H11*'Key Drivers'!$H$123 -> -298.32511 | I23: =-I11*'Key Drivers'!$H$123 -> -341.51986 | J23: =-J11*'Key Drivers'!$I$123 -> -226.3094 | K23: =-K11*'Key Drivers'!$I$123 -> -249.40304 | L23: =-L11*'Key Drivers'!$I$123 -> -256.53882 | M23: =-M11*'Key Drivers'!$I$123 -> -284.81622 | N23: =-N11*'Key Drivers'!$J$123 -> -187.09677 | O23: =-O11*'Key Drivers'!$J$123 -> -204.05602 | P23: =-P11*'Key Drivers'!$J$123 -> -209.52712 | Q23: =-Q11*'Key Drivers'!$J$123 -> -231.43761 | S23: =SUM(F23:I23) -> -2759.845 | T23: =SUM(J23:M23) -> -1017.0675 | U23: =SUM(N23:Q23) -> -832.11752
C24: Unlevered free cash flow | F24: =F18+F19+F20+F21+F22+F23 -> 5043.25 | G24: =G18+G19+G20+G21+G22+G23 -> 5552 | H24: =H18+H19+H20+H21+H22+H23 -> 1512.4102 | I24: =I18+I19+I20+I21+I22+I23 -> 750.33892 | J24: =J18+J19+J20+J21+J22+J23 -> 1172.227 | K24: =K18+K19+K20+K21+K22+K23 -> 1359.7381 | L24: =L18+L19+L20+L21+L22+L23 -> 1797.0548 | M24: =M18+M19+M20+M21+M22+M23 -> 2346.7359 | ... Q24: =Q18+Q19+Q20+Q21+Q22+Q23 -> 2226.8535 | S24: =S18+S19+S20+S21+S22+S23 -> 12857.999 | T24: =T18+T19+T20+T21+T22+T23 -> 6675.7559 | U24: =U18+U19+U20+U21+U22+U23 -> 7387.1537
C25: Memo: UFCF excl. deposits | E25: What the business earns on its own | F25: =F24-F22 -> -530.75 | G25: =G24-G22 -> -2569 | H25: =H24-H22 -> -411.94348 | I25: =I24-I22 -> -745.44116 | J25: =J24-J22 -> -245.2429 | K25: =K24-K22 -> 136.33649 | L25: =L24-L22 -> 396.40315 | M25: =M24-M22 -> 646.32504 | ... Q25: =Q24-Q22 -> 801.41882 | S25: =S24-S22 -> -4257.1346 | T25: =T24-T22 -> 933.82178 | U25: =U24-U22 -> 2742.064
C27: Discount period (years) | E27: Mid-quarter, from 30-Jun-26 | H27: =(H$8-$N$49)/365-0.125 -> 0.12705479 | I27: =(I$8-$N$49)/365-0.125 -> 0.37910959 | J27: =(J$8-$N$49)/365-0.125 -> 0.62568493 | K27: =(K$8-$N$49)/365-0.125 -> 0.875 | L27: =(L$8-$N$49)/365-0.125 -> 1.1270548 | M27: =(M$8-$N$49)/365-0.125 -> 1.3791096 | N27: =(N$8-$N$49)/365-0.125 -> 1.6284247 | O27: =(O$8-$N$49)/365-0.125 -> 1.8777397 | ... Q27: =(Q$8-$N$49)/365-0.125 -> 2.3818493
C28: Discount factor | H28: =1/(1+$N$53)^H27 -> 0.98809383 | I28: =1/(1+$N$53)^I27 -> 0.96489197 | J28: =1/(1+$N$53)^J27 -> 0.94272176 | K28: =1/(1+$N$53)^K27 -> 0.9208231 | L28: =1/(1+$N$53)^L27 -> 0.89920085 | M28: =1/(1+$N$53)^M27 -> 0.87808632 | N28: =1/(1+$N$53)^N27 -> 0.85768908 | O28: =1/(1+$N$53)^O27 -> 0.83776566 | ... Q28: =1/(1+$N$53)^Q27 -> 0.7988837
C29: PV of UFCF | H29: =H24*H28 -> 1494.4032 | I29: =I24*I28 -> 723.996 | J29: =J24*J28 -> 1105.0839 | K29: =K24*K28 -> 1252.0783 | L29: =L24*L28 -> 1615.9132 | M29: =M24*M28 -> 2060.6367 | N29: =N24*N28 -> 1432.3093 | O29: =O24*O28 -> 1388.4947 | ... Q29: =Q24*Q28 -> 1778.997
C31: Customer deposits
C32: Firm gas backlog (GW) | E32: Revenue tab | F32: =Revenue!V58 -> 44 | G32: =Revenue!W58 -> 53 | H32: =Revenue!X58 -> 58.17375 | I32: =Revenue!Y58 -> 63.033833 | J32: =Revenue!Z58 -> 66.047225 | K32: =Revenue!AA58 -> 68.943526 | L32: =Revenue!AB58 -> 71.808433 | M32: =Revenue!AC58 -> 74.542301 | ... Q32: =Revenue!AG58 -> 83.634677
C33: Power equipment RPO | E33: GW x $741mm per GW | F33: ='GEV Quarterly'!J236 -> 28530 | G33: ='GEV Quarterly'!K236 -> 39261 | H33: =H32*'Key Drivers'!$H$125 -> 43106.749 | I33: =I32*'Key Drivers'!$H$125 -> 46708.07 | J33: =J32*'Key Drivers'!$I$125 -> 48940.993 | K33: =K32*'Key Drivers'!$I$125 -> 51087.152 | L33: =L32*'Key Drivers'!$I$125 -> 53210.049 | M33: =M32*'Key Drivers'!$I$125 -> 55235.845 | N33: =N32*'Key Drivers'!$J$125 -> 57202.452 | O33: =O32*'Key Drivers'!$J$125 -> 58977.205 | P33: =P32*'Key Drivers'!$J$125 -> 60565.782 | Q33: =Q32*'Key Drivers'!$J$125 -> 61973.296
C34: Electrification equipment RPO | E34: Revenue tab backlog | F34: ='GEV Quarterly'!J240 -> 38598 | G34: ='GEV Quarterly'!K240 -> 40589 | H34: =Revenue!X92 -> 43408.048 | I34: =Revenue!Y92 -> 47594.228 | J34: =Revenue!Z92 -> 49912.127 | K34: =Revenue!AA92 -> 52349.877 | L34: =Revenue!AB92 -> 55972.593 | M34: =Revenue!AC92 -> 61240.831 | N34: =Revenue!AD92 -> 63385.876 | O34: =Revenue!AE92 -> 65692.275 | ... Q34: =Revenue!AG92 -> 74714.451
C35: Wind equipment RPO | E35: 1.5x trailing Wind equipment revenue | F35: ='GEV Quarterly'!J244 -> 8905 | G35: ='GEV Quarterly'!K244 -> 8197 | H35: ='Key Drivers'!$H$128*SUM(Revenue!U105:X105) -> 8789.4788 | I35: ='Key Drivers'!$H$128*SUM(Revenue!V105:Y105) -> 8462.2924 | J35: ='Key Drivers'!$I$128*SUM(Revenue!W105:Z105) -> 8319.0697 | K35: ='Key Drivers'!$I$128*SUM(Revenue!X105:AA105) -> 7813.6062 | L35: ='Key Drivers'!$I$128*SUM(Revenue!Y105:AB105) -> 7192.4229 | M35: ='Key Drivers'!$I$128*SUM(Revenue!Z105:AC105) -> 6612.6519 | N35: ='Key Drivers'!$J$128*SUM(Revenue!AA105:AD105) -> 6470.429 | O35: ='Key Drivers'!$J$128*SUM(Revenue!AB105:AE105) -> 6280.7985 | P35: ='Key Drivers'!$J$128*SUM(Revenue!AC105:AF105) -> 6043.7604 | Q35: ='Key Drivers'!$J$128*SUM(Revenue!AD105:AG105) -> 5822.5248
C36: Total equipment RPO | F36: =F33+F34+F35 -> 76033 | G36: =G33+G34+G35 -> 88047 | H36: =H33+H34+H35 -> 95304.276 | I36: =I33+I34+I35 -> 102764.59 | J36: =J33+J34+J35 -> 107172.19 | K36: =K33+K34+K35 -> 111250.64 | L36: =L33+L34+L35 -> 116375.07 | M36: =M33+M34+M35 -> 123089.33 | ... Q36: =Q33+Q34+Q35 -> 142510.27
C37: Power deposits, % of Power RPO | E37: Key Drivers, by quarter | F37: ='GEV Quarterly'!J287/'GEV Quarterly'!J236 -> 0.64770417 | G37: ='GEV Quarterly'!K287/'GEV Quarterly'!K236 -> 0.6571152 | H37: =G37+('Key Drivers'!$H$109-G37)*0.5 -> 0.6235576 | I37: ='Key Drivers'!$H$109 -> 0.59 | J37: ='Key Drivers'!$H$109+('Key Drivers'!$I$109-'Key Drivers'!$H$109)*1/4 -> 0.5825 | K37: ='Key Drivers'!$H$109+('Key Drivers'!$I$109-'Key Drivers'!$H$109)*2/4 -> 0.575 | L37: ='Key Drivers'!$H$109+('Key Drivers'!$I$109-'Key Drivers'!$H$109)*3/4 -> 0.5675 | M37: ='Key Drivers'!$H$109+('Key Drivers'!$I$109-'Key Drivers'!$H$109)*4/4 -> 0.56 | N37: ='Key Drivers'!$I$109+('Key Drivers'!$J$109-'Key Drivers'!$I$109)*1/4 -> 0.5525 | O37: ='Key Drivers'!$I$109+('Key Drivers'!$J$109-'Key Drivers'!$I$109)*2/4 -> 0.545 | P37: ='Key Drivers'!$I$109+('Key Drivers'!$J$109-'Key Drivers'!$I$109)*3/4 -> 0.5375 | Q37: ='Key Drivers'!$I$109+('Key Drivers'!$J$109-'Key Drivers'!$I$109)*4/4 -> 0.53
C38: Power deposits | F38: ='GEV Quarterly'!J287 -> 18479 | G38: ='GEV Quarterly'!K287 -> 25799 | H38: =H33*H37 -> 26879.541 | I38: =I33*I37 -> 27557.761 | J38: =J33*J37 -> 28508.129 | K38: =K33*K37 -> 29375.113 | L38: =L33*L37 -> 30196.703 | M38: =M33*M37 -> 30932.073 | N38: =N33*N37 -> 31604.355 | O38: =O33*O37 -> 32142.577 | ... Q38: =Q33*Q37 -> 32845.847
C39: Electrification deposits | F39: ='GEV Quarterly'!J288 -> 8259 | G39: ='GEV Quarterly'!K288 -> 9113 | H39: =H34*'Key Drivers'!$H$126 -> 9766.8108 | I39: =I34*'Key Drivers'!$H$126 -> 10708.701 | J39: =J34*'Key Drivers'!$I$126 -> 11230.229 | K39: =K34*'Key Drivers'!$I$126 -> 11778.722 | L39: =L34*'Key Drivers'!$I$126 -> 12593.833 | M39: =M34*'Key Drivers'!$I$126 -> 13779.187 | N39: =N34*'Key Drivers'!$J$126 -> 14261.822 | O39: =O34*'Key Drivers'!$J$126 -> 14780.762 | P39: =P34*'Key Drivers'!$J$126 -> 15592.986 | Q39: =Q34*'Key Drivers'!$J$126 -> 16810.751
C40: Wind deposits | F40: ='GEV Quarterly'!J289 -> 3173 | G40: ='GEV Quarterly'!K289 -> 3150 | H40: =H35*'Key Drivers'!$H$127 -> 3340.002 | I40: =I35*'Key Drivers'!$H$127 -> 3215.6711 | J40: =J35*'Key Drivers'!$I$127 -> 3161.2465 | K40: =K35*'Key Drivers'!$I$127 -> 2969.1704 | L40: =L35*'Key Drivers'!$I$127 -> 2733.1207 | M40: =M35*'Key Drivers'!$I$127 -> 2512.8077 | N40: =N35*'Key Drivers'!$J$127 -> 2458.763 | O40: =O35*'Key Drivers'!$J$127 -> 2386.7034 | P40: =P35*'Key Drivers'!$J$127 -> 2296.6289 | Q40: =Q35*'Key Drivers'!$J$127 -> 2212.5594
C41: Total customer deposits | F41: =F38+F39+F40 -> 29911 | G41: =G38+G39+G40 -> 38062 | H41: =H38+H39+H40 -> 39986.354 | I41: =I38+I39+I40 -> 41482.134 | J41: =J38+J39+J40 -> 42899.604 | K41: =K38+K39+K40 -> 44123.005 | L41: =L38+L39+L40 -> 45523.657 | M41: =M38+M39+M40 -> 47224.068 | ... Q41: =Q38+Q39+Q40 -> 51869.158
C42: Deposits, % of equipment RPO | F42: =F41/F36 -> 0.39339497 | G42: =G41/G36 -> 0.43229184 | H42: =H41/H36 -> 0.41956516 | I42: =I41/I36 -> 0.40366174 | J42: =J41/J36 -> 0.40028671 | K42: =K41/K36 -> 0.39660902 | L42: =L41/L36 -> 0.39118051 | M42: =M41/M36 -> 0.38365688 | ... Q42: =Q41/Q36 -> 0.36396785
C44: Valuation | K44: Inputs
C45: Exit multiple (EV / FY2029E EBITDA) | E45: Next-12-month EBITDA at Dec-28 | F45: =$N$55 -> 20 | K45: Company | N45: GE Vernova Inc.
C46: FY2029E EBITDA | F46: =V13 -> 9676.9939 | K46: Ticker | N46: NYSE:GEV
C47: Exit value, Dec-28 | F47: =F45*F46 -> 193539.88 | K47: Price ($) | N47: 987.45
C48: Years from valuation date | F48: =(Q$8-$N$49)/365 -> 2.5068493 | K48: Price date | N48: 46296
C49: Discount factor | F49: =1/(1+$N$53)^F48 -> 0.78952498 | K49: Valuation date | N49: 46203
C50: PV of exit value | F50: =F47*F49 -> 152804.57 | K50: Shares, period end (mm) | N50: ='GEV Quarterly'!K372 -> 266.33358
C51: PV of UFCF, Q3'26 to Q4'28 | F51: =SUM(H29:Q29) -> 14351.444 | K51: Dilution (mm) | N51: ='GEV Quarterly'!K30-'GEV Quarterly'!K29 -> 2
C52: Enterprise value, 30-Jun-26 | F52: =F50+F51 -> 167156.01 | K52: Diluted shares (mm) | N52: =N50+N51 -> 268.33358
C53: Exit value % of EV | F53: =F50/F52 -> 0.91414342 | K53: WACC | N53: ='WACC Calculation'!E52 -> 0.098857764
C54: Cash and restricted cash | E54: Jun-26 balance sheet | F54: ='GEV Quarterly'!K333 -> 13120 | K54: Cost of equity | N54: ='WACC Calculation'!E33 -> 0.099728728
C55: Long-term borrowings | F55: =-'GEV Quarterly'!K353 -> -2794 | K55: Exit multiple | N55: ='Key Drivers'!$J$114 -> 20
C56: Noncontrolling interests | F56: =-'GEV Quarterly'!K365 -> -1158 | K56: Market cap ($mm) | N56: =N47*N50 -> 262991.09
C57: Pension and OPEB | F57: =-'GEV Quarterly'!K355 -> -2654 | K57: Market EV ($mm) | N57: =N56-SUM(F54:F58) -> 255093.09
C58: Equity-method investments | F58: ='GEV Quarterly'!K344 -> 1384
C59: Equity value, 30-Jun-26 | F59: =F52+SUM(F54:F58) -> 175054.01
C60: Diluted shares (mm) | F60: =$N$52 -> 268.33358
C62: Value per share | F62: Now | G62: 3 months | H62: 6 months
C63: Date | F63: =$N$48 -> 46296 | G63: =EDATE($N$48,3) -> 46388 | H63: =EDATE($N$48,6) -> 46478
C64: Roll-forward at cost of equity | F64: =(1+$N$54)^((F63-$N$49)/365) -> 1.0245174 | G64: =(1+$N$54)^((G63-$N$49)/365) -> 1.0493626 | H64: =(1+$N$54)^((H63-$N$49)/365) -> 1.0742505
C65: Value per share ($) | F65: =$F$59*F64/$F$60 -> 668.36912 | G65: =$F$59*G64/$F$60 -> 684.57748 | H65: =$F$59*H64/$F$60 -> 700.81374
C66: Current price ($) | F66: =$N$47 -> 987.45 | G66: =$N$47 -> 987.45 | H66: =$N$47 -> 987.45
C67: Upside / (downside) | F67: =F65/F66-1 -> -0.32313623 | G67: =G65/G66-1 -> -0.30672188 | H67: =H65/H66-1 -> -0.29027926
C69: Implied perpetuity growth | F69: =(F47*$N$53-U24)/(F47+U24) -> 0.058457868
C70: EV / FY2026E EBITDA, DCF | F70: =F52/S13 -> 27.931987
C71: EV / FY2026E EBITDA, market | F71: =$N$57/S13 -> 42.626388
C72: EV / FY2028E EBITDA, DCF | F72: =F52/U13 -> 18.832528
C73: EV / FY2028E EBITDA, market | F73: =$N$57/U13 -> 28.739904
C75: 6-month value per share ($): WACC vs exit multiple
E76: WACC (down) / multiple (across) | F76: =$N$55+-4 -> 16 | G76: =$N$55+-2 -> 18 | H76: =$N$55+0 -> 20 | I76: =$N$55+2 -> 22 | J76: =$N$55+4 -> 24
E77: =$N$53+-0.02 -> 0.078857764 | F77: =((SUMPRODUCT($H$24:$Q$24,(1+$E77)^(-$H$27:$Q$27))+F$76*$F$46*(1+$E77)^(-$F$48))+SUM($F$54:$F$58))*$H$64/$F$60 -> 602.96831 | G77: =((SUMPRODUCT($H$24:$Q$24,(1+$E77)^(-$H$27:$Q$27))+G$76*$F$46*(1+$E77)^(-$F$48))+SUM($F$54:$F$58))*$H$64/$F$60 -> 667.02504 | H77: =((SUMPRODUCT($H$24:$Q$24,(1+$E77)^(-$H$27:$Q$27))+H$76*$F$46*(1+$E77)^(-$F$48))+SUM($F$54:$F$58))*$H$64/$F$60 -> 731.08176 | I77: =((SUMPRODUCT($H$24:$Q$24,(1+$E77)^(-$H$27:$Q$27))+I$76*$F$46*(1+$E77)^(-$F$48))+SUM($F$54:$F$58))*$H$64/$F$60 -> 795.13849 | J77: =((SUMPRODUCT($H$24:$Q$24,(1+$E77)^(-$H$27:$Q$27))+J$76*$F$46*(1+$E77)^(-$F$48))+SUM($F$54:$F$58))*$H$64/$F$60 -> 859.19521
E78: =$N$53+-0.01 -> 0.088857764 | F78: =((SUMPRODUCT($H$24:$Q$24,(1+$E78)^(-$H$27:$Q$27))+F$76*$F$46*(1+$E78)^(-$F$48))+SUM($F$54:$F$58))*$H$64/$F$60 -> 590.52236 | G78: =((SUMPRODUCT($H$24:$Q$24,(1+$E78)^(-$H$27:$Q$27))+G$76*$F$46*(1+$E78)^(-$F$48))+SUM($F$54:$F$58))*$H$64/$F$60 -> 653.11451 | H78: =((SUMPRODUCT($H$24:$Q$24,(1+$E78)^(-$H$27:$Q$27))+H$76*$F$46*(1+$E78)^(-$F$48))+SUM($F$54:$F$58))*$H$64/$F$60 -> 715.70666 | I78: =((SUMPRODUCT($H$24:$Q$24,(1+$E78)^(-$H$27:$Q$27))+I$76*$F$46*(1+$E78)^(-$F$48))+SUM($F$54:$F$58))*$H$64/$F$60 -> 778.29882 | J78: =((SUMPRODUCT($H$24:$Q$24,(1+$E78)^(-$H$27:$Q$27))+J$76*$F$46*(1+$E78)^(-$F$48))+SUM($F$54:$F$58))*$H$64/$F$60 -> 840.89097
E79: =$N$53+0 -> 0.098857764 | F79: =((SUMPRODUCT($H$24:$Q$24,(1+$E79)^(-$H$27:$Q$27))+F$76*$F$46*(1+$E79)^(-$F$48))+SUM($F$54:$F$58))*$H$64/$F$60 -> 578.46574 | G79: =((SUMPRODUCT($H$24:$Q$24,(1+$E79)^(-$H$27:$Q$27))+G$76*$F$46*(1+$E79)^(-$F$48))+SUM($F$54:$F$58))*$H$64/$F$60 -> 639.63974 | H79: =((SUMPRODUCT($H$24:$Q$24,(1+$E79)^(-$H$27:$Q$27))+H$76*$F$46*(1+$E79)^(-$F$48))+SUM($F$54:$F$58))*$H$64/$F$60 -> 700.81374 | I79: =((SUMPRODUCT($H$24:$Q$24,(1+$E79)^(-$H$27:$Q$27))+I$76*$F$46*(1+$E79)^(-$F$48))+SUM($F$54:$F$58))*$H$64/$F$60 -> 761.98774 | J79: =((SUMPRODUCT($H$24:$Q$24,(1+$E79)^(-$H$27:$Q$27))+J$76*$F$46*(1+$E79)^(-$F$48))+SUM($F$54:$F$58))*$H$64/$F$60 -> 823.16174
E80: =$N$53+0.01 -> 0.10885776 | F80: =((SUMPRODUCT($H$24:$Q$24,(1+$E80)^(-$H$27:$Q$27))+F$76*$F$46*(1+$E80)^(-$F$48))+SUM($F$54:$F$58))*$H$64/$F$60 -> 566.78285 | G80: =((SUMPRODUCT($H$24:$Q$24,(1+$E80)^(-$H$27:$Q$27))+G$76*$F$46*(1+$E80)^(-$F$48))+SUM($F$54:$F$58))*$H$64/$F$60 -> 626.58325 | H80: =((SUMPRODUCT($H$24:$Q$24,(1+$E80)^(-$H$27:$Q$27))+H$76*$F$46*(1+$E80)^(-$F$48))+SUM($F$54:$F$58))*$H$64/$F$60 -> 686.38364 | I80: =((SUMPRODUCT($H$24:$Q$24,(1+$E80)^(-$H$27:$Q$27))+I$76*$F$46*(1+$E80)^(-$F$48))+SUM($F$54:$F$58))*$H$64/$F$60 -> 746.18403 | J80: =((SUMPRODUCT($H$24:$Q$24,(1+$E80)^(-$H$27:$Q$27))+J$76*$F$46*(1+$E80)^(-$F$48))+SUM($F$54:$F$58))*$H$64/$F$60 -> 805.98442
E81: =$N$53+0.02 -> 0.11885776 | F81: =((SUMPRODUCT($H$24:$Q$24,(1+$E81)^(-$H$27:$Q$27))+F$76*$F$46*(1+$E81)^(-$F$48))+SUM($F$54:$F$58))*$H$64/$F$60 -> 555.45885 | G81: =((SUMPRODUCT($H$24:$Q$24,(1+$E81)^(-$H$27:$Q$27))+G$76*$F$46*(1+$E81)^(-$F$48))+SUM($F$54:$F$58))*$H$64/$F$60 -> 613.92839 | H81: =((SUMPRODUCT($H$24:$Q$24,(1+$E81)^(-$H$27:$Q$27))+H$76*$F$46*(1+$E81)^(-$F$48))+SUM($F$54:$F$58))*$H$64/$F$60 -> 672.39794 | I81: =((SUMPRODUCT($H$24:$Q$24,(1+$E81)^(-$H$27:$Q$27))+I$76*$F$46*(1+$E81)^(-$F$48))+SUM($F$54:$F$58))*$H$64/$F$60 -> 730.86749 | J81: =((SUMPRODUCT($H$24:$Q$24,(1+$E81)^(-$H$27:$Q$27))+J$76*$F$46*(1+$E81)^(-$F$48))+SUM($F$54:$F$58))*$H$64/$F$60 -> 789.33703
C83: Checks
C84: FY26 EBITDA margin guide (low, high) | F84: 0.12 | G84: 0.14
C85: FY2026E EBITDA margin | F85: =IF(AND(S14>=F84,S14<=G84),"In range ("&TEXT(S14,"0.0%")&")","Outside ("&TEXT(S14,"0.0%")&")") -> In range (13.0%)
C86: FY26 FCF guide, $mm (low, high) | F86: 11500 | G86: 12500
C87: FY2026E FCF (H1 reported + H2 UFCF) | F87: =SUM('GEV Quarterly'!J325:K325)+H24+I24 -> 12159.749
C88: FY2026E FCF vs guide | F88: =IF(AND(F87>=F86-500,F87<=G86+500),"In line ("&TEXT(F87,"#,##0")&")","Check ("&TEXT(F87,"#,##0")&")") -> In line (12,160)
C89: Thesis value per share, selected case ($) | F89: =INDEX('Key Drivers'!J162:J164,MATCH('Key Drivers'!$D$5,'Key Drivers'!$C162:$C164,0)) -> 700
C90: 6-month DCF value vs thesis | F90: =H65/F89-1 -> 0.0011624881

Sheet Reverse DCF
C2: GE Vernova (GEV)
C3: Reverse DCF: what the price needs, on consensus revenue
C4: US$ millions unless stated. Blue = input, black = formula, orange = assumption, grey = projection.
F6: Actual | H6: Projected quarters | S6: Fiscal year
C7: Fiscal period | E7: Note | F7: Q1'26A | G7: Q2'26A | H7: Q3'26E | I7: Q4'26E | J7: Q1'27E | K7: Q2'27E | L7: Q3'27E | M7: Q4'27E | N7: Q1'28E | O7: Q2'28E | P7: Q3'28E | Q7: Q4'28E | S7: FY2026E | T7: FY2027E | U7: FY2028E | V7: FY2029E
C8: Period end | F8: 46112 | G8: 46203 | H8: 46295 | I8: 46387 | J8: 46477 | K8: 46568 | L8: 46660 | M8: 46752 | N8: 46843 | O8: 46934 | P8: 47026 | Q8: 47118 | S8: 46387 | T8: 46752 | U8: 47118 | V8: 47483
C10: Cash flow (consensus, with the margin solved)
C11: Revenue | E11: Consensus DCF | F11: ='Consensus DCF'!F11 -> 9337 | G11: ='Consensus DCF'!G11 -> 11103 | H11: ='Consensus DCF'!H11 -> 12318.683 | I11: ='Consensus DCF'!I11 -> 13538.317 | J11: ='Consensus DCF'!J11 -> 11133.906 | K11: ='Consensus DCF'!K11 -> 12630.995 | L11: ='Consensus DCF'!L11 -> 13818.963 | M11: ='Consensus DCF'!M11 -> 15187.136 | ... Q11: ='Consensus DCF'!Q11 -> 17438.254 | S11: ='Consensus DCF'!S11 -> 46297 | T11: ='Consensus DCF'!T11 -> 52771 | U11: ='Consensus DCF'!U11 -> 60593 | V11: ='Consensus DCF'!V11 -> 67864.16
C12: EBITDA | E12: Revenue x solved margin | F12: ='Consensus DCF'!F14 -> 896 | G12: ='Consensus DCF'!G14 -> 1250 | H12: =H11*H13 -> 1990.9415 | I12: =I11*I13 -> 2188.0585 | J12: =J11*J13 -> 1925.3539 | K12: =K11*K13 -> 2327.0649 | L12: =L11*L13 -> 2702.1861 | M12: =M11*M13 -> 3141.4484 | N12: =N11*N13 -> 2788.9661 | O12: =O11*O13 -> 3163.9765 | ... Q12: =Q11*Q13 -> 3804.272 | S12: =SUM(F12:I12) -> 6325 | T12: =SUM(J12:M12) -> 10096.053 | U12: =SUM(N12:Q12) -> 13218.769 | V12: =V11*V13 -> 14805.021
C13: Margin | E13: H2'26 consensus, then ramp to solved | F13: =F12/F11 -> 0.095962301 | G13: =G12/G11 -> 0.11258218 | H13: =$F$30+($F$37-$F$30)*H14 -> 0.16161968 | I13: =$F$30+($F$37-$F$30)*I14 -> 0.16161968 | J13: =$F$30+($F$37-$F$30)*J14 -> 0.17292708 | K13: =$F$30+($F$37-$F$30)*K14 -> 0.18423449 | L13: =$F$30+($F$37-$F$30)*L14 -> 0.19554189 | M13: =$F$30+($F$37-$F$30)*M14 -> 0.2068493 | N13: =$F$30+($F$37-$F$30)*N14 -> 0.2181567 | O13: =$F$30+($F$37-$F$30)*O14 -> 0.2181567 | ... Q13: =$F$30+($F$37-$F$30)*Q14 -> 0.2181567 | S13: =S12/S11 -> 0.13661792 | T13: =T12/T11 -> 0.19131821 | U13: =U12/U11 -> 0.2181567 | V13: =U13 -> 0.2181567
C14: Ramp weight | E14: 0 = H2 26 margin, 1 = solved | H14: 0 | I14: 0 | J14: 0.2 | K14: 0.4 | L14: 0.6 | M14: 0.8 | N14: 1 | O14: 1 | P14: 1 | Q14: 1
C15: D&A | E15: Consensus DCF | F15: ='Consensus DCF'!F16 -> 341 | G15: ='Consensus DCF'!G16 -> 418 | H15: ='Consensus DCF'!H16 -> 438.30251 | I15: ='Consensus DCF'!I16 -> 481.69749 | J15: ='Consensus DCF'!J16 -> 298.96619 | K15: ='Consensus DCF'!K16 -> 339.16583 | L15: ='Consensus DCF'!L16 -> 371.06499 | M15: ='Consensus DCF'!M16 -> 407.80299 | ... Q15: ='Consensus DCF'!Q16 -> 468.81515 | S15: =SUM(F15:I15) -> 1679 | T15: =SUM(J15:M15) -> 1417 | U15: =SUM(N15:Q15) -> 1629
C16: EBIT | F16: =F12-F15 -> 555 | G16: =G12-G15 -> 832 | H16: =H12-H15 -> 1552.639 | I16: =I12-I15 -> 1706.361 | J16: =J12-J15 -> 1626.3877 | K16: =K12-K15 -> 1987.8991 | L16: =L12-L15 -> 2331.1212 | M16: =M12-M15 -> 2733.6454 | ... Q16: =Q12-Q15 -> 3335.4569 | S16: =S12-S15 -> 4646 | T16: =T12-T15 -> 8679.0533 | U16: =U12-U15 -> 11589.769
C17: Tax rate | F17: ='Consensus DCF'!F18 -> 0.25 | G17: ='Consensus DCF'!G18 -> 0.25 | H17: ='Consensus DCF'!H18 -> 0.25 | I17: ='Consensus DCF'!I18 -> 0.25 | J17: ='Consensus DCF'!J18 -> 0.25 | K17: ='Consensus DCF'!K18 -> 0.25 | L17: ='Consensus DCF'!L18 -> 0.25 | M17: ='Consensus DCF'!M18 -> 0.25 | ... Q17: ='Consensus DCF'!Q18 -> 0.25
C18: Taxes | F18: =F16*F17 -> 138.75 | G18: =G16*G17 -> 208 | H18: =H16*H17 -> 388.15975 | I18: =I16*I17 -> 426.59025 | J18: =J16*J17 -> 406.59693 | K18: =K16*K17 -> 496.97477 | L18: =L16*L17 -> 582.78029 | M18: =M16*M17 -> 683.41134 | ... Q18: =Q16*Q17 -> 833.86422 | S18: =SUM(F18:I18) -> 1161.5 | T18: =SUM(J18:M18) -> 2169.7633 | U18: =SUM(N18:Q18) -> 2897.4422
C19: NOPAT | F19: =F16-F18 -> 416.25 | G19: =G16-G18 -> 624 | H19: =H16-H18 -> 1164.4792 | I19: =I16-I18 -> 1279.7708 | J19: =J16-J18 -> 1219.7908 | K19: =K16-K18 -> 1490.9243 | L19: =L16-L18 -> 1748.3409 | M19: =M16-M18 -> 2050.234 | ... Q19: =Q16-Q18 -> 2501.5927 | S19: =S16-S18 -> 3484.5 | T19: =T16-T18 -> 6509.29 | U19: =U16-U18 -> 8692.3267
C20: Add back: D&A | F20: =F15 -> 341 | G20: =G15 -> 418 | H20: =H15 -> 438.30251 | I20: =I15 -> 481.69749 | J20: =J15 -> 298.96619 | K20: =K15 -> 339.16583 | L20: =L15 -> 371.06499 | M20: =M15 -> 407.80299 | ... Q20: =Q15 -> 468.81515 | S20: =S15 -> 1679 | T20: =T15 -> 1417 | U20: =U15 -> 1629
C21: Capex | E21: Consensus DCF | F21: ='Consensus DCF'!F22 -> -397 | G21: ='Consensus DCF'!G22 -> -386 | H21: ='Consensus DCF'!H22 -> -331.58538 | I21: ='Consensus DCF'!I22 -> -364.41462 | J21: ='Consensus DCF'!J22 -> -307.40561 | K21: ='Consensus DCF'!K22 -> -348.74002 | L21: ='Consensus DCF'!L22 -> -381.53965 | M21: ='Consensus DCF'!M22 -> -419.31472 | ... Q21: ='Consensus DCF'!Q22 -> -458.4546 | S21: =SUM(F21:I21) -> -1479 | T21: =SUM(J21:M21) -> -1457 | U21: =SUM(N21:Q21) -> -1593
C22: Working capital, deposits and other | E22: Consensus DCF | F22: ='Consensus DCF'!F23 -> 4683 | G22: ='Consensus DCF'!G23 -> 4896 | H22: ='Consensus DCF'!H23 -> -212.19638 | I22: ='Consensus DCF'!I23 -> -338.05362 | J22: ='Consensus DCF'!J23 -> 569.8394 | K22: ='Consensus DCF'!K23 -> 398.07603 | L22: ='Consensus DCF'!L23 -> 261.77861 | M22: ='Consensus DCF'!M23 -> 104.80596 | ... Q22: ='Consensus DCF'!Q23 -> -155.84221 | S22: =SUM(F22:I22) -> 9028.75 | T22: =SUM(J22:M22) -> 1334.5 | U22: =SUM(N22:Q22) -> 679.25
C23: Unlevered free cash flow | F23: =F19+F20+F21+F22 -> 5043.25 | G23: =G19+G20+G21+G22 -> 5552 | H23: =H19+H20+H21+H22 -> 1059 | I23: =I19+I20+I21+I22 -> 1059 | J23: =J19+J20+J21+J22 -> 1781.1908 | K23: =K19+K20+K21+K22 -> 1879.4261 | L23: =L19+L20+L21+L22 -> 1999.6448 | M23: =M19+M20+M21+M22 -> 2143.5283 | ... Q23: =Q19+Q20+Q21+Q22 -> 2356.111 | S23: =S19+S20+S21+S22 -> 12713.25 | T23: =T19+T20+T21+T22 -> 7803.79 | U23: =U19+U20+U21+U22 -> 9407.5767
C25: Discount period (years) | E25: Mid-quarter, from 30-Jun-26 | H25: =(H$8-$N$56)/365-0.125 -> 0.12705479 | I25: =(I$8-$N$56)/365-0.125 -> 0.37910959 | J25: =(J$8-$N$56)/365-0.125 -> 0.62568493 | K25: =(K$8-$N$56)/365-0.125 -> 0.875 | L25: =(L$8-$N$56)/365-0.125 -> 1.1270548 | M25: =(M$8-$N$56)/365-0.125 -> 1.3791096 | N25: =(N$8-$N$56)/365-0.125 -> 1.6284247 | O25: =(O$8-$N$56)/365-0.125 -> 1.8777397 | ... Q25: =(Q$8-$N$56)/365-0.125 -> 2.3818493
C26: Discount factor | H26: =1/(1+$N$60)^H25 -> 0.98809383 | I26: =1/(1+$N$60)^I25 -> 0.96489197 | J26: =1/(1+$N$60)^J25 -> 0.94272176 | K26: =1/(1+$N$60)^K25 -> 0.9208231 | L26: =1/(1+$N$60)^L25 -> 0.89920085 | M26: =1/(1+$N$60)^M25 -> 0.87808632 | N26: =1/(1+$N$60)^N25 -> 0.85768908 | O26: =1/(1+$N$60)^O25 -> 0.83776566 | ... Q26: =1/(1+$N$60)^Q25 -> 0.7988837
C27: PV of UFCF | H27: =H23*H26 -> 1046.3914 | I27: =I23*I26 -> 1021.8206 | J27: =J23*J26 -> 1679.1673 | K27: =K23*K26 -> 1730.619 | L27: =L23*L26 -> 1798.0823 | M27: =M23*M26 -> 1882.2028 | N27: =N23*N26 -> 2013.4603 | O27: =O23*O26 -> 1969.3411 | ... Q27: =Q23*Q26 -> 1882.2587
C29: Solve for the FY2028E margin
C30: Starting margin (H2'26 consensus) | F30: ='Consensus DCF'!H15 -> 0.16161968
C31: EV implied by the price, 30-Jun-26 | E31: Price x shares, rolled back, less bridge | F31: =$N$54*$N$59/F71-SUM(F61:F65) -> 250727.18
C32: UFCF if margin stays at the starting level | H32: =(H11*$F$30-H15)*(1-H17)+H15+H21+H22 -> 1059 | I32: =(I11*$F$30-I15)*(1-I17)+I15+I21+I22 -> 1059 | J32: =(J11*$F$30-J15)*(1-J17)+J15+J21+J22 -> 1686.7691 | K32: =(K11*$F$30-K15)*(1-K17)+K15+K21+K22 -> 1665.1905 | L32: =(L11*$F$30-L15)*(1-L17)+L15+L21+L22 -> 1648.0674 | M32: =(M11*$F$30-M15)*(1-M17)+M15+M21+M22 -> 1628.347 | N32: =(N11*$F$30-N15)*(1-N17)+N15+N21+N22 -> 1805.4542 | O32: =(O11*$F$30-O15)*(1-O17)+O15+O21+O22 -> 1735.7294 | ... Q32: =(Q11*$F$30-Q15)*(1-Q17)+Q15+Q21+Q22 -> 1616.6808
C33: PV of the above | H33: =H32*H26 -> 1046.3914 | I33: =I32*I26 -> 1021.8206 | J33: =J32*J26 -> 1590.1539 | K33: =K32*K26 -> 1533.3458 | L33: =L32*L26 -> 1481.9436 | M33: =M32*M26 -> 1429.8292 | N33: =N32*N26 -> 1548.5183 | O33: =O32*O26 -> 1454.1345 | ... Q33: =Q32*Q26 -> 1291.5399
C34: PV of after-tax revenue x ramp weight | E34: Value of one point of margin x 100 | H34: =H14*H11*(1-H17)*H26 -> 0 | I34: =I14*I11*(1-I17)*I26 -> 0 | J34: =J14*J11*(1-J17)*J26 -> 1574.4263 | K34: =K14*K11*(1-K17)*K26 -> 3489.2736 | L34: =L14*L11*(1-L17)*L26 -> 5591.7104 | M34: =M14*M11*(1-M17)*M26 -> 8001.3698 | N34: =N14*N11*(1-N17)*N26 -> 8223.673 | O34: =O14*O11*(1-O17)*O26 -> 9112.7303 | ... Q34: =Q14*Q11*(1-Q17)*Q26 -> 10448.353
C35: EV with the margin held flat | E35: PV of flat UFCF + exit value | F35: =SUM(H33:Q33)+$N$62*F56*$F$30*V11 -> 186965.5
C36: Value of one unit of margin uplift | F36: =SUM(H34:Q34)+$N$62*F56*V11 -> 1127786.2
C37: Solved FY2028E EBITDA margin | E37: Value is linear in margin: no goal seek | F37: =$F$30+(F31-F35)/F36 -> 0.2181567
C39: What the price needs
C40: FY2028E margin needed, at the exit multiple | E40: On consensus revenue | F40: =F37 -> 0.2181567
C41: FY2028E EBITDA needed ($mm) | F41: =U12 -> 13218.769
C42: Exit multiple needed, consensus EBITDA | E42: Multiple of FY2029E EBITDA | F42: =(F31-'Consensus DCF'!F38)/(F56*'Consensus DCF'!V14) -> 20.267162
C43: Exit multiple needed, our EBITDA | E43: Selected case on Key Drivers | F43: =(F31-'Regular DCF'!F51)/(F56*'Regular DCF'!V13) -> 30.938307
C44: Market EV / FY2029E consensus EBITDA | F44: =$N$64/V12 -> 17.230174
C45: Consensus FY2028E margin | F45: ='Consensus DCF'!U15 -> 0.21570148
C46: Thesis base FY2028E margin | E46: Key Drivers | F46: ='Key Drivers'!J105 -> 0.16
C47: Thesis bull FY2028E margin | E47: Key Drivers | F47: ='Key Drivers'!J106 -> 0.18
C48: Thesis bear FY2028E margin | E48: Key Drivers | F48: ='Key Drivers'!J107 -> 0.13
C49: Company 2028 target margin | E49: Dec-25 outlook: $52B revenue, 20% | F49: 0.2
C51: Valuation (check: value now equals the price) | K51: Inputs (from Regular DCF)
C52: Exit multiple (EV / FY2029E EBITDA) | E52: Next-12-month EBITDA at Dec-28 | F52: =$N$62 -> 20 | K52: Company | N52: ='Regular DCF'!N45 -> GE Vernova Inc.
C53: FY2029E EBITDA | F53: =V12 -> 14805.021 | K53: Ticker | N53: ='Regular DCF'!N46 -> NYSE:GEV
C54: Exit value, Dec-28 | F54: =F52*F53 -> 296100.42 | K54: Price ($) | N54: ='Regular DCF'!N47 -> 987.45
C55: Years from valuation date | F55: =(Q$8-$N$56)/365 -> 2.5068493 | K55: Price date | N55: ='Regular DCF'!N48 -> 46296
C56: Discount factor | F56: =1/(1+$N$60)^F55 -> 0.78952498 | K56: Valuation date | N56: ='Regular DCF'!N49 -> 46203
C57: PV of exit value | F57: =F54*F56 -> 233778.68 | K57: Shares, period end (mm) | N57: ='Regular DCF'!N50 -> 266.33358
C58: PV of UFCF, Q3'26 to Q4'28 | F58: =SUM(H27:Q27) -> 16948.497 | K58: Dilution (mm) | N58: ='Regular DCF'!N51 -> 2
C59: Enterprise value, 30-Jun-26 | F59: =F57+F58 -> 250727.18 | K59: Diluted shares (mm) | N59: ='Regular DCF'!N52 -> 268.33358
C60: Exit value % of EV | F60: =F57/F59 -> 0.93240264 | K60: WACC | N60: ='Regular DCF'!N53 -> 0.098857764
C61: Cash and restricted cash | E61: Jun-26 balance sheet | F61: ='GEV Quarterly'!K333 -> 13120 | K61: Cost of equity | N61: ='Regular DCF'!N54 -> 0.099728728
C62: Long-term borrowings | F62: =-'GEV Quarterly'!K353 -> -2794 | K62: Exit multiple | N62: ='Key Drivers'!$J$115 -> 20
C63: Noncontrolling interests | F63: =-'GEV Quarterly'!K365 -> -1158 | K63: Market cap ($mm) | N63: ='Regular DCF'!N56 -> 262991.09
C64: Pension and OPEB | F64: =-'GEV Quarterly'!K355 -> -2654 | K64: Market EV ($mm) | N64: ='Regular DCF'!N57 -> 255093.09
C65: Equity-method investments | F65: ='GEV Quarterly'!K344 -> 1384
C66: Equity value, 30-Jun-26 | F66: =F59+SUM(F61:F65) -> 258625.18
C67: Diluted shares (mm) | F67: =$N$59 -> 268.33358
C69: Value per share | F69: Now | G69: 3 months | H69: 6 months
C70: Date | F70: =$N$55 -> 46296 | G70: =EDATE($N$55,3) -> 46388 | H70: =EDATE($N$55,6) -> 46478
C71: Roll-forward at cost of equity | F71: =(1+$N$61)^((F70-$N$56)/365) -> 1.0245174 | G71: =(1+$N$61)^((G70-$N$56)/365) -> 1.0493626 | H71: =(1+$N$61)^((H70-$N$56)/365) -> 1.0742505
C72: Value per share ($) | F72: =$F$66*F71/$F$67 -> 987.45 | G72: =$F$66*G71/$F$67 -> 1011.3963 | H72: =$F$66*H71/$F$67 -> 1035.3837
C73: Current price ($) | F73: =$N$54 -> 987.45 | G73: =$N$54 -> 987.45 | H73: =$N$54 -> 987.45
C74: Upside / (downside) | F74: =F72/F73-1 -> 0 | G74: =G72/G73-1 -> 0.024250597 | H74: =H72/H73-1 -> 0.048542962
C76: Implied perpetuity growth | F76: =(F54*$N$60-U23)/(F54+U23) -> 0.065020389
C77: EV / FY2026E EBITDA, DCF | F77: =F59/S12 -> 39.640661
C78: EV / FY2026E EBITDA, market | F78: =$N$64/S12 -> 40.330924
C79: EV / FY2028E EBITDA, DCF | F79: =F59/U12 -> 18.967514
C80: EV / FY2028E EBITDA, market | F80: =$N$64/U12 -> 19.297795
C82: Check: value now less price (should be zero) | F82: =F72-F73 -> 0
C84: FY2028E margin the price needs: WACC vs exit multiple
E85: WACC (down) / multiple (across) | F85: =$N$62+-4 -> 16 | G85: =$N$62+-2 -> 18 | H85: =$N$62+0 -> 20 | I85: =$N$62+2 -> 22 | J85: =$N$62+4 -> 24
E86: =$N$60+-0.02 -> 0.078857764 | F86: =$F$30+($F$31-(SUMPRODUCT($H$32:$Q$32,(1+$E86)^(-$H$25:$Q$25))+F$85*$F$30*$V$11*(1+$E86)^(-$F$55)))/(SUMPRODUCT($H$14:$Q$14,$H$11:$Q$11,1-$H$17:$Q$17,(1+$E86)^(-$H$25:$Q$25))+F$85*$V$11*(1+$E86)^(-$F$55)) -> 0.25740438 | G86: =$F$30+($F$31-(SUMPRODUCT($H$32:$Q$32,(1+$E86)^(-$H$25:$Q$25))+G$85*$F$30*$V$11*(1+$E86)^(-$F$55)))/(SUMPRODUCT($H$14:$Q$14,$H$11:$Q$11,1-$H$17:$Q$17,(1+$E86)^(-$H$25:$Q$25))+G$85*$V$11*(1+$E86)^(-$F$55)) -> 0.23035724 | H86: =$F$30+($F$31-(SUMPRODUCT($H$32:$Q$32,(1+$E86)^(-$H$25:$Q$25))+H$85*$F$30*$V$11*(1+$E86)^(-$F$55)))/(SUMPRODUCT($H$14:$Q$14,$H$11:$Q$11,1-$H$17:$Q$17,(1+$E86)^(-$H$25:$Q$25))+H$85*$V$11*(1+$E86)^(-$F$55)) -> 0.20845367 | I86: =$F$30+($F$31-(SUMPRODUCT($H$32:$Q$32,(1+$E86)^(-$H$25:$Q$25))+I$85*$F$30*$V$11*(1+$E86)^(-$F$55)))/(SUMPRODUCT($H$14:$Q$14,$H$11:$Q$11,1-$H$17:$Q$17,(1+$E86)^(-$H$25:$Q$25))+I$85*$V$11*(1+$E86)^(-$F$55)) -> 0.19035383 | J86: =$F$30+($F$31-(SUMPRODUCT($H$32:$Q$32,(1+$E86)^(-$H$25:$Q$25))+J$85*$F$30*$V$11*(1+$E86)^(-$F$55)))/(SUMPRODUCT($H$14:$Q$14,$H$11:$Q$11,1-$H$17:$Q$17,(1+$E86)^(-$H$25:$Q$25))+J$85*$V$11*(1+$E86)^(-$F$55)) -> 0.17514606
E87: =$N$60+-0.01 -> 0.088857764 | F87: =$F$30+($F$31-(SUMPRODUCT($H$32:$Q$32,(1+$E87)^(-$H$25:$Q$25))+F$85*$F$30*$V$11*(1+$E87)^(-$F$55)))/(SUMPRODUCT($H$14:$Q$14,$H$11:$Q$11,1-$H$17:$Q$17,(1+$E87)^(-$H$25:$Q$25))+F$85*$V$11*(1+$E87)^(-$F$55)) -> 0.26333337 | G87: =$F$30+($F$31-(SUMPRODUCT($H$32:$Q$32,(1+$E87)^(-$H$25:$Q$25))+G$85*$F$30*$V$11*(1+$E87)^(-$F$55)))/(SUMPRODUCT($H$14:$Q$14,$H$11:$Q$11,1-$H$17:$Q$17,(1+$E87)^(-$H$25:$Q$25))+G$85*$V$11*(1+$E87)^(-$F$55)) -> 0.23567391 | H87: =$F$30+($F$31-(SUMPRODUCT($H$32:$Q$32,(1+$E87)^(-$H$25:$Q$25))+H$85*$F$30*$V$11*(1+$E87)^(-$F$55)))/(SUMPRODUCT($H$14:$Q$14,$H$11:$Q$11,1-$H$17:$Q$17,(1+$E87)^(-$H$25:$Q$25))+H$85*$V$11*(1+$E87)^(-$F$55)) -> 0.21327263 | I87: =$F$30+($F$31-(SUMPRODUCT($H$32:$Q$32,(1+$E87)^(-$H$25:$Q$25))+I$85*$F$30*$V$11*(1+$E87)^(-$F$55)))/(SUMPRODUCT($H$14:$Q$14,$H$11:$Q$11,1-$H$17:$Q$17,(1+$E87)^(-$H$25:$Q$25))+I$85*$V$11*(1+$E87)^(-$F$55)) -> 0.19476027 | J87: =$F$30+($F$31-(SUMPRODUCT($H$32:$Q$32,(1+$E87)^(-$H$25:$Q$25))+J$85*$F$30*$V$11*(1+$E87)^(-$F$55)))/(SUMPRODUCT($H$14:$Q$14,$H$11:$Q$11,1-$H$17:$Q$17,(1+$E87)^(-$H$25:$Q$25))+J$85*$V$11*(1+$E87)^(-$F$55)) -> 0.17920503
E88: =$N$60+0 -> 0.098857764 | F88: =$F$30+($F$31-(SUMPRODUCT($H$32:$Q$32,(1+$E88)^(-$H$25:$Q$25))+F$85*$F$30*$V$11*(1+$E88)^(-$F$55)))/(SUMPRODUCT($H$14:$Q$14,$H$11:$Q$11,1-$H$17:$Q$17,(1+$E88)^(-$H$25:$Q$25))+F$85*$V$11*(1+$E88)^(-$F$55)) -> 0.26934177 | G88: =$F$30+($F$31-(SUMPRODUCT($H$32:$Q$32,(1+$E88)^(-$H$25:$Q$25))+G$85*$F$30*$V$11*(1+$E88)^(-$F$55)))/(SUMPRODUCT($H$14:$Q$14,$H$11:$Q$11,1-$H$17:$Q$17,(1+$E88)^(-$H$25:$Q$25))+G$85*$V$11*(1+$E88)^(-$F$55)) -> 0.24106214 | H88: =$F$30+($F$31-(SUMPRODUCT($H$32:$Q$32,(1+$E88)^(-$H$25:$Q$25))+H$85*$F$30*$V$11*(1+$E88)^(-$F$55)))/(SUMPRODUCT($H$14:$Q$14,$H$11:$Q$11,1-$H$17:$Q$17,(1+$E88)^(-$H$25:$Q$25))+H$85*$V$11*(1+$E88)^(-$F$55)) -> 0.2181567 | I88: =$F$30+($F$31-(SUMPRODUCT($H$32:$Q$32,(1+$E88)^(-$H$25:$Q$25))+I$85*$F$30*$V$11*(1+$E88)^(-$F$55)))/(SUMPRODUCT($H$14:$Q$14,$H$11:$Q$11,1-$H$17:$Q$17,(1+$E88)^(-$H$25:$Q$25))+I$85*$V$11*(1+$E88)^(-$F$55)) -> 0.19922644 | J88: =$F$30+($F$31-(SUMPRODUCT($H$32:$Q$32,(1+$E88)^(-$H$25:$Q$25))+J$85*$F$30*$V$11*(1+$E88)^(-$F$55)))/(SUMPRODUCT($H$14:$Q$14,$H$11:$Q$11,1-$H$17:$Q$17,(1+$E88)^(-$H$25:$Q$25))+J$85*$V$11*(1+$E88)^(-$F$55)) -> 0.18331916
E89: =$N$60+0.01 -> 0.10885776 | F89: =$F$30+($F$31-(SUMPRODUCT($H$32:$Q$32,(1+$E89)^(-$H$25:$Q$25))+F$85*$F$30*$V$11*(1+$E89)^(-$F$55)))/(SUMPRODUCT($H$14:$Q$14,$H$11:$Q$11,1-$H$17:$Q$17,(1+$E89)^(-$H$25:$Q$25))+F$85*$V$11*(1+$E89)^(-$F$55)) -> 0.27542985 | G89: =$F$30+($F$31-(SUMPRODUCT($H$32:$Q$32,(1+$E89)^(-$H$25:$Q$25))+G$85*$F$30*$V$11*(1+$E89)^(-$F$55)))/(SUMPRODUCT($H$14:$Q$14,$H$11:$Q$11,1-$H$17:$Q$17,(1+$E89)^(-$H$25:$Q$25))+G$85*$V$11*(1+$E89)^(-$F$55)) -> 0.24652217 | H89: =$F$30+($F$31-(SUMPRODUCT($H$32:$Q$32,(1+$E89)^(-$H$25:$Q$25))+H$85*$F$30*$V$11*(1+$E89)^(-$F$55)))/(SUMPRODUCT($H$14:$Q$14,$H$11:$Q$11,1-$H$17:$Q$17,(1+$E89)^(-$H$25:$Q$25))+H$85*$V$11*(1+$E89)^(-$F$55)) -> 0.22310612 | I89: =$F$30+($F$31-(SUMPRODUCT($H$32:$Q$32,(1+$E89)^(-$H$25:$Q$25))+I$85*$F$30*$V$11*(1+$E89)^(-$F$55)))/(SUMPRODUCT($H$14:$Q$14,$H$11:$Q$11,1-$H$17:$Q$17,(1+$E89)^(-$H$25:$Q$25))+I$85*$V$11*(1+$E89)^(-$F$55)) -> 0.20375256 | J89: =$F$30+($F$31-(SUMPRODUCT($H$32:$Q$32,(1+$E89)^(-$H$25:$Q$25))+J$85*$F$30*$V$11*(1+$E89)^(-$F$55)))/(SUMPRODUCT($H$14:$Q$14,$H$11:$Q$11,1-$H$17:$Q$17,(1+$E89)^(-$H$25:$Q$25))+J$85*$V$11*(1+$E89)^(-$F$55)) -> 0.18748868
E90: =$N$60+0.02 -> 0.11885776 | F90: =$F$30+($F$31-(SUMPRODUCT($H$32:$Q$32,(1+$E90)^(-$H$25:$Q$25))+F$85*$F$30*$V$11*(1+$E90)^(-$F$55)))/(SUMPRODUCT($H$14:$Q$14,$H$11:$Q$11,1-$H$17:$Q$17,(1+$E90)^(-$H$25:$Q$25))+F$85*$V$11*(1+$E90)^(-$F$55)) -> 0.28159791 | G90: =$F$30+($F$31-(SUMPRODUCT($H$32:$Q$32,(1+$E90)^(-$H$25:$Q$25))+G$85*$F$30*$V$11*(1+$E90)^(-$F$55)))/(SUMPRODUCT($H$14:$Q$14,$H$11:$Q$11,1-$H$17:$Q$17,(1+$E90)^(-$H$25:$Q$25))+G$85*$V$11*(1+$E90)^(-$F$55)) -> 0.25205429 | H90: =$F$30+($F$31-(SUMPRODUCT($H$32:$Q$32,(1+$E90)^(-$H$25:$Q$25))+H$85*$F$30*$V$11*(1+$E90)^(-$F$55)))/(SUMPRODUCT($H$14:$Q$14,$H$11:$Q$11,1-$H$17:$Q$17,(1+$E90)^(-$H$25:$Q$25))+H$85*$V$11*(1+$E90)^(-$F$55)) -> 0.22812114 | I90: =$F$30+($F$31-(SUMPRODUCT($H$32:$Q$32,(1+$E90)^(-$H$25:$Q$25))+I$85*$F$30*$V$11*(1+$E90)^(-$F$55)))/(SUMPRODUCT($H$14:$Q$14,$H$11:$Q$11,1-$H$17:$Q$17,(1+$E90)^(-$H$25:$Q$25))+I$85*$V$11*(1+$E90)^(-$F$55)) -> 0.20833887 | J90: =$F$30+($F$31-(SUMPRODUCT($H$32:$Q$32,(1+$E90)^(-$H$25:$Q$25))+J$85*$F$30*$V$11*(1+$E90)^(-$F$55)))/(SUMPRODUCT($H$14:$Q$14,$H$11:$Q$11,1-$H$17:$Q$17,(1+$E90)^(-$H$25:$Q$25))+J$85*$V$11*(1+$E90)^(-$F$55)) -> 0.19171379

Sheet Consensus DCF
C2: GE Vernova (GEV)
C3: Consensus DCF: Street FY26-FY28, quarterly, 6-month view
C4: US$ millions unless stated. Blue = input, black = formula, orange = assumption, grey = projection.
F6: Actual | H6: Projected quarters | S6: Fiscal year
C7: Fiscal period | E7: Note | F7: Q1'26A | G7: Q2'26A | H7: Q3'26E | I7: Q4'26E | J7: Q1'27E | K7: Q2'27E | L7: Q3'27E | M7: Q4'27E | N7: Q1'28E | O7: Q2'28E | P7: Q3'28E | Q7: Q4'28E | S7: FY2026E | T7: FY2027E | U7: FY2028E | V7: FY2029E
C8: Period end | F8: 46112 | G8: 46203 | H8: 46295 | I8: 46387 | J8: 46477 | K8: 46568 | L8: 46660 | M8: 46752 | N8: 46843 | O8: 46934 | P8: 47026 | Q8: 47118 | S8: 46387 | T8: 46752 | U8: 47118 | V8: 47483
C10: Cash flow
C11: Revenue | E11: Consensus FY26-28, split by seasonality | F11: ='Regular DCF'!F11 -> 9337 | G11: ='Regular DCF'!G11 -> 11103 | H11: =($S11-$F11-$G11)*H13 -> 12318.683 | I11: =($S11-$F11-$G11)*I13 -> 13538.317 | J11: =$T11*J13 -> 11133.906 | K11: =$T11*K13 -> 12630.995 | L11: =$T11*L13 -> 13818.963 | M11: =$T11*M13 -> 15187.136 | N11: =$U11*N13 -> 12784.233 | O11: =$U11*O13 -> 14503.229 | P11: =$U11*P13 -> 15867.284 | Q11: =$U11*Q13 -> 17438.254 | S11: 46297 | T11: 52771 | U11: 60593 | V11: =U11*(1+V12) -> 67864.16
C12: Growth, YoY | E12: FY29E: assumption | F12: =F11/Revenue!R18-1 -> 0.1624751 | G12: =G11/Revenue!S18-1 -> 0.21850307 | H12: =H11/Revenue!T18-1 -> 0.23569892 | I12: =I11/Revenue!U18-1 -> 0.23569892 | J12: =J11/Revenue!V18-1 -> 0.19245005 | K12: =K11/Revenue!W18-1 -> 0.13762002 | L12: =L11/Revenue!X18-1 -> 0.15804557 | M12: =M11/Revenue!Y18-1 -> 0.11173154 | ... Q12: =Q11/Revenue!AC18-1 -> 0.22452679 | S12: =S11/Revenue!$G$18-1 -> 0.21613386 | T12: =T11/S11-1 -> 0.13983627 | U12: =U11/T11-1 -> 0.14822535 | V12: 0.12
C13: Seasonal weight | E13: FY25 revenue pattern | H13: =Revenue!T18/Revenue!$G$18/(Revenue!T18/Revenue!$G$18+Revenue!U18/Revenue!$G$18) -> 0.47641577 | I13: =Revenue!U18/Revenue!$G$18/(Revenue!T18/Revenue!$G$18+Revenue!U18/Revenue!$G$18) -> 0.52358423 | J13: =Revenue!R18/Revenue!$G$18 -> 0.21098532 | K13: =Revenue!S18/Revenue!$G$18 -> 0.23935486 | L13: =Revenue!T18/Revenue!$G$18 -> 0.26186661 | M13: =Revenue!U18/Revenue!$G$18 -> 0.28779322 | N13: =Revenue!R18/Revenue!$G$18 -> 0.21098532 | O13: =Revenue!S18/Revenue!$G$18 -> 0.23935486 | P13: =Revenue!T18/Revenue!$G$18 -> 0.26186661 | Q13: =Revenue!U18/Revenue!$G$18 -> 0.28779322
C14: EBITDA | E14: Annual consensus, pro rata to revenue | F14: ='Regular DCF'!F13 -> 896 | G14: ='Regular DCF'!G13 -> 1250 | H14: =($S14-$F14-$G14)*H11/SUM($H11:$I11) -> 1990.9415 | I14: =($S14-$F14-$G14)*I11/SUM($H11:$I11) -> 2188.0585 | J14: =$T14*J11/$T11 -> 2013.4329 | K14: =$T14*K11/$T11 -> 2284.1634 | L14: =$T14*L11/$T11 -> 2498.9931 | M14: =$T14*M11/$T11 -> 2746.4107 | N14: =$U14*N11/$U11 -> 2757.5781 | O14: =$U14*O11/$U11 -> 3128.368 | P14: =$U14*P11/$U11 -> 3422.5966 | Q14: =$U14*Q11/$U11 -> 3761.4574 | S14: 6325 | T14: 9543 | U14: 13070 | V14: =V11*V15 -> 14638.4
C15: Margin | E15: FY29E holds FY28E | F15: =F14/F11 -> 0.095962301 | G15: =G14/G11 -> 0.11258218 | H15: =H14/H11 -> 0.16161968 | I15: =I14/I11 -> 0.16161968 | J15: =J14/J11 -> 0.18083796 | K15: =K14/K11 -> 0.18083796 | L15: =L14/L11 -> 0.18083796 | M15: =M14/M11 -> 0.18083796 | ... Q15: =Q14/Q11 -> 0.21570148 | S15: =S14/S11 -> 0.13661792 | T15: =T14/T11 -> 0.18083796 | U15: =U14/U11 -> 0.21570148 | V15: =U15 -> 0.21570148
C16: D&A | E16: Consensus EBITDA less EBIT | F16: ='Regular DCF'!F15 -> 341 | G16: ='Regular DCF'!G15 -> 418 | H16: =(($S14-$S17)-$F16-$G16)*H11/SUM($H11:$I11) -> 438.30251 | I16: =(($S14-$S17)-$F16-$G16)*I11/SUM($H11:$I11) -> 481.69749 | J16: =($T14-$T17)*J11/$T11 -> 298.96619 | K16: =($T14-$T17)*K11/$T11 -> 339.16583 | L16: =($T14-$T17)*L11/$T11 -> 371.06499 | M16: =($T14-$T17)*M11/$T11 -> 407.80299 | N16: =($U14-$U17)*N11/$U11 -> 343.69508 | O16: =($U14-$U17)*O11/$U11 -> 389.90906 | P16: =($U14-$U17)*P11/$U11 -> 426.58071 | Q16: =($U14-$U17)*Q11/$U11 -> 468.81515 | S16: =S14-S17 -> 1679 | T16: =T14-T17 -> 1417 | U16: =U14-U17 -> 1629
C17: EBIT | F17: =F14-F16 -> 555 | G17: =G14-G16 -> 832 | H17: =H14-H16 -> 1552.639 | I17: =I14-I16 -> 1706.361 | J17: =J14-J16 -> 1714.4667 | K17: =K14-K16 -> 1944.9976 | L17: =L14-L16 -> 2127.9281 | M17: =M14-M16 -> 2338.6077 | ... Q17: =Q14-Q16 -> 3292.6422 | S17: 4646 | T17: 8126 | U17: 11441
C18: Tax rate | F18: ='Key Drivers'!$H$124 -> 0.25 | G18: ='Key Drivers'!$H$124 -> 0.25 | H18: ='Key Drivers'!$H$124 -> 0.25 | I18: ='Key Drivers'!$H$124 -> 0.25 | J18: ='Key Drivers'!$I$124 -> 0.25 | K18: ='Key Drivers'!$I$124 -> 0.25 | L18: ='Key Drivers'!$I$124 -> 0.25 | M18: ='Key Drivers'!$I$124 -> 0.25 | N18: ='Key Drivers'!$J$124 -> 0.25 | O18: ='Key Drivers'!$J$124 -> 0.25 | P18: ='Key Drivers'!$J$124 -> 0.25 | Q18: ='Key Drivers'!$J$124 -> 0.25 | S18: ='Key Drivers'!$H$124 -> 0.25 | T18: ='Key Drivers'!$I$124 -> 0.25 | U18: ='Key Drivers'!$J$124 -> 0.25
C19: Taxes | F19: =F17*F18 -> 138.75 | G19: =G17*G18 -> 208 | H19: =H17*H18 -> 388.15975 | I19: =I17*I18 -> 426.59025 | J19: =J17*J18 -> 428.61667 | K19: =K17*K18 -> 486.24939 | L19: =L17*L18 -> 531.98202 | M19: =M17*M18 -> 584.65192 | ... Q19: =Q17*Q18 -> 823.16055 | S19: =SUM(F19:I19) -> 1161.5 | T19: =SUM(J19:M19) -> 2031.5 | U19: =SUM(N19:Q19) -> 2860.25
C20: NOPAT | F20: =F17-F19 -> 416.25 | G20: =G17-G19 -> 624 | H20: =H17-H19 -> 1164.4792 | I20: =I17-I19 -> 1279.7708 | J20: =J17-J19 -> 1285.85 | K20: =K17-K19 -> 1458.7482 | L20: =L17-L19 -> 1595.9461 | M20: =M17-M19 -> 1753.9558 | ... Q20: =Q17-Q19 -> 2469.4817 | S20: =SUM(F20:I20) -> 3484.5 | T20: =SUM(J20:M20) -> 6094.5 | U20: =SUM(N20:Q20) -> 8580.75
C21: Add back: D&A | F21: =F16 -> 341 | G21: =G16 -> 418 | H21: =H16 -> 438.30251 | I21: =I16 -> 481.69749 | J21: =J16 -> 298.96619 | K21: =K16 -> 339.16583 | L21: =L16 -> 371.06499 | M21: =M16 -> 407.80299 | ... Q21: =Q16 -> 468.81515 | S21: =SUM(F21:I21) -> 1679 | T21: =SUM(J21:M21) -> 1417 | U21: =SUM(N21:Q21) -> 1629
C22: Capex | E22: Consensus | F22: ='Regular DCF'!F20 -> -397 | G22: ='Regular DCF'!G20 -> -386 | H22: =($S22-$F22-$G22)*H11/SUM($H11:$I11) -> -331.58538 | I22: =($S22-$F22-$G22)*I11/SUM($H11:$I11) -> -364.41462 | J22: =$T22*J11/$T11 -> -307.40561 | K22: =$T22*K11/$T11 -> -348.74002 | L22: =$T22*L11/$T11 -> -381.53965 | M22: =$T22*M11/$T11 -> -419.31472 | N22: =$U22*N11/$U11 -> -336.09961 | O22: =$U22*O11/$U11 -> -381.29229 | P22: =$U22*P11/$U11 -> -417.15351 | Q22: =$U22*Q11/$U11 -> -458.4546 | S22: -1479 | T22: -1457 | U22: -1593
C23: Working capital, deposits and other | E23: Implied by consensus FCF | F23: ='Regular DCF'!F21+'Regular DCF'!F22+'Regular DCF'!F23 -> 4683 | G23: ='Regular DCF'!G21+'Regular DCF'!G22+'Regular DCF'!G23 -> 4896 | H23: =H25-(H20+H21+H22) -> -212.19638 | I23: =I25-(I20+I21+I22) -> -338.05362 | J23: =J25-(J20+J21+J22) -> 569.8394 | K23: =K25-(K20+K21+K22) -> 398.07603 | L23: =L25-(L20+L21+L22) -> 261.77861 | M23: =M25-(M20+M21+M22) -> 104.80596 | N23: =N25-(N20+N21+N22) -> 505.99228 | O23: =O25-(O20+O21+O22) -> 261.53905 | ... Q23: =Q25-(Q20+Q21+Q22) -> -155.84221 | S23: =SUM(F23:I23) -> 9028.75 | T23: =SUM(J23:M23) -> 1334.5 | U23: =SUM(N23:Q23) -> 679.25
C24: Unlevered free cash flow | F24: =F20+F21+F22+F23 -> 5043.25 | G24: =G20+G21+G22+G23 -> 5552 | H24: =H20+H21+H22+H23 -> 1059 | I24: =I20+I21+I22+I23 -> 1059 | J24: =J20+J21+J22+J23 -> 1847.25 | K24: =K20+K21+K22+K23 -> 1847.25 | L24: =L20+L21+L22+L23 -> 1847.25 | M24: =M20+M21+M22+M23 -> 1847.25 | ... Q24: =Q20+Q21+Q22+Q23 -> 2324 | S24: =SUM(F24:I24) -> 12713.25 | T24: =SUM(J24:M24) -> 7389 | U24: =SUM(N24:Q24) -> 9296
C25: Memo: consensus free cash flow | E25: H1 reported; rest split evenly | F25: ='GEV Quarterly'!J325 -> 4791 | G25: ='GEV Quarterly'!K325 -> 5106 | H25: =($S25-$F25-$G25)/2 -> 1059 | I25: =($S25-$F25-$G25)/2 -> 1059 | J25: =$T25/4 -> 1847.25 | K25: =$T25/4 -> 1847.25 | L25: =$T25/4 -> 1847.25 | M25: =$T25/4 -> 1847.25 | N25: =$U25/4 -> 2324 | O25: =$U25/4 -> 2324 | P25: =$U25/4 -> 2324 | Q25: =$U25/4 -> 2324 | S25: 12015 | T25: 7389 | U25: 9296
C27: Discount period (years) | E27: Mid-quarter, from 30-Jun-26 | H27: =(H$8-$N$36)/365-0.125 -> 0.12705479 | I27: =(I$8-$N$36)/365-0.125 -> 0.37910959 | J27: =(J$8-$N$36)/365-0.125 -> 0.62568493 | K27: =(K$8-$N$36)/365-0.125 -> 0.875 | L27: =(L$8-$N$36)/365-0.125 -> 1.1270548 | M27: =(M$8-$N$36)/365-0.125 -> 1.3791096 | N27: =(N$8-$N$36)/365-0.125 -> 1.6284247 | O27: =(O$8-$N$36)/365-0.125 -> 1.8777397 | ... Q27: =(Q$8-$N$36)/365-0.125 -> 2.3818493
C28: Discount factor | H28: =1/(1+$N$40)^H27 -> 0.98809383 | I28: =1/(1+$N$40)^I27 -> 0.96489197 | J28: =1/(1+$N$40)^J27 -> 0.94272176 | K28: =1/(1+$N$40)^K27 -> 0.9208231 | L28: =1/(1+$N$40)^L27 -> 0.89920085 | M28: =1/(1+$N$40)^M27 -> 0.87808632 | N28: =1/(1+$N$40)^N27 -> 0.85768908 | O28: =1/(1+$N$40)^O27 -> 0.83776566 | ... Q28: =1/(1+$N$40)^Q27 -> 0.7988837
C29: PV of UFCF | H29: =H24*H28 -> 1046.3914 | I29: =I24*I28 -> 1021.8206 | J29: =J24*J28 -> 1741.4428 | K29: =K24*K28 -> 1700.9905 | L29: =L24*L28 -> 1661.0488 | M29: =M24*M28 -> 1622.045 | N29: =N24*N28 -> 1993.2694 | O29: =O24*O28 -> 1946.9674 | ... Q29: =Q24*Q28 -> 1856.6057
C31: Valuation | K31: Inputs (from Regular DCF)
C32: Exit multiple (EV / FY2029E EBITDA) | E32: Next-12-month EBITDA at Dec-28 | F32: =$N$42 -> 20 | K32: Company | N32: ='Regular DCF'!N45 -> GE Vernova Inc.
C33: FY2029E EBITDA | F33: =V14 -> 14638.4 | K33: Ticker | N33: ='Regular DCF'!N46 -> NYSE:GEV
C34: Exit value, Dec-28 | F34: =F32*F33 -> 292768 | K34: Price ($) | N34: ='Regular DCF'!N47 -> 987.45
C35: Years from valuation date | F35: =(Q$8-$N$36)/365 -> 2.5068493 | K35: Price date | N35: ='Regular DCF'!N48 -> 46296
C36: Discount factor | F36: =1/(1+$N$40)^F35 -> 0.78952498 | K36: Valuation date | N36: ='Regular DCF'!N49 -> 46203
C37: PV of exit value | F37: =F34*F36 -> 231147.65 | K37: Shares, period end (mm) | N37: ='Regular DCF'!N50 -> 266.33358
C38: PV of UFCF, Q3'26 to Q4'28 | F38: =SUM(H29:Q29) -> 16491.831 | K38: Dilution (mm) | N38: ='Regular DCF'!N51 -> 2
C39: Enterprise value, 30-Jun-26 | F39: =F37+F38 -> 247639.48 | K39: Diluted shares (mm) | N39: ='Regular DCF'!N52 -> 268.33358
C40: Exit value % of EV | F40: =F37/F39 -> 0.93340387 | K40: WACC | N40: ='Regular DCF'!N53 -> 0.098857764
C41: Cash and restricted cash | E41: Jun-26 balance sheet | F41: ='GEV Quarterly'!K333 -> 13120 | K41: Cost of equity | N41: ='Regular DCF'!N54 -> 0.099728728
C42: Long-term borrowings | F42: =-'GEV Quarterly'!K353 -> -2794 | K42: Exit multiple | N42: ='Key Drivers'!$J$115 -> 20
C43: Noncontrolling interests | F43: =-'GEV Quarterly'!K365 -> -1158 | K43: Market cap ($mm) | N43: ='Regular DCF'!N56 -> 262991.09
C44: Pension and OPEB | F44: =-'GEV Quarterly'!K355 -> -2654 | K44: Market EV ($mm) | N44: ='Regular DCF'!N57 -> 255093.09
C45: Equity-method investments | F45: ='GEV Quarterly'!K344 -> 1384
C46: Equity value, 30-Jun-26 | F46: =F39+SUM(F41:F45) -> 255537.48
C47: Diluted shares (mm) | F47: =$N$39 -> 268.33358
C49: Value per share | F49: Now | G49: 3 months | H49: 6 months
C50: Date | F50: =$N$35 -> 46296 | G50: =EDATE($N$35,3) -> 46388 | H50: =EDATE($N$35,6) -> 46478
C51: Roll-forward at cost of equity | F51: =(1+$N$41)^((F50-$N$36)/365) -> 1.0245174 | G51: =(1+$N$41)^((G50-$N$36)/365) -> 1.0493626 | H51: =(1+$N$41)^((H50-$N$36)/365) -> 1.0742505
C52: Value per share ($) | F52: =$F$46*F51/$F$47 -> 975.66094 | G52: =$F$46*G51/$F$47 -> 999.3213 | H52: =$F$46*H51/$F$47 -> 1023.0224
C53: Current price ($) | F53: =$N$34 -> 987.45 | G53: =$N$34 -> 987.45 | H53: =$N$34 -> 987.45
C54: Upside / (downside) | F54: =F52/F53-1 -> -0.011938889 | G54: =G52/G53-1 -> 0.012022183 | H54: =H52/H53-1 -> 0.036024523
C56: Implied perpetuity growth | F56: =(F34*$N$40-U24)/(F34+U24) -> 0.065040487
C57: EV / FY2026E EBITDA, DCF | F57: =F39/S14 -> 39.152487
C58: EV / FY2026E EBITDA, market | F58: =$N$44/S14 -> 40.330924
C59: EV / FY2028E EBITDA, DCF | F59: =F39/U14 -> 18.947168
C60: EV / FY2028E EBITDA, market | F60: =$N$44/U14 -> 19.517452
C62: 6-month value per share ($): WACC vs exit multiple
E63: WACC (down) / multiple (across) | F63: =$N$42+-4 -> 16 | G63: =$N$42+-2 -> 18 | H63: =$N$42+0 -> 20 | I63: =$N$42+2 -> 22 | J63: =$N$42+4 -> 24
E64: =$N$40+-0.02 -> 0.078857764 | F64: =((SUMPRODUCT($H$24:$Q$24,(1+$E64)^(-$H$27:$Q$27))+F$63*$F$33*(1+$E64)^(-$F$35))+SUM($F$41:$F$45))*$H$51/$F$47 -> 874.51898 | G64: =((SUMPRODUCT($H$24:$Q$24,(1+$E64)^(-$H$27:$Q$27))+G$63*$F$33*(1+$E64)^(-$F$35))+SUM($F$41:$F$45))*$H$51/$F$47 -> 971.41767 | H64: =((SUMPRODUCT($H$24:$Q$24,(1+$E64)^(-$H$27:$Q$27))+H$63*$F$33*(1+$E64)^(-$F$35))+SUM($F$41:$F$45))*$H$51/$F$47 -> 1068.3164 | I64: =((SUMPRODUCT($H$24:$Q$24,(1+$E64)^(-$H$27:$Q$27))+I$63*$F$33*(1+$E64)^(-$F$35))+SUM($F$41:$F$45))*$H$51/$F$47 -> 1165.215 | J64: =((SUMPRODUCT($H$24:$Q$24,(1+$E64)^(-$H$27:$Q$27))+J$63*$F$33*(1+$E64)^(-$F$35))+SUM($F$41:$F$45))*$H$51/$F$47 -> 1262.1137
E65: =$N$40+-0.01 -> 0.088857764 | F65: =((SUMPRODUCT($H$24:$Q$24,(1+$E65)^(-$H$27:$Q$27))+F$63*$F$33*(1+$E65)^(-$F$35))+SUM($F$41:$F$45))*$H$51/$F$47 -> 855.94133 | G65: =((SUMPRODUCT($H$24:$Q$24,(1+$E65)^(-$H$27:$Q$27))+G$63*$F$33*(1+$E65)^(-$F$35))+SUM($F$41:$F$45))*$H$51/$F$47 -> 950.62456 | H65: =((SUMPRODUCT($H$24:$Q$24,(1+$E65)^(-$H$27:$Q$27))+H$63*$F$33*(1+$E65)^(-$F$35))+SUM($F$41:$F$45))*$H$51/$F$47 -> 1045.3078 | I65: =((SUMPRODUCT($H$24:$Q$24,(1+$E65)^(-$H$27:$Q$27))+I$63*$F$33*(1+$E65)^(-$F$35))+SUM($F$41:$F$45))*$H$51/$F$47 -> 1139.991 | J65: =((SUMPRODUCT($H$24:$Q$24,(1+$E65)^(-$H$27:$Q$27))+J$63*$F$33*(1+$E65)^(-$F$35))+SUM($F$41:$F$45))*$H$51/$F$47 -> 1234.6742
E66: =$N$40+0 -> 0.098857764 | F66: =((SUMPRODUCT($H$24:$Q$24,(1+$E66)^(-$H$27:$Q$27))+F$63*$F$33*(1+$E66)^(-$F$35))+SUM($F$41:$F$45))*$H$51/$F$47 -> 837.94645 | G66: =((SUMPRODUCT($H$24:$Q$24,(1+$E66)^(-$H$27:$Q$27))+G$63*$F$33*(1+$E66)^(-$F$35))+SUM($F$41:$F$45))*$H$51/$F$47 -> 930.48443 | H66: =((SUMPRODUCT($H$24:$Q$24,(1+$E66)^(-$H$27:$Q$27))+H$63*$F$33*(1+$E66)^(-$F$35))+SUM($F$41:$F$45))*$H$51/$F$47 -> 1023.0224 | I66: =((SUMPRODUCT($H$24:$Q$24,(1+$E66)^(-$H$27:$Q$27))+I$63*$F$33*(1+$E66)^(-$F$35))+SUM($F$41:$F$45))*$H$51/$F$47 -> 1115.5604 | J66: =((SUMPRODUCT($H$24:$Q$24,(1+$E66)^(-$H$27:$Q$27))+J$63*$F$33*(1+$E66)^(-$F$35))+SUM($F$41:$F$45))*$H$51/$F$47 -> 1208.0984
E67: =$N$40+0.01 -> 0.10885776 | F67: =((SUMPRODUCT($H$24:$Q$24,(1+$E67)^(-$H$27:$Q$27))+F$63*$F$33*(1+$E67)^(-$F$35))+SUM($F$41:$F$45))*$H$51/$F$47 -> 820.51095 | G67: =((SUMPRODUCT($H$24:$Q$24,(1+$E67)^(-$H$27:$Q$27))+G$63*$F$33*(1+$E67)^(-$F$35))+SUM($F$41:$F$45))*$H$51/$F$47 -> 910.97107 | H67: =((SUMPRODUCT($H$24:$Q$24,(1+$E67)^(-$H$27:$Q$27))+H$63*$F$33*(1+$E67)^(-$F$35))+SUM($F$41:$F$45))*$H$51/$F$47 -> 1001.4312 | I67: =((SUMPRODUCT($H$24:$Q$24,(1+$E67)^(-$H$27:$Q$27))+I$63*$F$33*(1+$E67)^(-$F$35))+SUM($F$41:$F$45))*$H$51/$F$47 -> 1091.8913 | J67: =((SUMPRODUCT($H$24:$Q$24,(1+$E67)^(-$H$27:$Q$27))+J$63*$F$33*(1+$E67)^(-$F$35))+SUM($F$41:$F$45))*$H$51/$F$47 -> 1182.3514
E68: =$N$40+0.02 -> 0.11885776 | F68: =((SUMPRODUCT($H$24:$Q$24,(1+$E68)^(-$H$27:$Q$27))+F$63*$F$33*(1+$E68)^(-$F$35))+SUM($F$41:$F$45))*$H$51/$F$47 -> 803.61256 | G68: =((SUMPRODUCT($H$24:$Q$24,(1+$E68)^(-$H$27:$Q$27))+G$63*$F$33*(1+$E68)^(-$F$35))+SUM($F$41:$F$45))*$H$51/$F$47 -> 892.05952 | H68: =((SUMPRODUCT($H$24:$Q$24,(1+$E68)^(-$H$27:$Q$27))+H$63*$F$33*(1+$E68)^(-$F$35))+SUM($F$41:$F$45))*$H$51/$F$47 -> 980.50647 | I68: =((SUMPRODUCT($H$24:$Q$24,(1+$E68)^(-$H$27:$Q$27))+I$63*$F$33*(1+$E68)^(-$F$35))+SUM($F$41:$F$45))*$H$51/$F$47 -> 1068.9534 | J68: =((SUMPRODUCT($H$24:$Q$24,(1+$E68)^(-$H$27:$Q$27))+J$63*$F$33*(1+$E68)^(-$F$35))+SUM($F$41:$F$45))*$H$51/$F$47 -> 1157.4004
C70: Street target ($) | F70: 1237
C71: 6-month DCF value vs Street target | F71: =H52/F70-1 -> -0.17298107
C72: Exit multiple the Street target needs | F72: =((F70*F47/H51-SUM(F41:F45))-F38)/(F36*F33) -> 24.624643

Sheet WACC Calculation
C2: GE Vernova (GEV)
C3: WACC
C4: Blue = input, black = formula, orange = assumption. Peer data as of 29-Sep to 2-Oct-26 (StockAnalysis). Debt and market cap in local currency, billions.
C8: Beta
C9: Unlevered beta = levered beta / (1 + D/E x (1 - tax))
C10: Company | D10: Ticker | E10: Currency | F10: Levered beta | G10: Tax rate | H10: Debt (bn) | I10: Market cap (bn) | J10: Debt / equity | K10: Unlevered beta
C11: Siemens Energy AG | D11: ETR:ENR | E11: EUR | F11: 1.87 | G11: 0.3 | H11: 2.96 | I11: 120.5 | J11: =H11/I11 -> 0.024564315 | K11: =F11/(1+J11*(1-G11)) -> 1.8383889
C12: Mitsubishi Heavy Industries | D12: TYO:7011 | E12: JPY | F12: 0.37 | G12: 0.3 | H12: 853.82 | I12: 12640 | J12: =H12/I12 -> 0.067549051 | K12: =F12/(1+J12*(1-G12)) -> 0.3532947
C13: GE Aerospace | D13: NYSE:GE | E13: USD | F13: 1.35 | G13: 0.25 | H13: 20.23 | I13: 324.12 | J13: =H13/I13 -> 0.062415155 | K13: =F13/(1+J13*(1-G13)) -> 1.2896306
C14: Eaton Corporation plc | D14: NYSE:ETN | E14: USD | F14: 1.13 | G14: 0.25 | H14: 21.33 | I14: 169.84 | J14: =H14/I14 -> 0.12558879 | K14: =F14/(1+J14*(1-G14)) -> 1.0327259
C15: Schneider Electric SE | D15: EPA:SU | E15: EUR | F15: 1.15 | G15: 0.25 | H15: 20.81 | I15: 164.2 | J15: =H15/I15 -> 0.12673569 | K15: =F15/(1+J15*(1-G15)) -> 1.0501787
C16: ABB Ltd | D16: SWX:ABBN | E16: CHF | F16: 1.01 | G16: 0.2 | H16: 7.39 | I16: 146.61 | J16: =H16/I16 -> 0.050405839 | K16: =F16/(1+J16*(1-G16)) -> 0.97085076
C17: Hitachi, Ltd. | D17: TYO:6501 | E17: JPY | F17: 0.54 | G17: 0.3 | H17: 1060 | I17: 24710 | J17: =H17/I17 -> 0.042897612 | K17: =F17/(1+J17*(1-G17)) -> 0.52425743
C18: Hubbell Incorporated | D18: NYSE:HUBB | E18: USD | F18: 0.89 | G18: 0.25 | H18: 5.56 | I18: 24.67 | J18: =H18/I18 -> 0.22537495 | K18: =F18/(1+J18*(1-G18)) -> 0.76131415
C19: Vertiv Holdings Co | D19: NYSE:VRT | E19: USD | F19: 2.07 | G19: 0.25 | H19: 3.34 | I19: 94.75 | J19: =H19/I19 -> 0.03525066 | K19: =F19/(1+J19*(1-G19)) -> 2.0166829
C20: Emerson Electric Co. | D20: NYSE:EMR | E20: USD | F20: 1.23 | G20: 0.25 | H20: 13.8 | I20: 88.45 | J20: =H20/I20 -> 0.15602035 | K20: =F20/(1+J20*(1-G20)) -> 1.1011488
C21: Quanta Services | D21: NYSE:PWR | E21: USD | F21: 1.27 | G21: 0.25 | H21: 6.6 | I21: 99.62 | J21: =H21/I21 -> 0.066251757 | K21: =F21/(1+J21*(1-G21)) -> 1.2098824
C23: Peer median | F23: =MEDIAN(F11:F21) -> 1.15 | G23: =MEDIAN(G11:G21) -> 0.25 | J23: =MEDIAN(J11:J21) -> 0.066251757 | K23: =MEDIAN(K11:K21) -> 1.0501787
C24: Peer mean | F24: =AVERAGE(F11:F21) -> 1.1709091 | G24: =AVERAGE(G11:G21) -> 0.25909091 | J24: =AVERAGE(J11:J21) -> 0.089368561 | K24: =AVERAGE(K11:K21) -> 1.1043959
C26: GE Vernova (relevered) | D26: NYSE:GEV | E26: USD | F26: 0.97 | G26: ='Key Drivers'!$H$124 -> 0.25 | H26: =E48/1000 -> 3.72 | I26: =E46/1000 -> 262.99109 | J26: =H26/I26 -> 0.014144966 | K26: =K23*(1+J26*(1-G26)) -> 1.0613197
C29: Cost of equity
C30: Risk-free rate (US 10-year) | E30: 0.0525
C31: Equity risk premium | E31: 0.0445
C32: Beta (relevered) | E32: =K26 -> 1.0613197
C33: Cost of equity | E33: =E30+E32*E31 -> 0.099728728
C34: Memo: using GEV observed beta | E34: =E30+F26*E31 -> 0.095665
C36: Cost of debt
C37: Notes issued Feb-26 | D37: Principal ($mm) | E37: Coupon
C38: 4.250% due 2031 | D38: 600 | E38: 0.0425
C39: 4.875% due 2036 | D39: 1000 | E39: 0.04875
C40: 5.500% due 2056 | D40: 1000 | E40: 0.055
C41: Pre-tax cost of debt | E41: =SUMPRODUCT(D38:D40,E38:E40)/SUM(D38:D40) -> 0.049711538
C42: Tax rate | E42: ='Key Drivers'!$H$124 -> 0.25
C43: After-tax cost of debt | E43: =E41*(1-E42) -> 0.037283654
C45: Capital structure
C46: Market capitalisation ($mm) | E46: ='Regular DCF'!$N$56 -> 262991.09
C47: % equity | E47: =E46/E50 -> 0.98605232
C48: Total debt incl. leases ($mm) | E48: 3720
C49: % debt | E49: =E48/E50 -> 0.013947676
C50: Total capital ($mm) | E50: =E46+E48 -> 266711.09
C52: WACC | E52: =E47*E33+E49*E43 -> 0.098857764
